Workbook
Name Akun: [1]Akun!$A$1:$G$65536
Name BLN: #REF!
Name BUKU_BESAR_HUTANG_DAGANG: 'Bk Hutang'!$A$5
Name BUKU_BESAR_INVENTARIS: #REF!
Name DAF_AKUN: Akun!$A:$G
Name DAF_KODE: Kode!$A:$F
Name DARKOD_BANTU: Kode!$B$10:$B$188
Name ERR: 'Data GL'!$O$4
Name Excel_BuiltIn__FilterDatabase_4: Jurnal!$F$8:$O$602
Name HPP: #REF!
Name Hugang: Kode!$B$11:$B$89
Name INVENTARIS: Kode!$B$146+Kode!$B$146:$B$170
Name JU_AKUN: Jurnal!$A:$O
Name JU_KODE: Jurnal!$C:$O
Name KENDARAAN: Kode!$B$173:$B$177
Name KKKKKKKKKKKK: [2]Akun!$B$10:$B$66
Name KODE: Kode!$A$10:$A$214
Name Nabantu: Kode!$B$10:$B$215
Name NAMA: #REF!
Name NAMA_BANTU: Kode!$B$10:$B$214
Name NamaAkun: Akun!$B$10:$B$116
Name NL: 'Neraca Lajur'!$A$1:$J$115
Name Nokun: Akun!$A$10:$A$116
Name not: '[1]Data GL'!#REF!
Name Pitgang: Kode!$B$91:$B$130
Name PIUTANG_DAGANG: Kode!$B$90
Name Tarkun: Akun!$A$10:$G$124
Name TGL: #REF!
Name THN: #REF!

Sheet Data GL
C3: GENERAL LEDGER
C4: Jenis Usaha | E4: PERCETAKAN | O4: =TRUE() -> TRUE
C5: Alamat | E5: JL. Prof Dr. Yohannes 1099 YK | O5: 43101
C6: Nama Pengusaha | E6: CV. SPEKTRA DIGITAL ARTWORK | O6: AND(NOW()>O5;NOW()<O6)
C7: Periode Pembukuan | E7: Jan
C8: Tahun Buku | E8: 2026

Sheet Kode
A1: ='[3]Data GL'!E6 -> CV. SPEKTRA DIGITAL ARTWORK
A2: ='[3]Data GL'!E4 -> PERCETAKAN
A3: ='[3]Data GL'!E5 -> JL. Prof Dr. Yohannes 1099 YK
A5: DAFTAR KODE PEMBANTU
A6: =CONCATENATE('[3]Data GL'!E7," -"," TAHUN"," ",'[3]Data GL'!E8) -> Jan - TAHUN 2026
A8: No | B8: Lawan Transaksi | E8: Kode | F8: Saldo Awal
B9: Nama | C9: NPWP | D9: Alamat
A10: A | B10: HUTANG DAGANG
A11: 1 | B11: Aneka Warna Indah, PT | C11: 0013041108073000 | E11: H-001 | F11: 89792000
A12: 2 | B12: Artha Inti Lestari, PT | C12: 0023419682036000 | E12: H-002 | F12: 5172600
A13: 3 | B13: Jaya Sejahtera, CV | C13: 0814248126543000 | E13: H-003 | F13: 3685010
A14: 4 | B14: Kurnia Jaya, CV | C14: 0026564468504000 | E14: H-004 | F14: 1295903
A15: 5 | B15: Mulia Mandiri Supply, PT | C15: 0027922004044000 | E15: H-005 | F15: 77920499
A16: 6 | B16: Multi Prima Karya Sejati, CV | C16: 0022311278085000 | E16: H-006 | F16: 2234427
A17: 7 | B17: Multiviscomindo, PT | C17: 0027962547062000 | E17: H-007 | F17: 231328247
A18: 8 | B18: Nusign Supply Indonesia, PT | C18: 0311882641418000 | E18: H-008 | F18: 522471950
A19: 9 | B19: Putra Mutiara Jaya, PT | C19: 0029132289424000 | E19: H-009 | F19: 32490018
A20: 10 | B20: Samafitro, PT | C20: 0013109087073000 | E20: H-010 | F20: 89698276
A21: 11 | B21: Tri Mitra Sejati, CV | C21: 0755762911503000 | E21: H-011 | F21: 1680025
A22: 12 | B22: Omega Garda Rupla, PT | C22: 0026450528543000 | E22: H-012
A23: 13 | B23: Mitra Abadi Jaya Mandiri, CV | C23: 0314894494541000 | E23: H-013
A24: 14 | B24: Attaya Global Visindo, PT | C24: 0835815531009000 | E24: H-014
A25: 15
A26: 16
A27: 17
A28: 18
A29: 19
A30: 20
A31: 21
A32: 22
A33: 23
A34: 24
A35: 25
A36: Jumlah | F36: =SUM(F11:F35) -> 1.057769e+09 | H36: 7.3942024e+09 | I36: selisih dgn yg dilapor SPT | J36: =H36-F36 -> 6336433416
A37: B | B37: PIUTANG DAGANG
A38: 1 | B38: Artindo Grafika Printing, PT | C38: 0025062092004000 | E38: P-001 | F38: 1231037841
A39: 2 | B39: CIPUTRA NUSA LESTARI | C39: 0736718511542000 | E39: P-002 | F39: 488400
A40: 3 | B40: CITRA JOGJA KREASI | C40: 0032926479542000 | E40: P-003 | F40: 7229541
A41: 4 | B41: DJARUM, PT | C41: 0012023974511000 | E41: P-004 | F41: 27152215
A42: 5 | B42: K-24 INDONESIA | C42: 0023694474541000 | E42: P-005 | F42: 12654
A43: 6 | B43: KARTIKA MUDA JAYA | C43: 0210008959542000 | E43: P-006 | F43: 5050056
A44: 7 | B44: MIROTA KSM | C44: 0011367331542000 | E44: P-007 | F44: 975579
A45: 8 | B45: NOX INDONESIA GAUNG GEMERLAP | C45: 0824228274541000 | E45: P-008 | F45: 7967358
A46: 9 | B46: ROTI KEHIDUPAN INDONESIA | C46: 0904115565541000 | E46: P-009 | F46: 688755
A47: 10 | B47: SUKSES MANDIRI | C47: 0758550131541000 | E47: P-010 | F47: 616383
A48: 11 | B48: WOOK GLOBAL TECHNOLOGY | C48: 0855776142041000 | E48: P-011 | F48: 521256
A49: 12 | B49: Pustaka Insan Madani, PT | C49: 0023984578542000 | E49: P-012
A50: 13 | B50: Cermin Jiwa Ilahi, PT | C50: 0755766318541000 | E50: P-013
A51: 14 | B51: Sumber Baru Land, PT | C51: 0022653869542000 | E51: P-014
A52: 15 | E52: P-015
A53: 16
A54: 17
A55: 18
A56: 19
A57: 20
A58: 21
A59: 22
A60: Jumlah | F60: =SUM(F38:F59) -> 1281740038 | H60: 1.28174e+09 | I60: sama | J60: =F60-H60 -> 0.4545455

Sheet Akun
A1: ='[3]Data GL'!E6 -> CV. SPEKTRA DIGITAL ARTWORK
A2: ='[3]Data GL'!E4 -> PERCETAKAN
A3: ='[3]Data GL'!E5 -> JL. Prof Dr. Yohannes 1099 YK
A5: DAFTAR AKUN
A6: =CONCATENATE('[3]Data GL'!E7," -"," TAHUN"," ",'[3]Data GL'!E8) -> Jan - TAHUN 2026
A8: Kode | B8: Nama Akun | C8: Pos | D8: Pos | F8: Saldo Awal | G8: Saldo Awal
A9: Akun | C9: Saldo | D9: Laporan | F9: Debet | G9: Kredit
A10: 10000 | B10: AKTIVA
A11: 11000 | B11: AKTIVA LANCAR
A12: 11100 | B12: Kas | C12: D | D12: NR | F12: 650389307
A13: 11101 | B13: Bank | C13: D | D13: NR
A14: 11102 | B14: Piutang Dagang | C14: D | D14: NR | F14: 1281740038
A15: 11103 | B15: Piutang Karyawan | C15: D | D15: NR
A16: 11200 | B16: Persediaan Barang Jadi | C16: D | D16: NR | F16: 1553000000
A17: 11300 | B17: Persediaan Barang Proses | C17: D | D17: NR
A18: 11301 | B18: Persediaan Bahan Baku | C18: D | D18: NR | F18: 10187858027
A19: 11400 | B19: Persediaan Bahan Penolong | C19: D | D19: NR
A20: 11401 | B20: Persediaan Lain-lain | C20: D | D20: NR
A21: 11402 | B21: Ppn Dibayar dimuka | C21: D | D21: NR
A22: 11403 | B22: Pph Pasal 23 | C22: D | D22: NR
A23: 11500 | B23: Pph Pasal 25 | C23: D | D23: NR
A24: 11600 | B24: PPN Masukan | C24: D | D24: NR
A25: 11700 | B25: Uang Muka Pembelian | C25: D | D25: NR
A26: 11800 | B26: Uang Muka Sewa | C26: D | D26: NR
A27: 12000 | B27: AKTIVA TETAP
A28: 12100 | B28: Gedung dan Listrik | C28: D | D28: NR | F28: =166591000-118001958 -> 48589042
A29: 12200 | B29: Peralatan Pabrik | C29: D | D29: NR | F29: =10909833758-4657711650 -> 6252122108
A30: 12300 | B30: Peralatan Kantor | C30: D | D30: NR | F30: =910637468-701727855 -> 208909613
A31: 12400 | B31: Kendaraan | C31: D | D31: NR
A32: 12500 | B32: Investaris Kantor | C32: D | D32: NR
A33: 12601 | B33: Akm. Penyusutan Bangunan | C33: D | D33: NR
A34: 12602 | B34: Akm. Penyusutan Mesin | C34: D | D34: NR
A35: 12603 | B35: Akm. Penyusutan Peralatan Kantor | C35: D | D35: NR
A36: 12604 | B36: Akm. Penyusutan Kendaraan | C36: D | D36: NR
A37: 12605 | B37: Akm. | C37: D | D37: NR
A38: 20000 | B38: KEWAJIBAN
A39: 21100 | B39: Hutang Dagang | C39: K | D39: NR | G39: 7162874124
A40: 22101 | B40: Hutang Pph Final PP 46 | C40: K | D40: NR | G40: 31589467
A41: 22102 | B41: Hutang Pph Pasal 23 | C41: K | D41: NR
A42: 22103 | B42: Hutang Pph Pasal 4(2) | C42: K | D42: NR
A43: 22104 | B43: Hutang Pph Pasal 25/29 | C43: K | D43: NR
A44: 22105 | B44: PPN Keluaran | C44: K | D44: NR
A45: 23100 | B45: Hutang Bank | C45: K | D45: NR
A46: 24100 | B46: Hutang Biaya | C46: K | D46: NR
A47: 25100 | B47: Hutang Lain-lain | C47: K | D47: NR
A48: 26100 | B48: Hutang Pemegang Saham | C48: K | D48: NR
A49: 27100 | B49: Uang Muka Penjualan | C49: K | D49: NR
A50: 30000 | B50: EKUITAS
A51: 31000 | B51: Modal | C51: K | D51: NR | G51: 11488144544
A52: 32000 | B52: Laba Ditahan Amnesty | C52: K | D52: NR | G52: 1500000000
A53: 33000 | B53: Prive | C53: D | D53: LR
A54: 34000 | B54: Pajak Penghasilan | C54: D | D54: LR
A55: 40000 | B55: PENDAPATAN
A56: 41000 | B56: Penjualan Barang | C56: K | D56: LR
A57: 41001 | B57: Retur Penjualan Barang | C57: K | D57: LR
A58: 41002 | B58: Pendapatan Lain-lain | C58: K | D58: LR
A59: 50000 | B59: HARGA POKOK PENJUALAN
A60: 51000 | B60: Persediaan Bahan Baku Awal | C60: D | D60: LR
A61: 52000 | B61: Persediaan Bahan Baku Akhir | C61: D | D61: LR
A62: 53000 | B62: Pembelian Bahan Baku | C62: D | D62: LR
A63: 53001 | B63: Persediaan Bahan Penolong Awal | C63: D | D63: LR
A64: 53002 | B64: Persediaan Bahan Penolong Akhir | C64: D | D64: LR
A65: 53003 | B65: Pembelian Bahan Penolong | C65: D | D65: LR
A66: 53004 | B66: Tenaga Kerja Langsung | C66: D | D66: LR
A67: 53005 | B67: Biaya Listrik | C67: D | D67: LR
A68: 60000 | B68: BIAYA OPERASIONAL
A69: 61000 | B69: BIAYA MANAJEMEN :
A70: 61001 | B70: Gaji & Tunjangan | C70: D | D70: LR
A71: 61002 | B71: Asuransi Tenaga Kerja | C71: D | D71: LR
A72: 61003 | B72: Perjalanan Dinas | C72: D | D72: LR
A73: 61004 | B73: Biaya Konsultan Pajak | C73: D | D73: LR
A74: 62000 | B74: BIAYA PENJUALAN :
A75: 62001 | B75: Ongkos Kirim | C75: D | D75: LR
A76: 62002 | B76: BBM dan Parkir | C76: D | D76: LR
A77: 62003 | B77: Pamflet & Brosur | C77: D | D77: LR
A78: 63000 | B78: BIAYA UMUM & ADMINISTRASI :
A79: 63001 | B79: Penyusutan | C79: D | D79: LR
A80: 63002 | B80: Telepon | C80: D | D80: LR
A81: 63003 | B81: Internet | C81: D | D81: LR
A82: 63004 | B82: Listrik & Air | C82: D | D82: LR
A83: 63005 | B83: Rapat/Pelatihan Karyawan | C83: D | D83: LR
A84: 63006 | B84: Perlengkapan Kantor | C84: D | D84: LR
A85: 63007 | B85: Administrasi Kantor (ATK) | C85: D | D85: LR
A86: 63008 | B86: Biaya Brosur, dan Pamflet | C86: D | D86: LR
A87: 63009 | B87: Pajak Kendaraan & Retribusi | C87: D | D87: LR
A88: 63010 | B88: Paket/Kurir | C88: D | D88: LR
A89: 63011 | B89: Materai & Benda Pos | C89: D | D89: LR
A90: 63012 | B90: Biaya Sparepart Investaris | C90: D | D90: LR
... A96: 64002 | B96: Biaya Administrasi Bank | C96: D | D96: LR
A97: 70000 | B97: PENDAPATAN & BIAYA LAIN-LAIN
A98: 71000 | B98: Penghasilan klain asuransi | C98: K | D98: LR
A99: 72000 | B99: Bunga Bank/ Jasa Giro | C99: K | D99: LR
A100: 73000 | B100: Selisih Kurs | C100: K | D100: LR
A101: 74000 | B101: Biaya Lain-lain diluar usaha | C101: K | D101: LR
B105: JUMLAH | F105: =SUM(F10:F104) -> 20182608135 | G105: =SUM(G10:G104) -> 20182608135 | I105: =SUM(I10:I104) -> 0 | J105: =SUM(J10:J104) -> 0
G108: =F105-G105 -> 0
G109: 20182608135
G110: =G109-G105 -> 0
G112: =G33+G34+G35 -> 0

Sheet Ledger
A1: ='Data GL'!E6 -> CV. SPEKTRA DIGITAL ARTWORK
A2: ='Data GL'!E4 -> PERCETAKAN
A3: ='Data GL'!E5 -> JL. Prof Dr. Yohannes 1099 YK
A5: BUKU BESAR
A6: =CONCATENATE('Data GL'!E7," -"," TAHUN"," ",'Data GL'!E8) -> Jan - TAHUN 2026
B8: =UPPER(IF(H9=0,"",VLOOKUP(H9,Tarkun,2,0))) -> PERSEDIAAN BAHAN PENOLONG
G9: 11801 | H9: 11400
A12: No | B12: Tanggal | C12: =VLOOKUP(H9,DAF_AKUN,3,FALSE) -> D | D12: Bukti | E12: Keterangan | F12: Debet | G12: Kredit | H12: Saldo
E13: Saldo Awal | F13: =IF($C$12="D",VLOOKUP(H9,DAF_AKUN,6,FALSE)+VLOOKUP(H9,DAF_AKUN,7,FALSE),0) -> 0 | G13: =IF($C$12="D",0,VLOOKUP(H9,DAF_AKUN,6,FALSE)+VLOOKUP(H9,DAF_AKUN,7,FALSE)) -> 0 | H13: =SUM(F13:G13) -> 0
A14: =A13+1 -> 1 | B14: =IF(ISERROR(VLOOKUP(A14&H$9,JU_AKUN,6,FALSE)=TRUE),"",VLOOKUP(A14&H$9,JU_AKUN,6,FALSE)) | C14: =IF(ISERROR(VLOOKUP(A14&H$9,JU_AKUN,7,FALSE)=TRUE),"",VLOOKUP(A14&H$9,JU_AKUN,7,FALSE)) | D14: =IF(ISERROR(VLOOKUP(A14&H$9,JU_AKUN,8,FALSE)=TRUE),"",VLOOKUP(A14&H$9,JU_AKUN,8,FALSE)) | E14: =IF(ISERROR(VLOOKUP(A14&H$9,JU_AKUN,9,FALSE)=TRUE),"",VLOOKUP(A14&H$9,JU_AKUN,9,FALSE)) | F14: =IF(ISERROR(VLOOKUP(A14&H$9,JU_AKUN,14,FALSE)=TRUE),"",VLOOKUP(A14&H$9,JU_AKUN,14,FALSE)) | G14: =IF(ISERROR(VLOOKUP(A14&H$9,JU_AKUN,15,FALSE)=TRUE),"",VLOOKUP(A14&H$9,JU_AKUN,15,FALSE)) | H14: =IF(OR(ERR=FALSE,AND(F14="",G14="")),0,IF($C$12="D",$H$13+SUM($F$14:F14)-SUM($G$14:G14),$H$13-SUM($F$14:F14)+SUM($G$14:G14))) -> 0
A15: =A14+1 -> 2 | B15: =IF(ISERROR(VLOOKUP(A15&H$9,JU_AKUN,6,FALSE)=TRUE),"",VLOOKUP(A15&H$9,JU_AKUN,6,FALSE)) | C15: =IF(ISERROR(VLOOKUP(A15&H$9,JU_AKUN,7,FALSE)=TRUE),"",VLOOKUP(A15&H$9,JU_AKUN,7,FALSE)) | D15: =IF(ISERROR(VLOOKUP(A15&H$9,JU_AKUN,8,FALSE)=TRUE),"",VLOOKUP(A15&H$9,JU_AKUN,8,FALSE)) | E15: =IF(ISERROR(VLOOKUP(A15&H$9,JU_AKUN,9,FALSE)=TRUE),"",VLOOKUP(A15&H$9,JU_AKUN,9,FALSE)) | F15: =IF(ISERROR(VLOOKUP(A15&H$9,JU_AKUN,14,FALSE)=TRUE),"",VLOOKUP(A15&H$9,JU_AKUN,14,FALSE)) | G15: =IF(ISERROR(VLOOKUP(A15&H$9,JU_AKUN,15,FALSE)=TRUE),"",VLOOKUP(A15&H$9,JU_AKUN,15,FALSE)) | H15: =IF(OR(ERR=FALSE,AND(F15="",G15="")),0,IF($C$12="D",$H$13+SUM($F$14:F15)-SUM($G$14:G15),$H$13-SUM($F$14:F15)+SUM($G$14:G15))) -> 0
A16: =A15+1 -> 3 | B16: =IF(ISERROR(VLOOKUP(A16&H$9,JU_AKUN,6,FALSE)=TRUE),"",VLOOKUP(A16&H$9,JU_AKUN,6,FALSE)) | C16: =IF(ISERROR(VLOOKUP(A16&H$9,JU_AKUN,7,FALSE)=TRUE),"",VLOOKUP(A16&H$9,JU_AKUN,7,FALSE)) | D16: =IF(ISERROR(VLOOKUP(A16&H$9,JU_AKUN,8,FALSE)=TRUE),"",VLOOKUP(A16&H$9,JU_AKUN,8,FALSE)) | E16: =IF(ISERROR(VLOOKUP(A16&H$9,JU_AKUN,9,FALSE)=TRUE),"",VLOOKUP(A16&H$9,JU_AKUN,9,FALSE)) | F16: =IF(ISERROR(VLOOKUP(A16&H$9,JU_AKUN,14,FALSE)=TRUE),"",VLOOKUP(A16&H$9,JU_AKUN,14,FALSE)) | G16: =IF(ISERROR(VLOOKUP(A16&H$9,JU_AKUN,15,FALSE)=TRUE),"",VLOOKUP(A16&H$9,JU_AKUN,15,FALSE)) | H16: =IF(OR(ERR=FALSE,AND(F16="",G16="")),0,IF($C$12="D",$H$13+SUM($F$14:F16)-SUM($G$14:G16),$H$13-SUM($F$14:F16)+SUM($G$14:G16))) -> 0
A17: =A16+1 -> 4 | B17: =IF(ISERROR(VLOOKUP(A17&H$9,JU_AKUN,6,FALSE)=TRUE),"",VLOOKUP(A17&H$9,JU_AKUN,6,FALSE)) | C17: =IF(ISERROR(VLOOKUP(A17&H$9,JU_AKUN,7,FALSE)=TRUE),"",VLOOKUP(A17&H$9,JU_AKUN,7,FALSE)) | D17: =IF(ISERROR(VLOOKUP(A17&H$9,JU_AKUN,8,FALSE)=TRUE),"",VLOOKUP(A17&H$9,JU_AKUN,8,FALSE)) | E17: =IF(ISERROR(VLOOKUP(A17&H$9,JU_AKUN,9,FALSE)=TRUE),"",VLOOKUP(A17&H$9,JU_AKUN,9,FALSE)) | F17: =IF(ISERROR(VLOOKUP(A17&H$9,JU_AKUN,14,FALSE)=TRUE),"",VLOOKUP(A17&H$9,JU_AKUN,14,FALSE)) | G17: =IF(ISERROR(VLOOKUP(A17&H$9,JU_AKUN,15,FALSE)=TRUE),"",VLOOKUP(A17&H$9,JU_AKUN,15,FALSE)) | H17: =IF(OR(ERR=FALSE,AND(F17="",G17="")),0,IF($C$12="D",$H$13+SUM($F$14:F17)-SUM($G$14:G17),$H$13-SUM($F$14:F17)+SUM($G$14:G17))) -> 0
A18: =A17+1 -> 5 | B18: =IF(ISERROR(VLOOKUP(A18&H$9,JU_AKUN,6,FALSE)=TRUE),"",VLOOKUP(A18&H$9,JU_AKUN,6,FALSE)) | C18: =IF(ISERROR(VLOOKUP(A18&H$9,JU_AKUN,7,FALSE)=TRUE),"",VLOOKUP(A18&H$9,JU_AKUN,7,FALSE)) | D18: =IF(ISERROR(VLOOKUP(A18&H$9,JU_AKUN,8,FALSE)=TRUE),"",VLOOKUP(A18&H$9,JU_AKUN,8,FALSE)) | E18: =IF(ISERROR(VLOOKUP(A18&H$9,JU_AKUN,9,FALSE)=TRUE),"",VLOOKUP(A18&H$9,JU_AKUN,9,FALSE)) | F18: =IF(ISERROR(VLOOKUP(A18&H$9,JU_AKUN,14,FALSE)=TRUE),"",VLOOKUP(A18&H$9,JU_AKUN,14,FALSE)) | G18: =IF(ISERROR(VLOOKUP(A18&H$9,JU_AKUN,15,FALSE)=TRUE),"",VLOOKUP(A18&H$9,JU_AKUN,15,FALSE)) | H18: =IF(OR(ERR=FALSE,AND(F18="",G18="")),0,IF($C$12="D",$H$13+SUM($F$14:F18)-SUM($G$14:G18),$H$13-SUM($F$14:F18)+SUM($G$14:G18))) -> 0
A19: =A18+1 -> 6 | B19: =IF(ISERROR(VLOOKUP(A19&H$9,JU_AKUN,6,FALSE)=TRUE),"",VLOOKUP(A19&H$9,JU_AKUN,6,FALSE)) | C19: =IF(ISERROR(VLOOKUP(A19&H$9,JU_AKUN,7,FALSE)=TRUE),"",VLOOKUP(A19&H$9,JU_AKUN,7,FALSE)) | D19: =IF(ISERROR(VLOOKUP(A19&H$9,JU_AKUN,8,FALSE)=TRUE),"",VLOOKUP(A19&H$9,JU_AKUN,8,FALSE)) | E19: =IF(ISERROR(VLOOKUP(A19&H$9,JU_AKUN,9,FALSE)=TRUE),"",VLOOKUP(A19&H$9,JU_AKUN,9,FALSE)) | F19: =IF(ISERROR(VLOOKUP(A19&H$9,JU_AKUN,14,FALSE)=TRUE),"",VLOOKUP(A19&H$9,JU_AKUN,14,FALSE)) | G19: =IF(ISERROR(VLOOKUP(A19&H$9,JU_AKUN,15,FALSE)=TRUE),"",VLOOKUP(A19&H$9,JU_AKUN,15,FALSE)) | H19: =IF(OR(ERR=FALSE,AND(F19="",G19="")),0,IF($C$12="D",$H$13+SUM($F$14:F19)-SUM($G$14:G19),$H$13-SUM($F$14:F19)+SUM($G$14:G19))) -> 0
A20: =A19+1 -> 7 | B20: =IF(ISERROR(VLOOKUP(A20&H$9,JU_AKUN,6,FALSE)=TRUE),"",VLOOKUP(A20&H$9,JU_AKUN,6,FALSE)) | C20: =IF(ISERROR(VLOOKUP(A20&H$9,JU_AKUN,7,FALSE)=TRUE),"",VLOOKUP(A20&H$9,JU_AKUN,7,FALSE)) | D20: =IF(ISERROR(VLOOKUP(A20&H$9,JU_AKUN,8,FALSE)=TRUE),"",VLOOKUP(A20&H$9,JU_AKUN,8,FALSE)) | E20: =IF(ISERROR(VLOOKUP(A20&H$9,JU_AKUN,9,FALSE)=TRUE),"",VLOOKUP(A20&H$9,JU_AKUN,9,FALSE)) | F20: =IF(ISERROR(VLOOKUP(A20&H$9,JU_AKUN,14,FALSE)=TRUE),"",VLOOKUP(A20&H$9,JU_AKUN,14,FALSE)) | G20: =IF(ISERROR(VLOOKUP(A20&H$9,JU_AKUN,15,FALSE)=TRUE),"",VLOOKUP(A20&H$9,JU_AKUN,15,FALSE)) | H20: =IF(OR(ERR=FALSE,AND(F20="",G20="")),0,IF($C$12="D",$H$13+SUM($F$14:F20)-SUM($G$14:G20),$H$13-SUM($F$14:F20)+SUM($G$14:G20))) -> 0
A21: =A20+1 -> 8 | B21: =IF(ISERROR(VLOOKUP(A21&H$9,JU_AKUN,6,FALSE)=TRUE),"",VLOOKUP(A21&H$9,JU_AKUN,6,FALSE)) | C21: =IF(ISERROR(VLOOKUP(A21&H$9,JU_AKUN,7,FALSE)=TRUE),"",VLOOKUP(A21&H$9,JU_AKUN,7,FALSE)) | D21: =IF(ISERROR(VLOOKUP(A21&H$9,JU_AKUN,8,FALSE)=TRUE),"",VLOOKUP(A21&H$9,JU_AKUN,8,FALSE)) | E21: =IF(ISERROR(VLOOKUP(A21&H$9,JU_AKUN,9,FALSE)=TRUE),"",VLOOKUP(A21&H$9,JU_AKUN,9,FALSE)) | F21: =IF(ISERROR(VLOOKUP(A21&H$9,JU_AKUN,14,FALSE)=TRUE),"",VLOOKUP(A21&H$9,JU_AKUN,14,FALSE)) | G21: =IF(ISERROR(VLOOKUP(A21&H$9,JU_AKUN,15,FALSE)=TRUE),"",VLOOKUP(A21&H$9,JU_AKUN,15,FALSE)) | H21: =IF(OR(ERR=FALSE,AND(F21="",G21="")),0,IF($C$12="D",$H$13+SUM($F$14:F21)-SUM($G$14:G21),$H$13-SUM($F$14:F21)+SUM($G$14:G21))) -> 0
A22: =A21+1 -> 9 | B22: =IF(ISERROR(VLOOKUP(A22&H$9,JU_AKUN,6,FALSE)=TRUE),"",VLOOKUP(A22&H$9,JU_AKUN,6,FALSE)) | C22: =IF(ISERROR(VLOOKUP(A22&H$9,JU_AKUN,7,FALSE)=TRUE),"",VLOOKUP(A22&H$9,JU_AKUN,7,FALSE)) | D22: =IF(ISERROR(VLOOKUP(A22&H$9,JU_AKUN,8,FALSE)=TRUE),"",VLOOKUP(A22&H$9,JU_AKUN,8,FALSE)) | E22: =IF(ISERROR(VLOOKUP(A22&H$9,JU_AKUN,9,FALSE)=TRUE),"",VLOOKUP(A22&H$9,JU_AKUN,9,FALSE)) | F22: =IF(ISERROR(VLOOKUP(A22&H$9,JU_AKUN,14,FALSE)=TRUE),"",VLOOKUP(A22&H$9,JU_AKUN,14,FALSE)) | G22: =IF(ISERROR(VLOOKUP(A22&H$9,JU_AKUN,15,FALSE)=TRUE),"",VLOOKUP(A22&H$9,JU_AKUN,15,FALSE)) | H22: =IF(OR(ERR=FALSE,AND(F22="",G22="")),0,IF($C$12="D",$H$13+SUM($F$14:F22)-SUM($G$14:G22),$H$13-SUM($F$14:F22)+SUM($G$14:G22))) -> 0
A23: =A22+1 -> 10 | B23: =IF(ISERROR(VLOOKUP(A23&H$9,JU_AKUN,6,FALSE)=TRUE),"",VLOOKUP(A23&H$9,JU_AKUN,6,FALSE)) | C23: =IF(ISERROR(VLOOKUP(A23&H$9,JU_AKUN,7,FALSE)=TRUE),"",VLOOKUP(A23&H$9,JU_AKUN,7,FALSE)) | D23: =IF(ISERROR(VLOOKUP(A23&H$9,JU_AKUN,8,FALSE)=TRUE),"",VLOOKUP(A23&H$9,JU_AKUN,8,FALSE)) | E23: =IF(ISERROR(VLOOKUP(A23&H$9,JU_AKUN,9,FALSE)=TRUE),"",VLOOKUP(A23&H$9,JU_AKUN,9,FALSE)) | F23: =IF(ISERROR(VLOOKUP(A23&H$9,JU_AKUN,14,FALSE)=TRUE),"",VLOOKUP(A23&H$9,JU_AKUN,14,FALSE)) | G23: =IF(ISERROR(VLOOKUP(A23&H$9,JU_AKUN,15,FALSE)=TRUE),"",VLOOKUP(A23&H$9,JU_AKUN,15,FALSE)) | H23: =IF(OR(ERR=FALSE,AND(F23="",G23="")),0,IF($C$12="D",$H$13+SUM($F$14:F23)-SUM($G$14:G23),$H$13-SUM($F$14:F23)+SUM($G$14:G23))) -> 0
A24: =A23+1 -> 11 | B24: =IF(ISERROR(VLOOKUP(A24&H$9,JU_AKUN,6,FALSE)=TRUE),"",VLOOKUP(A24&H$9,JU_AKUN,6,FALSE)) | C24: =IF(ISERROR(VLOOKUP(A24&H$9,JU_AKUN,7,FALSE)=TRUE),"",VLOOKUP(A24&H$9,JU_AKUN,7,FALSE)) | D24: =IF(ISERROR(VLOOKUP(A24&H$9,JU_AKUN,8,FALSE)=TRUE),"",VLOOKUP(A24&H$9,JU_AKUN,8,FALSE)) | E24: =IF(ISERROR(VLOOKUP(A24&H$9,JU_AKUN,9,FALSE)=TRUE),"",VLOOKUP(A24&H$9,JU_AKUN,9,FALSE)) | F24: =IF(ISERROR(VLOOKUP(A24&H$9,JU_AKUN,14,FALSE)=TRUE),"",VLOOKUP(A24&H$9,JU_AKUN,14,FALSE)) | G24: =IF(ISERROR(VLOOKUP(A24&H$9,JU_AKUN,15,FALSE)=TRUE),"",VLOOKUP(A24&H$9,JU_AKUN,15,FALSE)) | H24: =IF(OR(ERR=FALSE,AND(F24="",G24="")),0,IF($C$12="D",$H$13+SUM($F$14:F24)-SUM($G$14:G24),$H$13-SUM($F$14:F24)+SUM($G$14:G24))) -> 0
A25: =A24+1 -> 12 | B25: =IF(ISERROR(VLOOKUP(A25&H$9,JU_AKUN,6,FALSE)=TRUE),"",VLOOKUP(A25&H$9,JU_AKUN,6,FALSE)) | C25: =IF(ISERROR(VLOOKUP(A25&H$9,JU_AKUN,7,FALSE)=TRUE),"",VLOOKUP(A25&H$9,JU_AKUN,7,FALSE)) | D25: =IF(ISERROR(VLOOKUP(A25&H$9,JU_AKUN,8,FALSE)=TRUE),"",VLOOKUP(A25&H$9,JU_AKUN,8,FALSE)) | E25: =IF(ISERROR(VLOOKUP(A25&H$9,JU_AKUN,9,FALSE)=TRUE),"",VLOOKUP(A25&H$9,JU_AKUN,9,FALSE)) | F25: =IF(ISERROR(VLOOKUP(A25&H$9,JU_AKUN,14,FALSE)=TRUE),"",VLOOKUP(A25&H$9,JU_AKUN,14,FALSE)) | G25: =IF(ISERROR(VLOOKUP(A25&H$9,JU_AKUN,15,FALSE)=TRUE),"",VLOOKUP(A25&H$9,JU_AKUN,15,FALSE)) | H25: =IF(OR(ERR=FALSE,AND(F25="",G25="")),0,IF($C$12="D",$H$13+SUM($F$14:F25)-SUM($G$14:G25),$H$13-SUM($F$14:F25)+SUM($G$14:G25))) -> 0
... A8459: =A8458+1 -> 8446 | B8459: =IF(ISERROR(VLOOKUP(A8459&H$9,JU_AKUN,6,FALSE)=TRUE),"",VLOOKUP(A8459&H$9,JU_AKUN,6,FALSE)) | C8459: =IF(ISERROR(VLOOKUP(A8459&H$9,JU_AKUN,7,FALSE)=TRUE),"",VLOOKUP(A8459&H$9,JU_AKUN,7,FALSE)) | D8459: =IF(ISERROR(VLOOKUP(A8459&H$9,JU_AKUN,8,FALSE)=TRUE),"",VLOOKUP(A8459&H$9,JU_AKUN,8,FALSE)) | E8459: =IF(ISERROR(VLOOKUP(A8459&H$9,JU_AKUN,9,FALSE)=TRUE),"",VLOOKUP(A8459&H$9,JU_AKUN,9,FALSE)) | F8459: =IF(ISERROR(VLOOKUP(A8459&H$9,JU_AKUN,14,FALSE)=TRUE),"",VLOOKUP(A8459&H$9,JU_AKUN,14,FALSE)) | G8459: =IF(ISERROR(VLOOKUP(A8459&H$9,JU_AKUN,15,FALSE)=TRUE),"",VLOOKUP(A8459&H$9,JU_AKUN,15,FALSE)) | H8459: =IF(OR(ERR=FALSE,AND(F8459="",G8459="")),0,IF($C$12="D",$H$13+SUM($F$14:F8459)-SUM($G$14:G8459),$H$13-SUM($F$14:F8459)+SUM($G$14:G8459))) -> 0
F8460: =SUM(F1:F8258) -> 0 | G8460: =SUM(G1:G8258) -> 11801 | H8460: =+F8460-G8460 -> -11801

Sheet Jurnal
F1: ='Data GL'!E6 -> CV. SPEKTRA DIGITAL ARTWORK
F2: ='Data GL'!E4 -> PERCETAKAN
F3: ='Data GL'!E5 -> JL. Prof Dr. Yohannes 1099 YK
F5: JURNAL UMUM
F6: =CONCATENATE('Data GL'!E7," -"," TAHUN"," ",'Data GL'!E8) -> Jan - TAHUN 2026
A7: -
A8: Akun | B8: Akun | C8: Bantu | D8: Bantu | F8: Tanggal | H8: Bukti | I8: Keterangan | J8: Nama Akun | K8: Kode | L8: Nama Akun Pembantu | M8: Kode | N8: Debet | O8: Kredit | P8: Indikator
A9: 1 | B9: 2 | C9: 1 | D9: 2 | K9: Akun | M9: Bantu
A10: =B10&K10 -> 111100 | B10: =IF(ERR=TRUE,COUNTIF($K$10:K10,K10),0) -> 1 | C10: =D10&M10 -> 1 | D10: =IF(ERR=FALSE,0,COUNTIF($M$10:M10,M10)) -> 1 | F10: 46023 | G10: 2 | I10: Penjualan Retail | J10: =IF(K10=0,"",VLOOKUP(K10,Tarkun,2,0)) -> Kas | K10: 11100 | M10: =IF(L10=0," ",(VLOOKUP(L10,Kode!$B$10:$E$423,4,0))) | N10: 9301100 | P10: =IF(K10="","",IF(AND(K10>0,$M$602=0),"Balance","Unbalance")) -> Balance
A11: =B11&K11 -> 122105 | B11: =IF(ERR=TRUE,COUNTIF($K$10:K11,K11),0) -> 1 | C11: =D11&M11 -> 2 | D11: =IF(ERR=FALSE,0,COUNTIF($M$10:M11,M11)) -> 2 | F11: 46024 | G11: 2 | I11: Penjualan Retail | J11: =IF(K11=0,"",VLOOKUP(K11,Tarkun,2,0)) -> PPN Keluaran | K11: 22105 | M11: =IF(L11=0," ",(VLOOKUP(L11,Kode!$B$10:$E$423,4,0))) | O11: 921730.63 | P11: =IF(K11="","",IF(AND(K11>0,$M$602=0),"Balance","Unbalance")) -> Balance
A12: =B12&K12 -> 141000 | B12: =IF(ERR=TRUE,COUNTIF($K$10:K12,K12),0) -> 1 | C12: =D12&M12 -> 3 | D12: =IF(ERR=FALSE,0,COUNTIF($M$10:M12,M12)) -> 3 | F12: 46025 | G12: 2 | I12: Penjualan Retail | J12: =IF(K12=0,"",VLOOKUP(K12,Tarkun,2,0)) -> Penjualan Barang | K12: 41000 | M12: =IF(L12=0," ",(VLOOKUP(L12,Kode!$B$10:$E$423,4,0))) | O12: 8379369.4 | P12: =IF(K12="","",IF(AND(K12>0,$M$602=0),"Balance","Unbalance")) -> Balance
A13: =B13&K13 -> 0 | B13: =IF(ERR=TRUE,COUNTIF($K$10:K13,K13),0) -> 0 | C13: =D13&M13 -> 4 | D13: =IF(ERR=FALSE,0,COUNTIF($M$10:M13,M13)) -> 4 | F13: 46051 | J13: =IF(K13=0,"",VLOOKUP(K13,Tarkun,2,0)) | M13: =IF(L13=0," ",(VLOOKUP(L13,Kode!$B$10:$E$423,4,0))) | O13: 0 | P13: =IF(K13="","",IF(AND(K13>0,$M$602=0),"Balance","Unbalance"))
A14: =B14&K14 -> 211100 | B14: =IF(ERR=TRUE,COUNTIF($K$10:K14,K14),0) -> 2 | C14: =D14&M14 -> 5 | D14: =IF(ERR=FALSE,0,COUNTIF($M$10:M14,M14)) -> 5 | F14: 46023 | G14: 3 | I14: Penjualan Retail | J14: =IF(K14=0,"",VLOOKUP(K14,Tarkun,2,0)) -> Kas | K14: 11100 | M14: =IF(L14=0," ",(VLOOKUP(L14,Kode!$B$10:$E$423,4,0))) | N14: 19566300 | P14: =IF(K14="","",IF(AND(K14>0,$M$602=0),"Balance","Unbalance")) -> Balance
A15: =B15&K15 -> 222105 | B15: =IF(ERR=TRUE,COUNTIF($K$10:K15,K15),0) -> 2 | C15: =D15&M15 -> 6 | D15: =IF(ERR=FALSE,0,COUNTIF($M$10:M15,M15)) -> 6 | F15: 46026 | G15: 3 | I15: Penjualan Retail | J15: =IF(K15=0,"",VLOOKUP(K15,Tarkun,2,0)) -> PPN Keluaran | K15: 22105 | M15: =IF(L15=0," ",(VLOOKUP(L15,Kode!$B$10:$E$423,4,0))) | O15: 1939002.7 | P15: =IF(K15="","",IF(AND(K15>0,$M$602=0),"Balance","Unbalance")) -> Balance
A16: =B16&K16 -> 241000 | B16: =IF(ERR=TRUE,COUNTIF($K$10:K16,K16),0) -> 2 | C16: =D16&M16 -> 7 | D16: =IF(ERR=FALSE,0,COUNTIF($M$10:M16,M16)) -> 7 | F16: 46027 | G16: 3 | I16: Penjualan Retail | J16: =IF(K16=0,"",VLOOKUP(K16,Tarkun,2,0)) -> Penjualan Barang | K16: 41000 | M16: =IF(L16=0," ",(VLOOKUP(L16,Kode!$B$10:$E$423,4,0))) | O16: 17627297 | P16: =IF(K16="","",IF(AND(K16>0,$M$602=0),"Balance","Unbalance")) -> Balance
A17: =B17&K17 -> 0 | B17: =IF(ERR=TRUE,COUNTIF($K$10:K17,K17),0) -> 0 | C17: =D17&M17 -> 8 | D17: =IF(ERR=FALSE,0,COUNTIF($M$10:M17,M17)) -> 8 | F17: 46051 | J17: =IF(K17=0,"",VLOOKUP(K17,Tarkun,2,0)) | M17: =IF(L17=0," ",(VLOOKUP(L17,Kode!$B$10:$E$423,4,0))) | O17: 0 | P17: =IF(K17="","",IF(AND(K17>0,$M$602=0),"Balance","Unbalance"))
A18: =B18&K18 -> 111700 | B18: =IF(ERR=TRUE,COUNTIF($K$10:K18,K18),0) -> 1 | C18: =D18&M18 -> 9 | D18: =IF(ERR=FALSE,0,COUNTIF($M$10:M18,M18)) -> 9 | F18: 46048 | G18: 5 | I18: DP Mesin Flatbed Allwind Aneka Warna Indah, PT | J18: =IF(K18=0,"",VLOOKUP(K18,Tarkun,2,0)) -> Uang Muka Pembelian | K18: 11700 | M18: =IF(L18=0," ",(VLOOKUP(L18,Kode!$B$10:$E$423,4,0))) | N18: 200000000 | P18: =IF(K18="","",IF(AND(K18>0,$M$602=0),"Balance","Unbalance")) -> Balance
A19: =B19&K19 -> 311100 | B19: =IF(ERR=TRUE,COUNTIF($K$10:K19,K19),0) -> 3 | C19: =D19&M19 -> 10 | D19: =IF(ERR=FALSE,0,COUNTIF($M$10:M19,M19)) -> 10 | F19: 46048 | G19: 5 | I19: DP Mesin Flatbed Allwind Aneka Warna Indah, PT | J19: =IF(K19=0,"",VLOOKUP(K19,Tarkun,2,0)) -> Kas | K19: 11100 | M19: =IF(L19=0," ",(VLOOKUP(L19,Kode!$B$10:$E$423,4,0))) | O19: 200000000 | P19: =IF(K19="","",IF(AND(K19>0,$M$602=0),"Balance","Unbalance")) -> Balance
A20: =B20&K20 -> 411100 | B20: =IF(ERR=TRUE,COUNTIF($K$10:K20,K20),0) -> 4 | C20: =D20&M20 -> 11 | D20: =IF(ERR=FALSE,0,COUNTIF($M$10:M20,M20)) -> 11 | F20: 46023 | G20: 5 | I20: Penjualan Retail | J20: =IF(K20=0,"",VLOOKUP(K20,Tarkun,2,0)) -> Kas | K20: 11100 | M20: =IF(L20=0," ",(VLOOKUP(L20,Kode!$B$10:$E$423,4,0))) | N20: 29812000 | P20: =IF(K20="","",IF(AND(K20>0,$M$602=0),"Balance","Unbalance")) -> Balance
A21: =B21&K21 -> 322105 | B21: =IF(ERR=TRUE,COUNTIF($K$10:K21,K21),0) -> 3 | C21: =D21&M21 -> 12 | D21: =IF(ERR=FALSE,0,COUNTIF($M$10:M21,M21)) -> 12 | F21: 46026 | G21: 5 | I21: Penjualan Retail | J21: =IF(K21=0,"",VLOOKUP(K21,Tarkun,2,0)) -> PPN Keluaran | K21: 22105 | M21: =IF(L21=0," ",(VLOOKUP(L21,Kode!$B$10:$E$423,4,0))) | O21: 2954342.3 | P21: =IF(K21="","",IF(AND(K21>0,$M$602=0),"Balance","Unbalance")) -> Balance
A22: =B22&K22 -> 341000 | B22: =IF(ERR=TRUE,COUNTIF($K$10:K22,K22),0) -> 3 | C22: =D22&M22 -> 13 | D22: =IF(ERR=FALSE,0,COUNTIF($M$10:M22,M22)) -> 13 | F22: 46027 | G22: 5 | I22: Penjualan Retail | J22: =IF(K22=0,"",VLOOKUP(K22,Tarkun,2,0)) -> Penjualan Barang | K22: 41000 | M22: =IF(L22=0," ",(VLOOKUP(L22,Kode!$B$10:$E$423,4,0))) | O22: 26857658 | P22: =IF(K22="","",IF(AND(K22>0,$M$602=0),"Balance","Unbalance")) -> Balance
A23: =B23&K23 -> 112200 | B23: =IF(ERR=TRUE,COUNTIF($K$10:K23,K23),0) -> 1 | C23: =D23&M23 -> 14 | D23: =IF(ERR=FALSE,0,COUNTIF($M$10:M23,M23)) -> 14 | F23: 46051 | G23: 5 | H23: 04002600004962829 | I23: Pembelian Mesin ALLWIN 2512GS UV FLATBED RICOH ke Aneka Warna Indah, PT | J23: =IF(K23=0,"",VLOOKUP(K23,Tarkun,2,0)) -> Peralatan Pabrik | K23: 12200 | M23: =IF(L23=0," ",(VLOOKUP(L23,Kode!$B$10:$E$423,4,0))) | N23: 495495496 | O23: 0 | P23: =IF(K23="","",IF(AND(K23>0,$M$602=0),"Balance","Unbalance")) -> Balance
A24: =B24&K24 -> 111600 | B24: =IF(ERR=TRUE,COUNTIF($K$10:K24,K24),0) -> 1 | C24: =D24&M24 -> 15 | D24: =IF(ERR=FALSE,0,COUNTIF($M$10:M24,M24)) -> 15 | F24: 46051 | G24: 5 | H24: 04002600004962829 | I24: Pembelian Mesin ALLWIN 2512GS UV FLATBED RICOH ke Aneka Warna Indah, PT | J24: =IF(K24=0,"",VLOOKUP(K24,Tarkun,2,0)) -> PPN Masukan | K24: 11600 | M24: =IF(L24=0," ",(VLOOKUP(L24,Kode!$B$10:$E$423,4,0))) | N24: 54504505 | O24: 0 | P24: =IF(K24="","",IF(AND(K24>0,$M$602=0),"Balance","Unbalance")) -> Balance
A25: =B25&K25 -> 121100 | B25: =IF(ERR=TRUE,COUNTIF($K$10:K25,K25),0) -> 1 | C25: =D25&M25 -> 1H-001 | D25: =IF(ERR=FALSE,0,COUNTIF($M$10:M25,M25)) -> 1 | F25: 46051 | G25: 5 | H25: 04002600004962829 | I25: Pembelian Mesin ALLWIN 2512GS UV FLATBED RICOH ke Aneka Warna Indah, PT | J25: =IF(K25=0,"",VLOOKUP(K25,Tarkun,2,0)) -> Hutang Dagang | K25: 21100 | L25: Aneka Warna Indah, PT | M25: =IF(L25=0," ",(VLOOKUP(L25,Kode!$B$10:$E$423,4,0))) -> H-001 | O25: 350000001 | P25: =IF(K25="","",IF(AND(K25>0,$M$602=0),"Balance","Unbalance")) -> Balance
A26: =B26&K26 -> 211700 | B26: =IF(ERR=TRUE,COUNTIF($K$10:K26,K26),0) -> 2 | C26: =D26&M26 -> 16 | D26: =IF(ERR=FALSE,0,COUNTIF($M$10:M26,M26)) -> 16 | F26: 46051 | G26: 5 | H26: 04002600004962829 | I26: Pembelian Mesin ALLWIN 2512GS UV FLATBED RICOH ke Aneka Warna Indah, PT | J26: =IF(K26=0,"",VLOOKUP(K26,Tarkun,2,0)) -> Uang Muka Pembelian | K26: 11700 | M26: =IF(L26=0," ",(VLOOKUP(L26,Kode!$B$10:$E$423,4,0))) | O26: 200000000 | P26: =IF(K26="","",IF(AND(K26>0,$M$602=0),"Balance","Unbalance")) -> Balance
A27: =B27&K27 -> 211600 | B27: =IF(ERR=TRUE,COUNTIF($K$10:K27,K27),0) -> 2 | C27: =D27&M27 -> 17 | D27: =IF(ERR=FALSE,0,COUNTIF($M$10:M27,M27)) -> 17 | F27: 46051 | G27: 5 | H27: 04002600007083162 | I27: Pembelian BB ke Aneka Warna Indah, PT | J27: =IF(K27=0,"",VLOOKUP(K27,Tarkun,2,0)) -> PPN Masukan | K27: 11600 | M27: =IF(L27=0," ",(VLOOKUP(L27,Kode!$B$10:$E$423,4,0))) | N27: 1557838 | O27: 0 | P27: =IF(K27="","",IF(AND(K27>0,$M$602=0),"Balance","Unbalance")) -> Balance
A28: =B28&K28 -> 153000 | B28: =IF(ERR=TRUE,COUNTIF($K$10:K28,K28),0) -> 1 | C28: =D28&M28 -> 18 | D28: =IF(ERR=FALSE,0,COUNTIF($M$10:M28,M28)) -> 18 | F28: 46051 | G28: 5 | H28: 04002600007083162 | I28: Pembelian BB ke Aneka Warna Indah, PT | J28: =IF(K28=0,"",VLOOKUP(K28,Tarkun,2,0)) -> Pembelian Bahan Baku | K28: 53000 | M28: =IF(L28=0," ",(VLOOKUP(L28,Kode!$B$10:$E$423,4,0))) | N28: 14162162 | O28: 0 | P28: =IF(K28="","",IF(AND(K28>0,$M$602=0),"Balance","Unbalance")) -> Balance
A29: =B29&K29 -> 221100 | B29: =IF(ERR=TRUE,COUNTIF($K$10:K29,K29),0) -> 2 | C29: =D29&M29 -> 2H-001 | D29: =IF(ERR=FALSE,0,COUNTIF($M$10:M29,M29)) -> 2 | F29: 46051 | G29: 5 | H29: 04002600007083162 | I29: Pembelian BB ke Aneka Warna Indah, PT | J29: =IF(K29=0,"",VLOOKUP(K29,Tarkun,2,0)) -> Hutang Dagang | K29: 21100 | L29: Aneka Warna Indah, PT | M29: =IF(L29=0," ",(VLOOKUP(L29,Kode!$B$10:$E$423,4,0))) -> H-001 | O29: 15720000 | P29: =IF(K29="","",IF(AND(K29>0,$M$602=0),"Balance","Unbalance")) -> Balance
A30: =B30&K30 -> 0 | B30: =IF(ERR=TRUE,COUNTIF($K$10:K30,K30),0) -> 0 | C30: =D30&M30 -> 19 | D30: =IF(ERR=FALSE,0,COUNTIF($M$10:M30,M30)) -> 19 | F30: 46051 | G30: 5 | J30: =IF(K30=0,"",VLOOKUP(K30,Tarkun,2,0)) | M30: =IF(L30=0," ",(VLOOKUP(L30,Kode!$B$10:$E$423,4,0))) | O30: 0 | P30: =IF(K30="","",IF(AND(K30>0,$M$602=0),"Balance","Unbalance"))
A31: =B31&K31 -> 0 | B31: =IF(ERR=TRUE,COUNTIF($K$10:K31,K31),0) -> 0 | C31: =D31&M31 -> 20 | D31: =IF(ERR=FALSE,0,COUNTIF($M$10:M31,M31)) -> 20 | F31: 46051 | G31: 5 | J31: =IF(K31=0,"",VLOOKUP(K31,Tarkun,2,0)) | M31: =IF(L31=0," ",(VLOOKUP(L31,Kode!$B$10:$E$423,4,0))) | O31: 0 | P31: =IF(K31="","",IF(AND(K31>0,$M$602=0),"Balance","Unbalance"))
A32: =B32&K32 -> 0 | B32: =IF(ERR=TRUE,COUNTIF($K$10:K32,K32),0) -> 0 | C32: =D32&M32 -> 21 | D32: =IF(ERR=FALSE,0,COUNTIF($M$10:M32,M32)) -> 21 | F32: 46051 | J32: =IF(K32=0,"",VLOOKUP(K32,Tarkun,2,0)) | M32: =IF(L32=0," ",(VLOOKUP(L32,Kode!$B$10:$E$423,4,0))) | O32: 0 | P32: =IF(K32="","",IF(AND(K32>0,$M$602=0),"Balance","Unbalance"))
A33: =B33&K33 -> 511100 | B33: =IF(ERR=TRUE,COUNTIF($K$10:K33,K33),0) -> 5 | C33: =D33&M33 -> 22 | D33: =IF(ERR=FALSE,0,COUNTIF($M$10:M33,M33)) -> 22 | F33: 46023 | G33: 6 | I33: Penjualan Retail | J33: =IF(K33=0,"",VLOOKUP(K33,Tarkun,2,0)) -> Kas | K33: 11100 | M33: =IF(L33=0," ",(VLOOKUP(L33,Kode!$B$10:$E$423,4,0))) | N33: 24833800 | P33: =IF(K33="","",IF(AND(K33>0,$M$602=0),"Balance","Unbalance")) -> Balance
A34: =B34&K34 -> 422105 | B34: =IF(ERR=TRUE,COUNTIF($K$10:K34,K34),0) -> 4 | C34: =D34&M34 -> 23 | D34: =IF(ERR=FALSE,0,COUNTIF($M$10:M34,M34)) -> 23 | F34: 46026 | G34: 6 | I34: Penjualan Retail | J34: =IF(K34=0,"",VLOOKUP(K34,Tarkun,2,0)) -> PPN Keluaran | K34: 22105 | M34: =IF(L34=0," ",(VLOOKUP(L34,Kode!$B$10:$E$423,4,0))) | O34: 2461007.2 | P34: =IF(K34="","",IF(AND(K34>0,$M$602=0),"Balance","Unbalance")) -> Balance
A35: =B35&K35 -> 441000 | B35: =IF(ERR=TRUE,COUNTIF($K$10:K35,K35),0) -> 4 | C35: =D35&M35 -> 24 | D35: =IF(ERR=FALSE,0,COUNTIF($M$10:M35,M35)) -> 24 | F35: 46027 | G35: 6 | I35: Penjualan Retail | J35: =IF(K35=0,"",VLOOKUP(K35,Tarkun,2,0)) -> Penjualan Barang | K35: 41000 | M35: =IF(L35=0," ",(VLOOKUP(L35,Kode!$B$10:$E$423,4,0))) | O35: 22372793 | P35: =IF(K35="","",IF(AND(K35>0,$M$602=0),"Balance","Unbalance")) -> Balance
A36: =B36&K36 -> 111102 | B36: =IF(ERR=TRUE,COUNTIF($K$10:K36,K36),0) -> 1 | C36: =D36&M36 -> 25 | D36: =IF(ERR=FALSE,0,COUNTIF($M$10:M36,M36)) -> 25 | F36: 46034 | G36: 6 | H36: 04002600002181848 | I36: Penjualan ke Artindo Grafika Printing, PT | J36: =IF(K36=0,"",VLOOKUP(K36,Tarkun,2,0)) -> Piutang Dagang | K36: 11102 | M36: =IF(L36=0," ",(VLOOKUP(L36,Kode!$B$10:$E$423,4,0))) | N36: 432781785 | P36: =IF(K36="","",IF(AND(K36>0,$M$602=0),"Balance","Unbalance")) -> Balance
A37: =B37&K37 -> 522105 | B37: =IF(ERR=TRUE,COUNTIF($K$10:K37,K37),0) -> 5 | C37: =D37&M37 -> 26 | D37: =IF(ERR=FALSE,0,COUNTIF($M$10:M37,M37)) -> 26 | F37: 46035 | G37: 6 | H37: 04002600002181848 | I37: Penjualan ke Artindo Grafika Printing, PT | J37: =IF(K37=0,"",VLOOKUP(K37,Tarkun,2,0)) -> PPN Keluaran | K37: 22105 | M37: =IF(L37=0," ",(VLOOKUP(L37,Kode!$B$10:$E$423,4,0))) | O37: 42888285 | P37: =IF(K37="","",IF(AND(K37>0,$M$602=0),"Balance","Unbalance")) -> Balance
A38: =B38&K38 -> 541000 | B38: =IF(ERR=TRUE,COUNTIF($K$10:K38,K38),0) -> 5 | C38: =D38&M38 -> 27 | D38: =IF(ERR=FALSE,0,COUNTIF($M$10:M38,M38)) -> 27 | F38: 46036 | G38: 6 | H38: 04002600002181848 | I38: Penjualan ke Artindo Grafika Printing, PT | J38: =IF(K38=0,"",VLOOKUP(K38,Tarkun,2,0)) -> Penjualan Barang | K38: 41000 | M38: =IF(L38=0," ",(VLOOKUP(L38,Kode!$B$10:$E$423,4,0))) | O38: 389893500 | P38: =IF(K38="","",IF(AND(K38>0,$M$602=0),"Balance","Unbalance")) -> Balance
A39: =B39&K39 -> 211102 | B39: =IF(ERR=TRUE,COUNTIF($K$10:K39,K39),0) -> 2 | C39: =D39&M39 -> 28 | D39: =IF(ERR=FALSE,0,COUNTIF($M$10:M39,M39)) -> 28 | F39: 46037 | G39: 6 | H39: 04002600002187886 | I39: Penjualan ke Artindo Grafika Printing, PT | J39: =IF(K39=0,"",VLOOKUP(K39,Tarkun,2,0)) -> Piutang Dagang | K39: 11102 | M39: =IF(L39=0," ",(VLOOKUP(L39,Kode!$B$10:$E$423,4,0))) | N39: 92157750 | P39: =IF(K39="","",IF(AND(K39>0,$M$602=0),"Balance","Unbalance")) -> Balance
A40: =B40&K40 -> 622105 | B40: =IF(ERR=TRUE,COUNTIF($K$10:K40,K40),0) -> 6 | C40: =D40&M40 -> 29 | D40: =IF(ERR=FALSE,0,COUNTIF($M$10:M40,M40)) -> 29 | F40: 46038 | G40: 6 | H40: 04002600002187886 | I40: Penjualan ke Artindo Grafika Printing, PT | J40: =IF(K40=0,"",VLOOKUP(K40,Tarkun,2,0)) -> PPN Keluaran | K40: 22105 | M40: =IF(L40=0," ",(VLOOKUP(L40,Kode!$B$10:$E$423,4,0))) | O40: 9132750 | P40: =IF(K40="","",IF(AND(K40>0,$M$602=0),"Balance","Unbalance")) -> Balance
A41: =B41&K41 -> 641000 | B41: =IF(ERR=TRUE,COUNTIF($K$10:K41,K41),0) -> 6 | C41: =D41&M41 -> 30 | D41: =IF(ERR=FALSE,0,COUNTIF($M$10:M41,M41)) -> 30 | F41: 46039 | G41: 6 | H41: 04002600002187886 | I41: Penjualan ke Artindo Grafika Printing, PT | J41: =IF(K41=0,"",VLOOKUP(K41,Tarkun,2,0)) -> Penjualan Barang | K41: 41000 | M41: =IF(L41=0," ",(VLOOKUP(L41,Kode!$B$10:$E$423,4,0))) | O41: 83025000 | P41: =IF(K41="","",IF(AND(K41>0,$M$602=0),"Balance","Unbalance")) -> Balance
A42: =B42&K42 -> 311102 | B42: =IF(ERR=TRUE,COUNTIF($K$10:K42,K42),0) -> 3 | C42: =D42&M42 -> 31 | D42: =IF(ERR=FALSE,0,COUNTIF($M$10:M42,M42)) -> 31 | F42: 46040 | G42: 6 | H42: 04002600002191593 | I42: Penjualan ke Artindo Grafika Printing, PT | J42: =IF(K42=0,"",VLOOKUP(K42,Tarkun,2,0)) -> Piutang Dagang | K42: 11102 | M42: =IF(L42=0," ",(VLOOKUP(L42,Kode!$B$10:$E$423,4,0))) | N42: 2071526.4 | P42: =IF(K42="","",IF(AND(K42>0,$M$602=0),"Balance","Unbalance")) -> Balance
A43: =B43&K43 -> 722105 | B43: =IF(ERR=TRUE,COUNTIF($K$10:K43,K43),0) -> 7 | C43: =D43&M43 -> 32 | D43: =IF(ERR=FALSE,0,COUNTIF($M$10:M43,M43)) -> 32 | F43: 46041 | G43: 6 | H43: 04002600002191593 | I43: Penjualan ke Artindo Grafika Printing, PT | J43: =IF(K43=0,"",VLOOKUP(K43,Tarkun,2,0)) -> PPN Keluaran | K43: 22105 | M43: =IF(L43=0," ",(VLOOKUP(L43,Kode!$B$10:$E$423,4,0))) | O43: 205286.4 | P43: =IF(K43="","",IF(AND(K43>0,$M$602=0),"Balance","Unbalance")) -> Balance
A44: =B44&K44 -> 741000 | B44: =IF(ERR=TRUE,COUNTIF($K$10:K44,K44),0) -> 7 | C44: =D44&M44 -> 33 | D44: =IF(ERR=FALSE,0,COUNTIF($M$10:M44,M44)) -> 33 | F44: 46042 | G44: 6 | H44: 04002600002191593 | I44: Penjualan ke Artindo Grafika Printing, PT | J44: =IF(K44=0,"",VLOOKUP(K44,Tarkun,2,0)) -> Penjualan Barang | K44: 41000 | M44: =IF(L44=0," ",(VLOOKUP(L44,Kode!$B$10:$E$423,4,0))) | O44: 1866240 | P44: =IF(K44="","",IF(AND(K44>0,$M$602=0),"Balance","Unbalance")) -> Balance
A45: =B45&K45 -> 411102 | B45: =IF(ERR=TRUE,COUNTIF($K$10:K45,K45),0) -> 4 | C45: =D45&M45 -> 34 | D45: =IF(ERR=FALSE,0,COUNTIF($M$10:M45,M45)) -> 34 | F45: 46043 | G45: 6 | H45: 04002600002200199 | I45: Penjualan ke Mirota KSM, PT | J45: =IF(K45=0,"",VLOOKUP(K45,Tarkun,2,0)) -> Piutang Dagang | K45: 11102 | M45: =IF(L45=0," ",(VLOOKUP(L45,Kode!$B$10:$E$423,4,0))) | N45: 24753 | P45: =IF(K45="","",IF(AND(K45>0,$M$602=0),"Balance","Unbalance")) -> Balance
A46: =B46&K46 -> 822105 | B46: =IF(ERR=TRUE,COUNTIF($K$10:K46,K46),0) -> 8 | C46: =D46&M46 -> 35 | D46: =IF(ERR=FALSE,0,COUNTIF($M$10:M46,M46)) -> 35 | F46: 46044 | G46: 6 | H46: 04002600002200199 | I46: Penjualan ke Mirota KSM, PT | J46: =IF(K46=0,"",VLOOKUP(K46,Tarkun,2,0)) -> PPN Keluaran | K46: 22105 | M46: =IF(L46=0," ",(VLOOKUP(L46,Kode!$B$10:$E$423,4,0))) | O46: 2453 | P46: =IF(K46="","",IF(AND(K46>0,$M$602=0),"Balance","Unbalance")) -> Balance
A47: =B47&K47 -> 841000 | B47: =IF(ERR=TRUE,COUNTIF($K$10:K47,K47),0) -> 8 | C47: =D47&M47 -> 36 | D47: =IF(ERR=FALSE,0,COUNTIF($M$10:M47,M47)) -> 36 | F47: 46045 | G47: 6 | H47: 04002600002200199 | I47: Penjualan ke Mirota KSM, PT | J47: =IF(K47=0,"",VLOOKUP(K47,Tarkun,2,0)) -> Penjualan Barang | K47: 41000 | M47: =IF(L47=0," ",(VLOOKUP(L47,Kode!$B$10:$E$423,4,0))) | O47: 22300 | P47: =IF(K47="","",IF(AND(K47>0,$M$602=0),"Balance","Unbalance")) -> Balance
A48: =B48&K48 -> 611100 | B48: =IF(ERR=TRUE,COUNTIF($K$10:K48,K48),0) -> 6 | C48: =D48&M48 -> 37 | D48: =IF(ERR=FALSE,0,COUNTIF($M$10:M48,M48)) -> 37 | F48: 46046 | G48: 6 | I48: Penerimaan Tunai pengembalian Pph Armada Servis Traga | J48: =IF(K48=0,"",VLOOKUP(K48,Tarkun,2,0)) -> Kas | K48: 11100 | M48: =IF(L48=0," ",(VLOOKUP(L48,Kode!$B$10:$E$423,4,0))) | N48: 18400 | P48: =IF(K48="","",IF(AND(K48>0,$M$602=0),"Balance","Unbalance")) -> Balance
A49: =B49&K49 -> 141002 | B49: =IF(ERR=TRUE,COUNTIF($K$10:K49,K49),0) -> 1 | C49: =D49&M49 -> 38 | D49: =IF(ERR=FALSE,0,COUNTIF($M$10:M49,M49)) -> 38 | F49: 46047 | G49: 6 | I49: Penerimaan Tunai pengembalian Pph Armada Servis Traga | J49: =IF(K49=0,"",VLOOKUP(K49,Tarkun,2,0)) -> Pendapatan Lain-lain | K49: 41002 | M49: =IF(L49=0," ",(VLOOKUP(L49,Kode!$B$10:$E$423,4,0))) | O49: 18400 | P49: =IF(K49="","",IF(AND(K49>0,$M$602=0),"Balance","Unbalance")) -> Balance
A50: =B50&K50 -> 711100 | B50: =IF(ERR=TRUE,COUNTIF($K$10:K50,K50),0) -> 7 | C50: =D50&M50 -> 39 | D50: =IF(ERR=FALSE,0,COUNTIF($M$10:M50,M50)) -> 39 | F50: 46048 | G50: 6 | I50: Penerimaan Dimuka Git Gow Ayo, PT | J50: =IF(K50=0,"",VLOOKUP(K50,Tarkun,2,0)) -> Kas | K50: 11100 | M50: =IF(L50=0," ",(VLOOKUP(L50,Kode!$B$10:$E$423,4,0))) | N50: 245141 | P50: =IF(K50="","",IF(AND(K50>0,$M$602=0),"Balance","Unbalance")) -> Balance
A51: =B51&K51 -> 127100 | B51: =IF(ERR=TRUE,COUNTIF($K$10:K51,K51),0) -> 1 | C51: =D51&M51 -> 40 | D51: =IF(ERR=FALSE,0,COUNTIF($M$10:M51,M51)) -> 40 | F51: 46049 | G51: 6 | I51: Penerimaan Dimuka Git Gow Ayo, PT | J51: =IF(K51=0,"",VLOOKUP(K51,Tarkun,2,0)) -> Uang Muka Penjualan | K51: 27100 | M51: =IF(L51=0," ",(VLOOKUP(L51,Kode!$B$10:$E$423,4,0))) | O51: 245141 | P51: =IF(K51="","",IF(AND(K51>0,$M$602=0),"Balance","Unbalance")) -> Balance
A52: =B52&K52 -> 311600 | B52: =IF(ERR=TRUE,COUNTIF($K$10:K52,K52),0) -> 3 | C52: =D52&M52 -> 41 | D52: =IF(ERR=FALSE,0,COUNTIF($M$10:M52,M52)) -> 41 | F52: 46051 | G52: 6 | H52: 04002600012775920 | I52: Pembelian BB ke Aneka Warna Indah, PT | J52: =IF(K52=0,"",VLOOKUP(K52,Tarkun,2,0)) -> PPN Masukan | K52: 11600 | M52: =IF(L52=0," ",(VLOOKUP(L52,Kode!$B$10:$E$423,4,0))) | N52: 1580631 | P52: =IF(K52="","",IF(AND(K52>0,$M$602=0),"Balance","Unbalance")) -> Balance
A53: =B53&K53 -> 253000 | B53: =IF(ERR=TRUE,COUNTIF($K$10:K53,K53),0) -> 2 | C53: =D53&M53 -> 42 | D53: =IF(ERR=FALSE,0,COUNTIF($M$10:M53,M53)) -> 42 | F53: 46051 | G53: 6 | H53: 04002600012775920 | I53: Pembelian BB ke Aneka Warna Indah, PT | J53: =IF(K53=0,"",VLOOKUP(K53,Tarkun,2,0)) -> Pembelian Bahan Baku | K53: 53000 | M53: =IF(L53=0," ",(VLOOKUP(L53,Kode!$B$10:$E$423,4,0))) | N53: 14369369 | P53: =IF(K53="","",IF(AND(K53>0,$M$602=0),"Balance","Unbalance")) -> Balance
A54: =B54&K54 -> 321100 | B54: =IF(ERR=TRUE,COUNTIF($K$10:K54,K54),0) -> 3 | C54: =D54&M54 -> 3H-001 | D54: =IF(ERR=FALSE,0,COUNTIF($M$10:M54,M54)) -> 3 | F54: 46051 | G54: 6 | H54: 04002600012775920 | I54: Pembelian BB ke Aneka Warna Indah, PT | J54: =IF(K54=0,"",VLOOKUP(K54,Tarkun,2,0)) -> Hutang Dagang | K54: 21100 | L54: Aneka Warna Indah, PT | M54: =IF(L54=0," ",(VLOOKUP(L54,Kode!$B$10:$E$423,4,0))) -> H-001 | O54: 15950000 | P54: =IF(K54="","",IF(AND(K54>0,$M$602=0),"Balance","Unbalance")) -> Balance
A55: =B55&K55 -> 411600 | B55: =IF(ERR=TRUE,COUNTIF($K$10:K55,K55),0) -> 4 | C55: =D55&M55 -> 43 | D55: =IF(ERR=FALSE,0,COUNTIF($M$10:M55,M55)) -> 43 | F55: 46051 | G55: 6 | H55: 04002600001499545 | I55: Pembelian BB ke Putra Mutiara Jaya, PT | J55: =IF(K55=0,"",VLOOKUP(K55,Tarkun,2,0)) -> PPN Masukan | K55: 11600 | M55: =IF(L55=0," ",(VLOOKUP(L55,Kode!$B$10:$E$423,4,0))) | N55: 1252118 | P55: =IF(K55="","",IF(AND(K55>0,$M$602=0),"Balance","Unbalance")) -> Balance
A56: =B56&K56 -> 353000 | B56: =IF(ERR=TRUE,COUNTIF($K$10:K56,K56),0) -> 3 | C56: =D56&M56 -> 44 | D56: =IF(ERR=FALSE,0,COUNTIF($M$10:M56,M56)) -> 44 | F56: 46051 | G56: 6 | H56: 04002600001499545 | I56: Pembelian BB ke Putra Mutiara Jaya, PT | J56: =IF(K56=0,"",VLOOKUP(K56,Tarkun,2,0)) -> Pembelian Bahan Baku | K56: 53000 | M56: =IF(L56=0," ",(VLOOKUP(L56,Kode!$B$10:$E$423,4,0))) | N56: 11382889 | P56: =IF(K56="","",IF(AND(K56>0,$M$602=0),"Balance","Unbalance")) -> Balance
A57: =B57&K57 -> 421100 | B57: =IF(ERR=TRUE,COUNTIF($K$10:K57,K57),0) -> 4 | C57: =D57&M57 -> 1H-009 | D57: =IF(ERR=FALSE,0,COUNTIF($M$10:M57,M57)) -> 1 | F57: 46051 | G57: 6 | H57: 04002600001499545 | I57: Pembelian BB ke Putra Mutiara Jaya, PT | J57: =IF(K57=0,"",VLOOKUP(K57,Tarkun,2,0)) -> Hutang Dagang | K57: 21100 | L57: Putra Mutiara Jaya, PT | M57: =IF(L57=0," ",(VLOOKUP(L57,Kode!$B$10:$E$423,4,0))) -> H-009 | O57: 12635007 | P57: =IF(K57="","",IF(AND(K57>0,$M$602=0),"Balance","Unbalance")) -> Balance
A58: =B58&K58 -> 511600 | B58: =IF(ERR=TRUE,COUNTIF($K$10:K58,K58),0) -> 5 | C58: =D58&M58 -> 45 | D58: =IF(ERR=FALSE,0,COUNTIF($M$10:M58,M58)) -> 45 | F58: 46051 | G58: 6 | H58: 04002600012759676 | I58: Pembelian BB ke Aneka Warna Indah, PT | J58: =IF(K58=0,"",VLOOKUP(K58,Tarkun,2,0)) -> PPN Masukan | K58: 11600 | M58: =IF(L58=0," ",(VLOOKUP(L58,Kode!$B$10:$E$423,4,0))) | N58: 265586 | P58: =IF(K58="","",IF(AND(K58>0,$M$602=0),"Balance","Unbalance")) -> Balance
A59: =B59&K59 -> 453000 | B59: =IF(ERR=TRUE,COUNTIF($K$10:K59,K59),0) -> 4 | C59: =D59&M59 -> 46 | D59: =IF(ERR=FALSE,0,COUNTIF($M$10:M59,M59)) -> 46 | F59: 46051 | G59: 6 | H59: 04002600012759676 | I59: Pembelian BB ke Aneka Warna Indah, PT | J59: =IF(K59=0,"",VLOOKUP(K59,Tarkun,2,0)) -> Pembelian Bahan Baku | K59: 53000 | M59: =IF(L59=0," ",(VLOOKUP(L59,Kode!$B$10:$E$423,4,0))) | N59: 2414414 | P59: =IF(K59="","",IF(AND(K59>0,$M$602=0),"Balance","Unbalance")) -> Balance
A60: =B60&K60 -> 521100 | B60: =IF(ERR=TRUE,COUNTIF($K$10:K60,K60),0) -> 5 | C60: =D60&M60 -> 4H-001 | D60: =IF(ERR=FALSE,0,COUNTIF($M$10:M60,M60)) -> 4 | F60: 46051 | G60: 6 | H60: 04002600012759676 | I60: Pembelian BB ke Aneka Warna Indah, PT | J60: =IF(K60=0,"",VLOOKUP(K60,Tarkun,2,0)) -> Hutang Dagang | K60: 21100 | L60: Aneka Warna Indah, PT | M60: =IF(L60=0," ",(VLOOKUP(L60,Kode!$B$10:$E$423,4,0))) -> H-001 | O60: 2680000 | P60: =IF(K60="","",IF(AND(K60>0,$M$602=0),"Balance","Unbalance")) -> Balance
A61: =B61&K61 -> 611600 | B61: =IF(ERR=TRUE,COUNTIF($K$10:K61,K61),0) -> 6 | C61: =D61&M61 -> 47 | D61: =IF(ERR=FALSE,0,COUNTIF($M$10:M61,M61)) -> 47 | F61: 46051 | G61: 6 | H61: 04002600006401523 | I61: Pembelian BB ke Omega Garda Rupala, PT | J61: =IF(K61=0,"",VLOOKUP(K61,Tarkun,2,0)) -> PPN Masukan | K61: 11600 | M61: =IF(L61=0," ",(VLOOKUP(L61,Kode!$B$10:$E$423,4,0))) | N61: 396396 | P61: =IF(K61="","",IF(AND(K61>0,$M$602=0),"Balance","Unbalance")) -> Balance
A62: =B62&K62 -> 553000 | B62: =IF(ERR=TRUE,COUNTIF($K$10:K62,K62),0) -> 5 | C62: =D62&M62 -> 48 | D62: =IF(ERR=FALSE,0,COUNTIF($M$10:M62,M62)) -> 48 | F62: 46051 | G62: 6 | H62: 04002600006401523 | I62: Pembelian BB ke Omega Garda Rupala, PT | J62: =IF(K62=0,"",VLOOKUP(K62,Tarkun,2,0)) -> Pembelian Bahan Baku | K62: 53000 | M62: =IF(L62=0," ",(VLOOKUP(L62,Kode!$B$10:$E$423,4,0))) | N62: 3603604 | P62: =IF(K62="","",IF(AND(K62>0,$M$602=0),"Balance","Unbalance")) -> Balance
A63: =B63&K63 -> 621100 | B63: =IF(ERR=TRUE,COUNTIF($K$10:K63,K63),0) -> 6 | C63: =D63&M63 -> 1H-012 | D63: =IF(ERR=FALSE,0,COUNTIF($M$10:M63,M63)) -> 1 | F63: 46051 | G63: 6 | H63: 04002600006401523 | I63: Pembelian BB ke Omega Garda Rupala, PT | J63: =IF(K63=0,"",VLOOKUP(K63,Tarkun,2,0)) -> Hutang Dagang | K63: 21100 | L63: Omega Garda Rupla, PT | M63: =IF(L63=0," ",(VLOOKUP(L63,Kode!$B$10:$E$423,4,0))) -> H-012 | O63: 4000000 | P63: =IF(K63="","",IF(AND(K63>0,$M$602=0),"Balance","Unbalance")) -> Balance
A64: =B64&K64 -> 711600 | B64: =IF(ERR=TRUE,COUNTIF($K$10:K64,K64),0) -> 7 | C64: =D64&M64 -> 49 | D64: =IF(ERR=FALSE,0,COUNTIF($M$10:M64,M64)) -> 49 | F64: 46051 | G64: 6 | H64: 04002600002170860 | I64: Pembelian BB ke Samafitro, PT | J64: =IF(K64=0,"",VLOOKUP(K64,Tarkun,2,0)) -> PPN Masukan | K64: 11600 | M64: =IF(L64=0," ",(VLOOKUP(L64,Kode!$B$10:$E$423,4,0))) | N64: 6504254 | P64: =IF(K64="","",IF(AND(K64>0,$M$602=0),"Balance","Unbalance")) -> Balance
A65: =B65&K65 -> 653000 | B65: =IF(ERR=TRUE,COUNTIF($K$10:K65,K65),0) -> 6 | C65: =D65&M65 -> 50 | D65: =IF(ERR=FALSE,0,COUNTIF($M$10:M65,M65)) -> 50 | F65: 46051 | G65: 6 | H65: 04002600002170860 | I65: Pembelian BB ke Samafitro, PT | J65: =IF(K65=0,"",VLOOKUP(K65,Tarkun,2,0)) -> Pembelian Bahan Baku | K65: 53000 | M65: =IF(L65=0," ",(VLOOKUP(L65,Kode!$B$10:$E$423,4,0))) | N65: 59129580 | P65: =IF(K65="","",IF(AND(K65>0,$M$602=0),"Balance","Unbalance")) -> Balance
A66: =B66&K66 -> 721100 | B66: =IF(ERR=TRUE,COUNTIF($K$10:K66,K66),0) -> 7 | C66: =D66&M66 -> 1H-010 | D66: =IF(ERR=FALSE,0,COUNTIF($M$10:M66,M66)) -> 1 | F66: 46051 | G66: 6 | H66: 04002600002170860 | I66: Pembelian BB ke Samafitro, PT | J66: =IF(K66=0,"",VLOOKUP(K66,Tarkun,2,0)) -> Hutang Dagang | K66: 21100 | L66: Samafitro, PT | M66: =IF(L66=0," ",(VLOOKUP(L66,Kode!$B$10:$E$423,4,0))) -> H-010 | O66: 65633834 | P66: =IF(K66="","",IF(AND(K66>0,$M$602=0),"Balance","Unbalance")) -> Balance
A67: =B67&K67 -> 811600 | B67: =IF(ERR=TRUE,COUNTIF($K$10:K67,K67),0) -> 8 | C67: =D67&M67 -> 51 | D67: =IF(ERR=FALSE,0,COUNTIF($M$10:M67,M67)) -> 51 | F67: 46051 | G67: 6 | H67: 04002600002170850 | I67: Pembelian BB ke Samafitro, PT | J67: =IF(K67=0,"",VLOOKUP(K67,Tarkun,2,0)) -> PPN Masukan | K67: 11600 | M67: =IF(L67=0," ",(VLOOKUP(L67,Kode!$B$10:$E$423,4,0))) | N67: 6663075 | P67: =IF(K67="","",IF(AND(K67>0,$M$602=0),"Balance","Unbalance")) -> Balance
A68: =B68&K68 -> 753000 | B68: =IF(ERR=TRUE,COUNTIF($K$10:K68,K68),0) -> 7 | C68: =D68&M68 -> 52 | D68: =IF(ERR=FALSE,0,COUNTIF($M$10:M68,M68)) -> 52 | F68: 46051 | G68: 6 | H68: 04002600002170850 | I68: Pembelian BB ke Samafitro, PT | J68: =IF(K68=0,"",VLOOKUP(K68,Tarkun,2,0)) -> Pembelian Bahan Baku | K68: 53000 | M68: =IF(L68=0," ",(VLOOKUP(L68,Kode!$B$10:$E$423,4,0))) | N68: 60573410 | P68: =IF(K68="","",IF(AND(K68>0,$M$602=0),"Balance","Unbalance")) -> Balance
A69: =B69&K69 -> 821100 | B69: =IF(ERR=TRUE,COUNTIF($K$10:K69,K69),0) -> 8 | C69: =D69&M69 -> 2H-010 | D69: =IF(ERR=FALSE,0,COUNTIF($M$10:M69,M69)) -> 2 | F69: 46051 | G69: 6 | H69: 04002600002170850 | I69: Pembelian BB ke Samafitro, PT | J69: =IF(K69=0,"",VLOOKUP(K69,Tarkun,2,0)) -> Hutang Dagang | K69: 21100 | L69: Samafitro, PT | M69: =IF(L69=0," ",(VLOOKUP(L69,Kode!$B$10:$E$423,4,0))) -> H-010 | O69: 67236485 | P69: =IF(K69="","",IF(AND(K69>0,$M$602=0),"Balance","Unbalance")) -> Balance
A70: =B70&K70 -> 911600 | B70: =IF(ERR=TRUE,COUNTIF($K$10:K70,K70),0) -> 9 | C70: =D70&M70 -> 53 | D70: =IF(ERR=FALSE,0,COUNTIF($M$10:M70,M70)) -> 53 | F70: 46051 | G70: 6 | H70: 04002600004201597 | I70: Pembelian BB ke Mitra Abadi Jaya Mandiri, CV | J70: =IF(K70=0,"",VLOOKUP(K70,Tarkun,2,0)) -> PPN Masukan | K70: 11600 | M70: =IF(L70=0," ",(VLOOKUP(L70,Kode!$B$10:$E$423,4,0))) | N70: 602027 | P70: =IF(K70="","",IF(AND(K70>0,$M$602=0),"Balance","Unbalance")) -> Balance
A71: =B71&K71 -> 853000 | B71: =IF(ERR=TRUE,COUNTIF($K$10:K71,K71),0) -> 8 | C71: =D71&M71 -> 54 | D71: =IF(ERR=FALSE,0,COUNTIF($M$10:M71,M71)) -> 54 | F71: 46051 | G71: 6 | H71: 04002600004201597 | I71: Pembelian BB ke Mitra Abadi Jaya Mandiri, CV | J71: =IF(K71=0,"",VLOOKUP(K71,Tarkun,2,0)) -> Pembelian Bahan Baku | K71: 53000 | M71: =IF(L71=0," ",(VLOOKUP(L71,Kode!$B$10:$E$423,4,0))) | N71: 5472975 | P71: =IF(K71="","",IF(AND(K71>0,$M$602=0),"Balance","Unbalance")) -> Balance
A72: =B72&K72 -> 921100 | B72: =IF(ERR=TRUE,COUNTIF($K$10:K72,K72),0) -> 9 | C72: =D72&M72 -> 1H-013 | D72: =IF(ERR=FALSE,0,COUNTIF($M$10:M72,M72)) -> 1 | F72: 46051 | G72: 6 | H72: 04002600004201597 | I72: Pembelian BB ke Mitra Abadi Jaya Mandiri, CV | J72: =IF(K72=0,"",VLOOKUP(K72,Tarkun,2,0)) -> Hutang Dagang | K72: 21100 | L72: Mitra Abadi Jaya Mandiri, CV | M72: =IF(L72=0," ",(VLOOKUP(L72,Kode!$B$10:$E$423,4,0))) -> H-013 | O72: 6075002 | P72: =IF(K72="","",IF(AND(K72>0,$M$602=0),"Balance","Unbalance")) -> Balance
A73: =B73&K73 -> 0 | B73: =IF(ERR=TRUE,COUNTIF($K$10:K73,K73),0) -> 0 | C73: =D73&M73 -> 55 | D73: =IF(ERR=FALSE,0,COUNTIF($M$10:M73,M73)) -> 55 | F73: 46051 | J73: =IF(K73=0,"",VLOOKUP(K73,Tarkun,2,0)) | M73: =IF(L73=0," ",(VLOOKUP(L73,Kode!$B$10:$E$423,4,0))) | P73: =IF(K73="","",IF(AND(K73>0,$M$602=0),"Balance","Unbalance"))
A74: =B74&K74 -> 811100 | B74: =IF(ERR=TRUE,COUNTIF($K$10:K74,K74),0) -> 8 | C74: =D74&M74 -> 56 | D74: =IF(ERR=FALSE,0,COUNTIF($M$10:M74,M74)) -> 56 | F74: 46051 | G74: 7 | I74: Penjualan Retail | J74: =IF(K74=0,"",VLOOKUP(K74,Tarkun,2,0)) -> Kas | K74: 11100 | M74: =IF(L74=0," ",(VLOOKUP(L74,Kode!$B$10:$E$423,4,0))) | N74: 26724400 | P74: =IF(K74="","",IF(AND(K74>0,$M$602=0),"Balance","Unbalance")) -> Balance
A75: =B75&K75 -> 922105 | B75: =IF(ERR=TRUE,COUNTIF($K$10:K75,K75),0) -> 9 | C75: =D75&M75 -> 57 | D75: =IF(ERR=FALSE,0,COUNTIF($M$10:M75,M75)) -> 57 | F75: 46051 | G75: 7 | I75: Penjualan Retail | J75: =IF(K75=0,"",VLOOKUP(K75,Tarkun,2,0)) -> PPN Keluaran | K75: 22105 | M75: =IF(L75=0," ",(VLOOKUP(L75,Kode!$B$10:$E$423,4,0))) | O75: 2648364 | P75: =IF(K75="","",IF(AND(K75>0,$M$602=0),"Balance","Unbalance")) -> Balance
A76: =B76&K76 -> 941000 | B76: =IF(ERR=TRUE,COUNTIF($K$10:K76,K76),0) -> 9 | C76: =D76&M76 -> 58 | D76: =IF(ERR=FALSE,0,COUNTIF($M$10:M76,M76)) -> 58 | F76: 46051 | G76: 7 | I76: Penjualan Retail | J76: =IF(K76=0,"",VLOOKUP(K76,Tarkun,2,0)) -> Penjualan Barang | K76: 41000 | M76: =IF(L76=0," ",(VLOOKUP(L76,Kode!$B$10:$E$423,4,0))) | O76: 24076036 | P76: =IF(K76="","",IF(AND(K76>0,$M$602=0),"Balance","Unbalance")) -> Balance
A77: =B77&K77 -> 511102 | B77: =IF(ERR=TRUE,COUNTIF($K$10:K77,K77),0) -> 5 | C77: =D77&M77 -> 59 | D77: =IF(ERR=FALSE,0,COUNTIF($M$10:M77,M77)) -> 59 | F77: 46050 | G77: 7 | H77: 04002600002202364 | I77: Penjualan ke Djarum, PT | J77: =IF(K77=0,"",VLOOKUP(K77,Tarkun,2,0)) -> Piutang Dagang | K77: 11102 | M77: =IF(L77=0," ",(VLOOKUP(L77,Kode!$B$10:$E$423,4,0))) | N77: 194250 | P77: =IF(K77="","",IF(AND(K77>0,$M$602=0),"Balance","Unbalance")) -> Balance
A78: =B78&K78 -> 1022105 | B78: =IF(ERR=TRUE,COUNTIF($K$10:K78,K78),0) -> 10 | C78: =D78&M78 -> 60 | D78: =IF(ERR=FALSE,0,COUNTIF($M$10:M78,M78)) -> 60 | F78: 46051 | G78: 7 | H78: 04002600002202364 | I78: Penjualan ke Djarum, PT | J78: =IF(K78=0,"",VLOOKUP(K78,Tarkun,2,0)) -> PPN Keluaran | K78: 22105 | M78: =IF(L78=0," ",(VLOOKUP(L78,Kode!$B$10:$E$423,4,0))) | O78: 19250 | P78: =IF(K78="","",IF(AND(K78>0,$M$602=0),"Balance","Unbalance")) -> Balance
A79: =B79&K79 -> 1041000 | B79: =IF(ERR=TRUE,COUNTIF($K$10:K79,K79),0) -> 10 | C79: =D79&M79 -> 61 | D79: =IF(ERR=FALSE,0,COUNTIF($M$10:M79,M79)) -> 61 | F79: 46052 | G79: 7 | H79: 04002600002202364 | I79: Penjualan ke Djarum, PT | J79: =IF(K79=0,"",VLOOKUP(K79,Tarkun,2,0)) -> Penjualan Barang | K79: 41000 | M79: =IF(L79=0," ",(VLOOKUP(L79,Kode!$B$10:$E$423,4,0))) | O79: 175000 | P79: =IF(K79="","",IF(AND(K79>0,$M$602=0),"Balance","Unbalance")) -> Balance
A80: =B80&K80 -> 611102 | B80: =IF(ERR=TRUE,COUNTIF($K$10:K80,K80),0) -> 6 | C80: =D80&M80 -> 62 | D80: =IF(ERR=FALSE,0,COUNTIF($M$10:M80,M80)) -> 62 | F80: 46051 | G80: 7 | H80: 04002600002204673 | I80: Penjualan ke Djarum, PT | J80: =IF(K80=0,"",VLOOKUP(K80,Tarkun,2,0)) -> Piutang Dagang | K80: 11102 | M80: =IF(L80=0," ",(VLOOKUP(L80,Kode!$B$10:$E$423,4,0))) | N80: 460650 | P80: =IF(K80="","",IF(AND(K80>0,$M$602=0),"Balance","Unbalance")) -> Balance
A81: =B81&K81 -> 1122105 | B81: =IF(ERR=TRUE,COUNTIF($K$10:K81,K81),0) -> 11 | C81: =D81&M81 -> 63 | D81: =IF(ERR=FALSE,0,COUNTIF($M$10:M81,M81)) -> 63 | F81: 46051 | G81: 7 | H81: 04002600002204673 | I81: Penjualan ke Djarum, PT | J81: =IF(K81=0,"",VLOOKUP(K81,Tarkun,2,0)) -> PPN Keluaran | K81: 22105 | M81: =IF(L81=0," ",(VLOOKUP(L81,Kode!$B$10:$E$423,4,0))) | O81: 45650 | P81: =IF(K81="","",IF(AND(K81>0,$M$602=0),"Balance","Unbalance")) -> Balance
A82: =B82&K82 -> 1141000 | B82: =IF(ERR=TRUE,COUNTIF($K$10:K82,K82),0) -> 11 | C82: =D82&M82 -> 64 | D82: =IF(ERR=FALSE,0,COUNTIF($M$10:M82,M82)) -> 64 | F82: 46051 | G82: 7 | H82: 04002600002204673 | I82: Penjualan ke Djarum, PT | J82: =IF(K82=0,"",VLOOKUP(K82,Tarkun,2,0)) -> Penjualan Barang | K82: 41000 | M82: =IF(L82=0," ",(VLOOKUP(L82,Kode!$B$10:$E$423,4,0))) | O82: 415000 | P82: =IF(K82="","",IF(AND(K82>0,$M$602=0),"Balance","Unbalance")) -> Balance
A83: =B83&K83 -> 1021100 | B83: =IF(ERR=TRUE,COUNTIF($K$10:K83,K83),0) -> 10 | C83: =D83&M83 -> 2H-012 | D83: =IF(ERR=FALSE,0,COUNTIF($M$10:M83,M83)) -> 2 | F83: 46051 | G83: 7 | I83: Bayar Hutang Omega 06/01 04002600006401523 | J83: =IF(K83=0,"",VLOOKUP(K83,Tarkun,2,0)) -> Hutang Dagang | K83: 21100 | L83: Omega Garda Rupla, PT | M83: =IF(L83=0," ",(VLOOKUP(L83,Kode!$B$10:$E$423,4,0))) -> H-012 | N83: 4000000 | P83: =IF(K83="","",IF(AND(K83>0,$M$602=0),"Balance","Unbalance")) -> Balance
A84: =B84&K84 -> 911100 | B84: =IF(ERR=TRUE,COUNTIF($K$10:K84,K84),0) -> 9 | C84: =D84&M84 -> 65 | D84: =IF(ERR=FALSE,0,COUNTIF($M$10:M84,M84)) -> 65 | F84: 46051 | G84: 7 | I84: Bayar Hutang Omega 06/01 04002600006401523 | J84: =IF(K84=0,"",VLOOKUP(K84,Tarkun,2,0)) -> Kas | K84: 11100 | M84: =IF(L84=0," ",(VLOOKUP(L84,Kode!$B$10:$E$423,4,0))) | O84: 4000000 | P84: =IF(K84="","",IF(AND(K84>0,$M$602=0),"Balance","Unbalance")) -> Balance
A85: =B85&K85 -> 164002 | B85: =IF(ERR=TRUE,COUNTIF($K$10:K85,K85),0) -> 1 | C85: =D85&M85 -> 66 | D85: =IF(ERR=FALSE,0,COUNTIF($M$10:M85,M85)) -> 66 | F85: 46051 | G85: 7 | I85: B. Adm Bayar Hutang Omega 06/01 04002600006401523 | J85: =IF(K85=0,"",VLOOKUP(K85,Tarkun,2,0)) -> Biaya Administrasi Bank | K85: 64002 | M85: =IF(L85=0," ",(VLOOKUP(L85,Kode!$B$10:$E$423,4,0))) | N85: 2500 | P85: =IF(K85="","",IF(AND(K85>0,$M$602=0),"Balance","Unbalance")) -> Balance
A86: =B86&K86 -> 1011100 | B86: =IF(ERR=TRUE,COUNTIF($K$10:K86,K86),0) -> 10 | C86: =D86&M86 -> 67 | D86: =IF(ERR=FALSE,0,COUNTIF($M$10:M86,M86)) -> 67 | F86: 46051 | G86: 7 | I86: B. Adm Bayar Hutang Omega 06/01 04002600006401523 | J86: =IF(K86=0,"",VLOOKUP(K86,Tarkun,2,0)) -> Kas | K86: 11100 | M86: =IF(L86=0," ",(VLOOKUP(L86,Kode!$B$10:$E$423,4,0))) | O86: 2500 | P86: =IF(K86="","",IF(AND(K86>0,$M$602=0),"Balance","Unbalance")) -> Balance
A87: =B87&K87 -> 161002 | B87: =IF(ERR=TRUE,COUNTIF($K$10:K87,K87),0) -> 1 | C87: =D87&M87 -> 68 | D87: =IF(ERR=FALSE,0,COUNTIF($M$10:M87,M87)) -> 68 | F87: 46051 | G87: 7 | I87: BPJS Tng Kerja | J87: =IF(K87=0,"",VLOOKUP(K87,Tarkun,2,0)) -> Asuransi Tenaga Kerja | K87: 61002 | M87: =IF(L87=0," ",(VLOOKUP(L87,Kode!$B$10:$E$423,4,0))) | N87: 3565575 | P87: =IF(K87="","",IF(AND(K87>0,$M$602=0),"Balance","Unbalance")) -> Balance
A88: =B88&K88 -> 1111100 | B88: =IF(ERR=TRUE,COUNTIF($K$10:K88,K88),0) -> 11 | C88: =D88&M88 -> 69 | D88: =IF(ERR=FALSE,0,COUNTIF($M$10:M88,M88)) -> 69 | F88: 46051 | G88: 7 | I88: BPJS Tng Kerja | J88: =IF(K88=0,"",VLOOKUP(K88,Tarkun,2,0)) -> Kas | K88: 11100 | M88: =IF(L88=0," ",(VLOOKUP(L88,Kode!$B$10:$E$423,4,0))) | O88: 3565575 | P88: =IF(K88="","",IF(AND(K88>0,$M$602=0),"Balance","Unbalance")) -> Balance
A89: =B89&K89 -> 261002 | B89: =IF(ERR=TRUE,COUNTIF($K$10:K89,K89),0) -> 2 | C89: =D89&M89 -> 70 | D89: =IF(ERR=FALSE,0,COUNTIF($M$10:M89,M89)) -> 70 | F89: 46051 | G89: 7 | I89: BPJS Kesehatan | J89: =IF(K89=0,"",VLOOKUP(K89,Tarkun,2,0)) -> Asuransi Tenaga Kerja | K89: 61002 | M89: =IF(L89=0," ",(VLOOKUP(L89,Kode!$B$10:$E$423,4,0))) | N89: 6562500 | P89: =IF(K89="","",IF(AND(K89>0,$M$602=0),"Balance","Unbalance")) -> Balance
A90: =B90&K90 -> 1211100 | B90: =IF(ERR=TRUE,COUNTIF($K$10:K90,K90),0) -> 12 | C90: =D90&M90 -> 71 | D90: =IF(ERR=FALSE,0,COUNTIF($M$10:M90,M90)) -> 71 | F90: 46051 | G90: 7 | I90: BPJS Kesehatan | J90: =IF(K90=0,"",VLOOKUP(K90,Tarkun,2,0)) -> Kas | K90: 11100 | M90: =IF(L90=0," ",(VLOOKUP(L90,Kode!$B$10:$E$423,4,0))) | O90: 6562500 | P90: =IF(K90="","",IF(AND(K90>0,$M$602=0),"Balance","Unbalance")) -> Balance
A91: =B91&K91 -> 1311100 | B91: =IF(ERR=TRUE,COUNTIF($K$10:K91,K91),0) -> 13 | C91: =D91&M91 -> 72 | D91: =IF(ERR=FALSE,0,COUNTIF($M$10:M91,M91)) -> 72 | F91: 46051 | G91: 7 | I91: Pembayaran Piutang Wook Des'26 | J91: =IF(K91=0,"",VLOOKUP(K91,Tarkun,2,0)) -> Kas | K91: 11100 | M91: =IF(L91=0," ",(VLOOKUP(L91,Kode!$B$10:$E$423,4,0))) | N91: 511864 | P91: =IF(K91="","",IF(AND(K91>0,$M$602=0),"Balance","Unbalance")) -> Balance
A92: =B92&K92 -> 111403 | B92: =IF(ERR=TRUE,COUNTIF($K$10:K92,K92),0) -> 1 | C92: =D92&M92 -> 73 | D92: =IF(ERR=FALSE,0,COUNTIF($M$10:M92,M92)) -> 73 | F92: 46051 | G92: 7 | I92: Pembayaran Piutang Wook Des'26 | J92: =IF(K92=0,"",VLOOKUP(K92,Tarkun,2,0)) -> Pph Pasal 23 | K92: 11403 | M92: =IF(L92=0," ",(VLOOKUP(L92,Kode!$B$10:$E$423,4,0))) | N92: 9392 | P92: =IF(K92="","",IF(AND(K92>0,$M$602=0),"Balance","Unbalance")) -> Balance
A93: =B93&K93 -> 711102 | B93: =IF(ERR=TRUE,COUNTIF($K$10:K93,K93),0) -> 7 | C93: =D93&M93 -> 1P-011 | D93: =IF(ERR=FALSE,0,COUNTIF($M$10:M93,M93)) -> 1 | F93: 46051 | G93: 7 | I93: Pembayaran Piutang Wook Des'26 | J93: =IF(K93=0,"",VLOOKUP(K93,Tarkun,2,0)) -> Piutang Dagang | K93: 11102 | L93: WOOK GLOBAL TECHNOLOGY | M93: =IF(L93=0," ",(VLOOKUP(L93,Kode!$B$10:$E$423,4,0))) -> P-011 | O93: 521256 | P93: =IF(K93="","",IF(AND(K93>0,$M$602=0),"Balance","Unbalance")) -> Balance
A94: =B94&K94 -> 0 | B94: =IF(ERR=TRUE,COUNTIF($K$10:K94,K94),0) -> 0 | C94: =D94&M94 -> 74 | D94: =IF(ERR=FALSE,0,COUNTIF($M$10:M94,M94)) -> 74 | F94: 46051 | J94: =IF(K94=0,"",VLOOKUP(K94,Tarkun,2,0)) | M94: =IF(L94=0," ",(VLOOKUP(L94,Kode!$B$10:$E$423,4,0))) | P94: =IF(K94="","",IF(AND(K94>0,$M$602=0),"Balance","Unbalance"))
A95: =B95&K95 -> 1411100 | B95: =IF(ERR=TRUE,COUNTIF($K$10:K95,K95),0) -> 14 | C95: =D95&M95 -> 75 | D95: =IF(ERR=FALSE,0,COUNTIF($M$10:M95,M95)) -> 75 | F95: 46051 | G95: 8 | I95: Penjualan Retail | J95: =IF(K95=0,"",VLOOKUP(K95,Tarkun,2,0)) -> Kas | K95: 11100 | M95: =IF(L95=0," ",(VLOOKUP(L95,Kode!$B$10:$E$423,4,0))) | N95: 28238700 | P95: =IF(K95="","",IF(AND(K95>0,$M$602=0),"Balance","Unbalance")) -> Balance
A96: =B96&K96 -> 1222105 | B96: =IF(ERR=TRUE,COUNTIF($K$10:K96,K96),0) -> 12 | C96: =D96&M96 -> 76 | D96: =IF(ERR=FALSE,0,COUNTIF($M$10:M96,M96)) -> 76 | F96: 46051 | G96: 8 | I96: Penjualan Retail | J96: =IF(K96=0,"",VLOOKUP(K96,Tarkun,2,0)) -> PPN Keluaran | K96: 22105 | M96: =IF(L96=0," ",(VLOOKUP(L96,Kode!$B$10:$E$423,4,0))) | O96: 2798429.7 | P96: =IF(K96="","",IF(AND(K96>0,$M$602=0),"Balance","Unbalance")) -> Balance
A97: =B97&K97 -> 1241000 | B97: =IF(ERR=TRUE,COUNTIF($K$10:K97,K97),0) -> 12 | C97: =D97&M97 -> 77 | D97: =IF(ERR=FALSE,0,COUNTIF($M$10:M97,M97)) -> 77 | F97: 46051 | G97: 8 | I97: Penjualan Retail | J97: =IF(K97=0,"",VLOOKUP(K97,Tarkun,2,0)) -> Penjualan Barang | K97: 41000 | M97: =IF(L97=0," ",(VLOOKUP(L97,Kode!$B$10:$E$423,4,0))) | O97: 25440270 | P97: =IF(K97="","",IF(AND(K97>0,$M$602=0),"Balance","Unbalance")) -> Balance
A98: =B98&K98 -> 811102 | B98: =IF(ERR=TRUE,COUNTIF($K$10:K98,K98),0) -> 8 | C98: =D98&M98 -> 78 | D98: =IF(ERR=FALSE,0,COUNTIF($M$10:M98,M98)) -> 78 | F98: 46051 | G98: 8 | H98: 04002600002816752 | I98: Penjualan ke Mirota KSM, PT | J98: =IF(K98=0,"",VLOOKUP(K98,Tarkun,2,0)) -> Piutang Dagang | K98: 11102 | M98: =IF(L98=0," ",(VLOOKUP(L98,Kode!$B$10:$E$423,4,0))) | N98: 255300 | P98: =IF(K98="","",IF(AND(K98>0,$M$602=0),"Balance","Unbalance")) -> Balance
A99: =B99&K99 -> 1322105 | B99: =IF(ERR=TRUE,COUNTIF($K$10:K99,K99),0) -> 13 | C99: =D99&M99 -> 79 | D99: =IF(ERR=FALSE,0,COUNTIF($M$10:M99,M99)) -> 79 | F99: 46051 | G99: 8 | H99: 04002600002816752 | I99: Penjualan ke Mirota KSM, PT | J99: =IF(K99=0,"",VLOOKUP(K99,Tarkun,2,0)) -> PPN Keluaran | K99: 22105 | M99: =IF(L99=0," ",(VLOOKUP(L99,Kode!$B$10:$E$423,4,0))) | O99: 25300 | P99: =IF(K99="","",IF(AND(K99>0,$M$602=0),"Balance","Unbalance")) -> Balance
A100: =B100&K100 -> 1341000 | B100: =IF(ERR=TRUE,COUNTIF($K$10:K100,K100),0) -> 13 | C100: =D100&M100 -> 80 | D100: =IF(ERR=FALSE,0,COUNTIF($M$10:M100,M100)) -> 80 | F100: 46051 | G100: 8 | H100: 04002600002816752 | I100: Penjualan ke Mirota KSM, PT | J100: =IF(K100=0,"",VLOOKUP(K100,Tarkun,2,0)) -> Penjualan Barang | K100: 41000 | M100: =IF(L100=0," ",(VLOOKUP(L100,Kode!$B$10:$E$423,4,0))) | O100: 230000 | P100: =IF(K100="","",IF(AND(K100>0,$M$602=0),"Balance","Unbalance")) -> Balance
A101: =B101&K101 -> 1011600 | B101: =IF(ERR=TRUE,COUNTIF($K$10:K101,K101),0) -> 10 | C101: =D101&M101 -> 81 | D101: =IF(ERR=FALSE,0,COUNTIF($M$10:M101,M101)) -> 81 | F101: 46051 | G101: 8 | H101: 04002600005706377 | I101: Pembelian BB ke Multiviscomindo, PT | J101: =IF(K101=0,"",VLOOKUP(K101,Tarkun,2,0)) -> PPN Masukan | K101: 11600 | M101: =IF(L101=0," ",(VLOOKUP(L101,Kode!$B$10:$E$423,4,0))) | N101: 32846183 | P101: =IF(K101="","",IF(AND(K101>0,$M$602=0),"Balance","Unbalance")) -> Balance
...

Sheet Bk Piutang
A1: ='Data GL'!E6 -> CV. SPEKTRA DIGITAL ARTWORK
A2: ='Data GL'!E4 -> PERCETAKAN
A3: ='Data GL'!E5 -> JL. Prof Dr. Yohannes 1099 YK
A5: BUKU BESAR PIUTANG DAGANG
A6: =CONCATENATE('Data GL'!E7," -"," TAHUN"," ",'Data GL'!E8) -> Jan - TAHUN 2026
A8: Kode Pembantu | D8: =IF(F8=0," ",(VLOOKUP(F8,Kode!$B$10:$E$188,4,0))) -> #N/A | F8: Artindo Grafika Printing, PT
A10: No | B10: Tanggal | D10: Bukti | E10: Keterangan | F10: Debet | G10: Kredit | H10: Saldo
E11: Saldo Awal | F11: =VLOOKUP(D8,Kode!$E$10:$F$412,2,FALSE) -> #N/A | G11: 0 | H11: =SUM(F11:G11) -> #N/A
A12: =A11+1 -> 1 | B12: =IF(ISERROR(VLOOKUP(A12&D$8,JU_KODE,4,FALSE)=TRUE),"",VLOOKUP(A12&D$8,JU_KODE,4,FALSE)) | C12: =IF(ISERROR(VLOOKUP(A12&D$8,JU_KODE,5,FALSE)=TRUE),"",VLOOKUP(A12&D$8,JU_KODE,5,FALSE)) | D12: =IF(ISERROR(VLOOKUP(A12&D$8,JU_KODE,6,FALSE)=TRUE),"",VLOOKUP(A12&D$8,JU_KODE,6,FALSE)) | E12: =IF(ISERROR(VLOOKUP(A12&D$8,JU_KODE,7,FALSE)=TRUE),"",VLOOKUP(A12&D$8,JU_KODE,7,FALSE)) | F12: =IF(ISERROR(VLOOKUP(A12&D$8,JU_KODE,12,FALSE)=TRUE),"",VLOOKUP(A12&D$8,JU_KODE,12,FALSE)) | G12: =IF(ISERROR(VLOOKUP(A12&D$8,JU_KODE,13,FALSE)=TRUE),"",VLOOKUP(A12&D$8,JU_KODE,13,FALSE)) | H12: =IF(OR(ERR=FALSE,AND(F12="",G12="")),0,$F$11+SUM($F$12:F12)-SUM($G$12:G12)) -> 0
A13: =A12+1 -> 2 | B13: =IF(ISERROR(VLOOKUP(A13&D$8,JU_KODE,4,FALSE)=TRUE),"",VLOOKUP(A13&D$8,JU_KODE,4,FALSE)) | C13: =IF(ISERROR(VLOOKUP(A13&D$8,JU_KODE,5,FALSE)=TRUE),"",VLOOKUP(A13&D$8,JU_KODE,5,FALSE)) | D13: =IF(ISERROR(VLOOKUP(A13&D$8,JU_KODE,6,FALSE)=TRUE),"",VLOOKUP(A13&D$8,JU_KODE,6,FALSE)) | E13: =IF(ISERROR(VLOOKUP(A13&D$8,JU_KODE,7,FALSE)=TRUE),"",VLOOKUP(A13&D$8,JU_KODE,7,FALSE)) | F13: =IF(ISERROR(VLOOKUP(A13&D$8,JU_KODE,12,FALSE)=TRUE),"",VLOOKUP(A13&D$8,JU_KODE,12,FALSE)) | G13: =IF(ISERROR(VLOOKUP(A13&D$8,JU_KODE,13,FALSE)=TRUE),"",VLOOKUP(A13&D$8,JU_KODE,13,FALSE)) | H13: =IF(OR(ERR=FALSE,AND(F13="",G13="")),0,$F$11+SUM($F$12:F13)-SUM($G$12:G13)) -> 0
A14: =A13+1 -> 3 | B14: =IF(ISERROR(VLOOKUP(A14&D$8,JU_KODE,4,FALSE)=TRUE),"",VLOOKUP(A14&D$8,JU_KODE,4,FALSE)) | C14: =IF(ISERROR(VLOOKUP(A14&D$8,JU_KODE,5,FALSE)=TRUE),"",VLOOKUP(A14&D$8,JU_KODE,5,FALSE)) | D14: =IF(ISERROR(VLOOKUP(A14&D$8,JU_KODE,6,FALSE)=TRUE),"",VLOOKUP(A14&D$8,JU_KODE,6,FALSE)) | E14: =IF(ISERROR(VLOOKUP(A14&D$8,JU_KODE,7,FALSE)=TRUE),"",VLOOKUP(A14&D$8,JU_KODE,7,FALSE)) | F14: =IF(ISERROR(VLOOKUP(A14&D$8,JU_KODE,12,FALSE)=TRUE),"",VLOOKUP(A14&D$8,JU_KODE,12,FALSE)) | G14: =IF(ISERROR(VLOOKUP(A14&D$8,JU_KODE,13,FALSE)=TRUE),"",VLOOKUP(A14&D$8,JU_KODE,13,FALSE)) | H14: =IF(OR(ERR=FALSE,AND(F14="",G14="")),0,$F$11+SUM($F$12:F14)-SUM($G$12:G14)) -> 0
A15: =A14+1 -> 4 | B15: =IF(ISERROR(VLOOKUP(A15&D$8,JU_KODE,4,FALSE)=TRUE),"",VLOOKUP(A15&D$8,JU_KODE,4,FALSE)) | C15: =IF(ISERROR(VLOOKUP(A15&D$8,JU_KODE,5,FALSE)=TRUE),"",VLOOKUP(A15&D$8,JU_KODE,5,FALSE)) | D15: =IF(ISERROR(VLOOKUP(A15&D$8,JU_KODE,6,FALSE)=TRUE),"",VLOOKUP(A15&D$8,JU_KODE,6,FALSE)) | E15: =IF(ISERROR(VLOOKUP(A15&D$8,JU_KODE,7,FALSE)=TRUE),"",VLOOKUP(A15&D$8,JU_KODE,7,FALSE)) | F15: =IF(ISERROR(VLOOKUP(A15&D$8,JU_KODE,12,FALSE)=TRUE),"",VLOOKUP(A15&D$8,JU_KODE,12,FALSE)) | G15: =IF(ISERROR(VLOOKUP(A15&D$8,JU_KODE,13,FALSE)=TRUE),"",VLOOKUP(A15&D$8,JU_KODE,13,FALSE)) | H15: =IF(OR(ERR=FALSE,AND(F15="",G15="")),0,$F$11+SUM($F$12:F15)-SUM($G$12:G15)) -> 0
A16: =A15+1 -> 5 | B16: =IF(ISERROR(VLOOKUP(A16&D$8,JU_KODE,4,FALSE)=TRUE),"",VLOOKUP(A16&D$8,JU_KODE,4,FALSE)) | C16: =IF(ISERROR(VLOOKUP(A16&D$8,JU_KODE,5,FALSE)=TRUE),"",VLOOKUP(A16&D$8,JU_KODE,5,FALSE)) | D16: =IF(ISERROR(VLOOKUP(A16&D$8,JU_KODE,6,FALSE)=TRUE),"",VLOOKUP(A16&D$8,JU_KODE,6,FALSE)) | E16: =IF(ISERROR(VLOOKUP(A16&D$8,JU_KODE,7,FALSE)=TRUE),"",VLOOKUP(A16&D$8,JU_KODE,7,FALSE)) | F16: =IF(ISERROR(VLOOKUP(A16&D$8,JU_KODE,12,FALSE)=TRUE),"",VLOOKUP(A16&D$8,JU_KODE,12,FALSE)) | G16: =IF(ISERROR(VLOOKUP(A16&D$8,JU_KODE,13,FALSE)=TRUE),"",VLOOKUP(A16&D$8,JU_KODE,13,FALSE)) | H16: =IF(OR(ERR=FALSE,AND(F16="",G16="")),0,$F$11+SUM($F$12:F16)-SUM($G$12:G16)) -> 0
A17: =A16+1 -> 6 | B17: =IF(ISERROR(VLOOKUP(A17&D$8,JU_KODE,4,FALSE)=TRUE),"",VLOOKUP(A17&D$8,JU_KODE,4,FALSE)) | C17: =IF(ISERROR(VLOOKUP(A17&D$8,JU_KODE,5,FALSE)=TRUE),"",VLOOKUP(A17&D$8,JU_KODE,5,FALSE)) | D17: =IF(ISERROR(VLOOKUP(A17&D$8,JU_KODE,6,FALSE)=TRUE),"",VLOOKUP(A17&D$8,JU_KODE,6,FALSE)) | E17: =IF(ISERROR(VLOOKUP(A17&D$8,JU_KODE,7,FALSE)=TRUE),"",VLOOKUP(A17&D$8,JU_KODE,7,FALSE)) | F17: =IF(ISERROR(VLOOKUP(A17&D$8,JU_KODE,12,FALSE)=TRUE),"",VLOOKUP(A17&D$8,JU_KODE,12,FALSE)) | G17: =IF(ISERROR(VLOOKUP(A17&D$8,JU_KODE,13,FALSE)=TRUE),"",VLOOKUP(A17&D$8,JU_KODE,13,FALSE)) | H17: =IF(OR(ERR=FALSE,AND(F17="",G17="")),0,$F$11+SUM($F$12:F17)-SUM($G$12:G17)) -> 0
A18: =A17+1 -> 7 | B18: =IF(ISERROR(VLOOKUP(A18&D$8,JU_KODE,4,FALSE)=TRUE),"",VLOOKUP(A18&D$8,JU_KODE,4,FALSE)) | C18: =IF(ISERROR(VLOOKUP(A18&D$8,JU_KODE,5,FALSE)=TRUE),"",VLOOKUP(A18&D$8,JU_KODE,5,FALSE)) | D18: =IF(ISERROR(VLOOKUP(A18&D$8,JU_KODE,6,FALSE)=TRUE),"",VLOOKUP(A18&D$8,JU_KODE,6,FALSE)) | E18: =IF(ISERROR(VLOOKUP(A18&D$8,JU_KODE,7,FALSE)=TRUE),"",VLOOKUP(A18&D$8,JU_KODE,7,FALSE)) | F18: =IF(ISERROR(VLOOKUP(A18&D$8,JU_KODE,12,FALSE)=TRUE),"",VLOOKUP(A18&D$8,JU_KODE,12,FALSE)) | G18: =IF(ISERROR(VLOOKUP(A18&D$8,JU_KODE,13,FALSE)=TRUE),"",VLOOKUP(A18&D$8,JU_KODE,13,FALSE)) | H18: =IF(OR(ERR=FALSE,AND(F18="",G18="")),0,$F$11+SUM($F$12:F18)-SUM($G$12:G18)) -> 0
A19: =A18+1 -> 8 | B19: =IF(ISERROR(VLOOKUP(A19&D$8,JU_KODE,4,FALSE)=TRUE),"",VLOOKUP(A19&D$8,JU_KODE,4,FALSE)) | C19: =IF(ISERROR(VLOOKUP(A19&D$8,JU_KODE,5,FALSE)=TRUE),"",VLOOKUP(A19&D$8,JU_KODE,5,FALSE)) | D19: =IF(ISERROR(VLOOKUP(A19&D$8,JU_KODE,6,FALSE)=TRUE),"",VLOOKUP(A19&D$8,JU_KODE,6,FALSE)) | E19: =IF(ISERROR(VLOOKUP(A19&D$8,JU_KODE,7,FALSE)=TRUE),"",VLOOKUP(A19&D$8,JU_KODE,7,FALSE)) | F19: =IF(ISERROR(VLOOKUP(A19&D$8,JU_KODE,12,FALSE)=TRUE),"",VLOOKUP(A19&D$8,JU_KODE,12,FALSE)) | G19: =IF(ISERROR(VLOOKUP(A19&D$8,JU_KODE,13,FALSE)=TRUE),"",VLOOKUP(A19&D$8,JU_KODE,13,FALSE)) | H19: =IF(OR(ERR=FALSE,AND(F19="",G19="")),0,$F$11+SUM($F$12:F19)-SUM($G$12:G19)) -> 0
A20: =A19+1 -> 9 | B20: =IF(ISERROR(VLOOKUP(A20&D$8,JU_KODE,4,FALSE)=TRUE),"",VLOOKUP(A20&D$8,JU_KODE,4,FALSE)) | C20: =IF(ISERROR(VLOOKUP(A20&D$8,JU_KODE,5,FALSE)=TRUE),"",VLOOKUP(A20&D$8,JU_KODE,5,FALSE)) | D20: =IF(ISERROR(VLOOKUP(A20&D$8,JU_KODE,6,FALSE)=TRUE),"",VLOOKUP(A20&D$8,JU_KODE,6,FALSE)) | E20: =IF(ISERROR(VLOOKUP(A20&D$8,JU_KODE,7,FALSE)=TRUE),"",VLOOKUP(A20&D$8,JU_KODE,7,FALSE)) | F20: =IF(ISERROR(VLOOKUP(A20&D$8,JU_KODE,12,FALSE)=TRUE),"",VLOOKUP(A20&D$8,JU_KODE,12,FALSE)) | G20: =IF(ISERROR(VLOOKUP(A20&D$8,JU_KODE,13,FALSE)=TRUE),"",VLOOKUP(A20&D$8,JU_KODE,13,FALSE)) | H20: =IF(OR(ERR=FALSE,AND(F20="",G20="")),0,$F$11+SUM($F$12:F20)-SUM($G$12:G20)) -> 0
A21: =A20+1 -> 10 | B21: =IF(ISERROR(VLOOKUP(A21&D$8,JU_KODE,4,FALSE)=TRUE),"",VLOOKUP(A21&D$8,JU_KODE,4,FALSE)) | C21: =IF(ISERROR(VLOOKUP(A21&D$8,JU_KODE,5,FALSE)=TRUE),"",VLOOKUP(A21&D$8,JU_KODE,5,FALSE)) | D21: =IF(ISERROR(VLOOKUP(A21&D$8,JU_KODE,6,FALSE)=TRUE),"",VLOOKUP(A21&D$8,JU_KODE,6,FALSE)) | E21: =IF(ISERROR(VLOOKUP(A21&D$8,JU_KODE,7,FALSE)=TRUE),"",VLOOKUP(A21&D$8,JU_KODE,7,FALSE)) | F21: =IF(ISERROR(VLOOKUP(A21&D$8,JU_KODE,12,FALSE)=TRUE),"",VLOOKUP(A21&D$8,JU_KODE,12,FALSE)) | G21: =IF(ISERROR(VLOOKUP(A21&D$8,JU_KODE,13,FALSE)=TRUE),"",VLOOKUP(A21&D$8,JU_KODE,13,FALSE)) | H21: =IF(OR(ERR=FALSE,AND(F21="",G21="")),0,$F$11+SUM($F$12:F21)-SUM($G$12:G21)) -> 0
A22: =A21+1 -> 11 | B22: =IF(ISERROR(VLOOKUP(A22&D$8,JU_KODE,4,FALSE)=TRUE),"",VLOOKUP(A22&D$8,JU_KODE,4,FALSE)) | C22: =IF(ISERROR(VLOOKUP(A22&D$8,JU_KODE,5,FALSE)=TRUE),"",VLOOKUP(A22&D$8,JU_KODE,5,FALSE)) | D22: =IF(ISERROR(VLOOKUP(A22&D$8,JU_KODE,6,FALSE)=TRUE),"",VLOOKUP(A22&D$8,JU_KODE,6,FALSE)) | E22: =IF(ISERROR(VLOOKUP(A22&D$8,JU_KODE,7,FALSE)=TRUE),"",VLOOKUP(A22&D$8,JU_KODE,7,FALSE)) | F22: =IF(ISERROR(VLOOKUP(A22&D$8,JU_KODE,12,FALSE)=TRUE),"",VLOOKUP(A22&D$8,JU_KODE,12,FALSE)) | G22: =IF(ISERROR(VLOOKUP(A22&D$8,JU_KODE,13,FALSE)=TRUE),"",VLOOKUP(A22&D$8,JU_KODE,13,FALSE)) | H22: =IF(OR(ERR=FALSE,AND(F22="",G22="")),0,$F$11+SUM($F$12:F22)-SUM($G$12:G22)) -> 0
A23: =A22+1 -> 12 | B23: =IF(ISERROR(VLOOKUP(A23&D$8,JU_KODE,4,FALSE)=TRUE),"",VLOOKUP(A23&D$8,JU_KODE,4,FALSE)) | C23: =IF(ISERROR(VLOOKUP(A23&D$8,JU_KODE,5,FALSE)=TRUE),"",VLOOKUP(A23&D$8,JU_KODE,5,FALSE)) | D23: =IF(ISERROR(VLOOKUP(A23&D$8,JU_KODE,6,FALSE)=TRUE),"",VLOOKUP(A23&D$8,JU_KODE,6,FALSE)) | E23: =IF(ISERROR(VLOOKUP(A23&D$8,JU_KODE,7,FALSE)=TRUE),"",VLOOKUP(A23&D$8,JU_KODE,7,FALSE)) | F23: =IF(ISERROR(VLOOKUP(A23&D$8,JU_KODE,12,FALSE)=TRUE),"",VLOOKUP(A23&D$8,JU_KODE,12,FALSE)) | G23: =IF(ISERROR(VLOOKUP(A23&D$8,JU_KODE,13,FALSE)=TRUE),"",VLOOKUP(A23&D$8,JU_KODE,13,FALSE)) | H23: =IF(OR(ERR=FALSE,AND(F23="",G23="")),0,$F$11+SUM($F$12:F23)-SUM($G$12:G23)) -> 0
... A223: =A222+1 -> 212 | B223: =IF(ISERROR(VLOOKUP(A223&D$8,JU_KODE,4,FALSE)=TRUE),"",VLOOKUP(A223&D$8,JU_KODE,4,FALSE)) | C223: =IF(ISERROR(VLOOKUP(A223&D$8,JU_KODE,5,FALSE)=TRUE),"",VLOOKUP(A223&D$8,JU_KODE,5,FALSE)) | D223: =IF(ISERROR(VLOOKUP(A223&D$8,JU_KODE,6,FALSE)=TRUE),"",VLOOKUP(A223&D$8,JU_KODE,6,FALSE)) | E223: =IF(ISERROR(VLOOKUP(A223&D$8,JU_KODE,7,FALSE)=TRUE),"",VLOOKUP(A223&D$8,JU_KODE,7,FALSE)) | F223: =IF(ISERROR(VLOOKUP(A223&D$8,JU_KODE,12,FALSE)=TRUE),"",VLOOKUP(A223&D$8,JU_KODE,12,FALSE)) | G223: =IF(ISERROR(VLOOKUP(A223&D$8,JU_KODE,13,FALSE)=TRUE),"",VLOOKUP(A223&D$8,JU_KODE,13,FALSE)) | H223: =IF(OR(ERR=FALSE,AND(F223="",G223="")),0,$F$11+SUM($F$12:F223)-SUM($G$12:G223)) -> 0

Sheet Bk Hutang
A1: ='Data GL'!E6 -> CV. SPEKTRA DIGITAL ARTWORK
A2: ='Data GL'!E4 -> PERCETAKAN
A3: ='Data GL'!E5 -> JL. Prof Dr. Yohannes 1099 YK
A5: BUKU BESAR HUTANG DAGANG
A6: =CONCATENATE('Data GL'!E7," -"," TAHUN"," ",'Data GL'!E8) -> Jan - TAHUN 2026
A8: Kode Pembantu | D8: =IF(F8=0," ",(VLOOKUP(F8,Kode!$B$10:$E$188,4,0))) -> H-003 | F8: Jaya Sejahtera, CV
A10: No | B10: Tanggal | D10: Bukti | E10: Keterangan | F10: Debet | G10: Kredit | H10: Saldo
E11: Saldo Awal | F11: 0 | G11: =VLOOKUP(D8,Kode!$E$10:$F$412,2,FALSE) -> 3685010 | H11: =SUM(F11:G11) -> 3685010
A12: =A11+1 -> 1 | B12: =IF(ISERROR(VLOOKUP(A12&D$8,JU_KODE,4,FALSE)=TRUE),"",VLOOKUP(A12&D$8,JU_KODE,4,FALSE)) -> 46051 | C12: =IF(ISERROR(VLOOKUP(A12&D$8,JU_KODE,5,FALSE)=TRUE),"",VLOOKUP(A12&D$8,JU_KODE,5,FALSE)) -> 9 | D12: =IF(ISERROR(VLOOKUP(A12&D$8,JU_KODE,6,FALSE)=TRUE),"",VLOOKUP(A12&D$8,JU_KODE,6,FALSE)) -> 04002600004398651 | E12: =IF(ISERROR(VLOOKUP(A12&D$8,JU_KODE,7,FALSE)=TRUE),"",VLOOKUP(A12&D$8,JU_KODE,7,FALSE)) -> Pembelian BB ke Jaya Sejahtera, CV | F12: =IF(ISERROR(VLOOKUP(A12&D$8,JU_KODE,12,FALSE)=TRUE),"",VLOOKUP(A12&D$8,JU_KODE,12,FALSE)) -> 0 | G12: =IF(ISERROR(VLOOKUP(A12&D$8,JU_KODE,13,FALSE)=TRUE),"",VLOOKUP(A12&D$8,JU_KODE,13,FALSE)) -> 4725000 | H12: =IF(OR(ERR=FALSE,AND(F12="",G12="")),0,$G$11-SUM($F$12:F12)+SUM($G$12:G12)) -> 8410010
A13: =A12+1 -> 2 | B13: =IF(ISERROR(VLOOKUP(A13&D$8,JU_KODE,4,FALSE)=TRUE),"",VLOOKUP(A13&D$8,JU_KODE,4,FALSE)) -> 46051 | C13: =IF(ISERROR(VLOOKUP(A13&D$8,JU_KODE,5,FALSE)=TRUE),"",VLOOKUP(A13&D$8,JU_KODE,5,FALSE)) -> 12 | D13: =IF(ISERROR(VLOOKUP(A13&D$8,JU_KODE,6,FALSE)=TRUE),"",VLOOKUP(A13&D$8,JU_KODE,6,FALSE)) -> 0 | E13: =IF(ISERROR(VLOOKUP(A13&D$8,JU_KODE,7,FALSE)=TRUE),"",VLOOKUP(A13&D$8,JU_KODE,7,FALSE)) -> Bayar Hutang Jaya Sejahtera 12/12'2025 | F13: =IF(ISERROR(VLOOKUP(A13&D$8,JU_KODE,12,FALSE)=TRUE),"",VLOOKUP(A13&D$8,JU_KODE,12,FALSE)) -> 3685000 | G13: =IF(ISERROR(VLOOKUP(A13&D$8,JU_KODE,13,FALSE)=TRUE),"",VLOOKUP(A13&D$8,JU_KODE,13,FALSE)) -> 0 | H13: =IF(OR(ERR=FALSE,AND(F13="",G13="")),0,$G$11-SUM($F$12:F13)+SUM($G$12:G13)) -> 4725010
A14: =A13+1 -> 3 | B14: =IF(ISERROR(VLOOKUP(A14&D$8,JU_KODE,4,FALSE)=TRUE),"",VLOOKUP(A14&D$8,JU_KODE,4,FALSE)) -> 46051 | C14: =IF(ISERROR(VLOOKUP(A14&D$8,JU_KODE,5,FALSE)=TRUE),"",VLOOKUP(A14&D$8,JU_KODE,5,FALSE)) -> 19 | D14: =IF(ISERROR(VLOOKUP(A14&D$8,JU_KODE,6,FALSE)=TRUE),"",VLOOKUP(A14&D$8,JU_KODE,6,FALSE)) -> 04002600015931055 | E14: =IF(ISERROR(VLOOKUP(A14&D$8,JU_KODE,7,FALSE)=TRUE),"",VLOOKUP(A14&D$8,JU_KODE,7,FALSE)) -> Pembelian BB ke Jaya Sejahtera, CV | F14: =IF(ISERROR(VLOOKUP(A14&D$8,JU_KODE,12,FALSE)=TRUE),"",VLOOKUP(A14&D$8,JU_KODE,12,FALSE)) -> 0 | G14: =IF(ISERROR(VLOOKUP(A14&D$8,JU_KODE,13,FALSE)=TRUE),"",VLOOKUP(A14&D$8,JU_KODE,13,FALSE)) -> 4790000 | H14: =IF(OR(ERR=FALSE,AND(F14="",G14="")),0,$G$11-SUM($F$12:F14)+SUM($G$12:G14)) -> 9515010
A15: =A14+1 -> 4 | B15: =IF(ISERROR(VLOOKUP(A15&D$8,JU_KODE,4,FALSE)=TRUE),"",VLOOKUP(A15&D$8,JU_KODE,4,FALSE)) -> 46051 | C15: =IF(ISERROR(VLOOKUP(A15&D$8,JU_KODE,5,FALSE)=TRUE),"",VLOOKUP(A15&D$8,JU_KODE,5,FALSE)) -> 27 | D15: =IF(ISERROR(VLOOKUP(A15&D$8,JU_KODE,6,FALSE)=TRUE),"",VLOOKUP(A15&D$8,JU_KODE,6,FALSE)) -> 04002600023320688 | E15: =IF(ISERROR(VLOOKUP(A15&D$8,JU_KODE,7,FALSE)=TRUE),"",VLOOKUP(A15&D$8,JU_KODE,7,FALSE)) -> Pembelian BB ke Jaya Sejahtera, CV | F15: =IF(ISERROR(VLOOKUP(A15&D$8,JU_KODE,12,FALSE)=TRUE),"",VLOOKUP(A15&D$8,JU_KODE,12,FALSE)) -> 0 | G15: =IF(ISERROR(VLOOKUP(A15&D$8,JU_KODE,13,FALSE)=TRUE),"",VLOOKUP(A15&D$8,JU_KODE,13,FALSE)) -> 6535000 | H15: =IF(OR(ERR=FALSE,AND(F15="",G15="")),0,$G$11-SUM($F$12:F15)+SUM($G$12:G15)) -> 16050010
A16: =A15+1 -> 5 | B16: =IF(ISERROR(VLOOKUP(A16&D$8,JU_KODE,4,FALSE)=TRUE),"",VLOOKUP(A16&D$8,JU_KODE,4,FALSE)) -> 46051 | C16: =IF(ISERROR(VLOOKUP(A16&D$8,JU_KODE,5,FALSE)=TRUE),"",VLOOKUP(A16&D$8,JU_KODE,5,FALSE)) -> 28 | D16: =IF(ISERROR(VLOOKUP(A16&D$8,JU_KODE,6,FALSE)=TRUE),"",VLOOKUP(A16&D$8,JU_KODE,6,FALSE)) -> 04002600023320809 | E16: =IF(ISERROR(VLOOKUP(A16&D$8,JU_KODE,7,FALSE)=TRUE),"",VLOOKUP(A16&D$8,JU_KODE,7,FALSE)) -> Pembelian BB ke Jaya Sejahtera, CV | F16: =IF(ISERROR(VLOOKUP(A16&D$8,JU_KODE,12,FALSE)=TRUE),"",VLOOKUP(A16&D$8,JU_KODE,12,FALSE)) -> 0 | G16: =IF(ISERROR(VLOOKUP(A16&D$8,JU_KODE,13,FALSE)=TRUE),"",VLOOKUP(A16&D$8,JU_KODE,13,FALSE)) -> 460000 | H16: =IF(OR(ERR=FALSE,AND(F16="",G16="")),0,$G$11-SUM($F$12:F16)+SUM($G$12:G16)) -> 16510010
A17: =A16+1 -> 6 | B17: =IF(ISERROR(VLOOKUP(A17&D$8,JU_KODE,4,FALSE)=TRUE),"",VLOOKUP(A17&D$8,JU_KODE,4,FALSE)) | C17: =IF(ISERROR(VLOOKUP(A17&D$8,JU_KODE,5,FALSE)=TRUE),"",VLOOKUP(A17&D$8,JU_KODE,5,FALSE)) | D17: =IF(ISERROR(VLOOKUP(A17&D$8,JU_KODE,6,FALSE)=TRUE),"",VLOOKUP(A17&D$8,JU_KODE,6,FALSE)) | E17: =IF(ISERROR(VLOOKUP(A17&D$8,JU_KODE,7,FALSE)=TRUE),"",VLOOKUP(A17&D$8,JU_KODE,7,FALSE)) | F17: =IF(ISERROR(VLOOKUP(A17&D$8,JU_KODE,12,FALSE)=TRUE),"",VLOOKUP(A17&D$8,JU_KODE,12,FALSE)) | G17: =IF(ISERROR(VLOOKUP(A17&D$8,JU_KODE,13,FALSE)=TRUE),"",VLOOKUP(A17&D$8,JU_KODE,13,FALSE)) | H17: =IF(OR(ERR=FALSE,AND(F17="",G17="")),0,$G$11-SUM($F$12:F17)+SUM($G$12:G17)) -> 0
A18: =A17+1 -> 7 | B18: =IF(ISERROR(VLOOKUP(A18&D$8,JU_KODE,4,FALSE)=TRUE),"",VLOOKUP(A18&D$8,JU_KODE,4,FALSE)) | C18: =IF(ISERROR(VLOOKUP(A18&D$8,JU_KODE,5,FALSE)=TRUE),"",VLOOKUP(A18&D$8,JU_KODE,5,FALSE)) | D18: =IF(ISERROR(VLOOKUP(A18&D$8,JU_KODE,6,FALSE)=TRUE),"",VLOOKUP(A18&D$8,JU_KODE,6,FALSE)) | E18: =IF(ISERROR(VLOOKUP(A18&D$8,JU_KODE,7,FALSE)=TRUE),"",VLOOKUP(A18&D$8,JU_KODE,7,FALSE)) | F18: =IF(ISERROR(VLOOKUP(A18&D$8,JU_KODE,12,FALSE)=TRUE),"",VLOOKUP(A18&D$8,JU_KODE,12,FALSE)) | G18: =IF(ISERROR(VLOOKUP(A18&D$8,JU_KODE,13,FALSE)=TRUE),"",VLOOKUP(A18&D$8,JU_KODE,13,FALSE)) | H18: =IF(OR(ERR=FALSE,AND(F18="",G18="")),0,$G$11-SUM($F$12:F18)+SUM($G$12:G18)) -> 0
A19: =A18+1 -> 8 | B19: =IF(ISERROR(VLOOKUP(A19&D$8,JU_KODE,4,FALSE)=TRUE),"",VLOOKUP(A19&D$8,JU_KODE,4,FALSE)) | C19: =IF(ISERROR(VLOOKUP(A19&D$8,JU_KODE,5,FALSE)=TRUE),"",VLOOKUP(A19&D$8,JU_KODE,5,FALSE)) | D19: =IF(ISERROR(VLOOKUP(A19&D$8,JU_KODE,6,FALSE)=TRUE),"",VLOOKUP(A19&D$8,JU_KODE,6,FALSE)) | E19: =IF(ISERROR(VLOOKUP(A19&D$8,JU_KODE,7,FALSE)=TRUE),"",VLOOKUP(A19&D$8,JU_KODE,7,FALSE)) | F19: =IF(ISERROR(VLOOKUP(A19&D$8,JU_KODE,12,FALSE)=TRUE),"",VLOOKUP(A19&D$8,JU_KODE,12,FALSE)) | G19: =IF(ISERROR(VLOOKUP(A19&D$8,JU_KODE,13,FALSE)=TRUE),"",VLOOKUP(A19&D$8,JU_KODE,13,FALSE)) | H19: =IF(OR(ERR=FALSE,AND(F19="",G19="")),0,$G$11-SUM($F$12:F19)+SUM($G$12:G19)) -> 0
A20: =A19+1 -> 9 | B20: =IF(ISERROR(VLOOKUP(A20&D$8,JU_KODE,4,FALSE)=TRUE),"",VLOOKUP(A20&D$8,JU_KODE,4,FALSE)) | C20: =IF(ISERROR(VLOOKUP(A20&D$8,JU_KODE,5,FALSE)=TRUE),"",VLOOKUP(A20&D$8,JU_KODE,5,FALSE)) | D20: =IF(ISERROR(VLOOKUP(A20&D$8,JU_KODE,6,FALSE)=TRUE),"",VLOOKUP(A20&D$8,JU_KODE,6,FALSE)) | E20: =IF(ISERROR(VLOOKUP(A20&D$8,JU_KODE,7,FALSE)=TRUE),"",VLOOKUP(A20&D$8,JU_KODE,7,FALSE)) | F20: =IF(ISERROR(VLOOKUP(A20&D$8,JU_KODE,12,FALSE)=TRUE),"",VLOOKUP(A20&D$8,JU_KODE,12,FALSE)) | G20: =IF(ISERROR(VLOOKUP(A20&D$8,JU_KODE,13,FALSE)=TRUE),"",VLOOKUP(A20&D$8,JU_KODE,13,FALSE)) | H20: =IF(OR(ERR=FALSE,AND(F20="",G20="")),0,$G$11-SUM($F$12:F20)+SUM($G$12:G20)) -> 0
A21: =A20+1 -> 10 | B21: =IF(ISERROR(VLOOKUP(A21&D$8,JU_KODE,4,FALSE)=TRUE),"",VLOOKUP(A21&D$8,JU_KODE,4,FALSE)) | C21: =IF(ISERROR(VLOOKUP(A21&D$8,JU_KODE,5,FALSE)=TRUE),"",VLOOKUP(A21&D$8,JU_KODE,5,FALSE)) | D21: =IF(ISERROR(VLOOKUP(A21&D$8,JU_KODE,6,FALSE)=TRUE),"",VLOOKUP(A21&D$8,JU_KODE,6,FALSE)) | E21: =IF(ISERROR(VLOOKUP(A21&D$8,JU_KODE,7,FALSE)=TRUE),"",VLOOKUP(A21&D$8,JU_KODE,7,FALSE)) | F21: =IF(ISERROR(VLOOKUP(A21&D$8,JU_KODE,12,FALSE)=TRUE),"",VLOOKUP(A21&D$8,JU_KODE,12,FALSE)) | G21: =IF(ISERROR(VLOOKUP(A21&D$8,JU_KODE,13,FALSE)=TRUE),"",VLOOKUP(A21&D$8,JU_KODE,13,FALSE)) | H21: =IF(OR(ERR=FALSE,AND(F21="",G21="")),0,$G$11-SUM($F$12:F21)+SUM($G$12:G21)) -> 0
A22: =A21+1 -> 11 | B22: =IF(ISERROR(VLOOKUP(A22&D$8,JU_KODE,4,FALSE)=TRUE),"",VLOOKUP(A22&D$8,JU_KODE,4,FALSE)) | C22: =IF(ISERROR(VLOOKUP(A22&D$8,JU_KODE,5,FALSE)=TRUE),"",VLOOKUP(A22&D$8,JU_KODE,5,FALSE)) | D22: =IF(ISERROR(VLOOKUP(A22&D$8,JU_KODE,6,FALSE)=TRUE),"",VLOOKUP(A22&D$8,JU_KODE,6,FALSE)) | E22: =IF(ISERROR(VLOOKUP(A22&D$8,JU_KODE,7,FALSE)=TRUE),"",VLOOKUP(A22&D$8,JU_KODE,7,FALSE)) | F22: =IF(ISERROR(VLOOKUP(A22&D$8,JU_KODE,12,FALSE)=TRUE),"",VLOOKUP(A22&D$8,JU_KODE,12,FALSE)) | G22: =IF(ISERROR(VLOOKUP(A22&D$8,JU_KODE,13,FALSE)=TRUE),"",VLOOKUP(A22&D$8,JU_KODE,13,FALSE)) | H22: =IF(OR(ERR=FALSE,AND(F22="",G22="")),0,$G$11-SUM($F$12:F22)+SUM($G$12:G22)) -> 0
A23: =A22+1 -> 12 | B23: =IF(ISERROR(VLOOKUP(A23&D$8,JU_KODE,4,FALSE)=TRUE),"",VLOOKUP(A23&D$8,JU_KODE,4,FALSE)) | C23: =IF(ISERROR(VLOOKUP(A23&D$8,JU_KODE,5,FALSE)=TRUE),"",VLOOKUP(A23&D$8,JU_KODE,5,FALSE)) | D23: =IF(ISERROR(VLOOKUP(A23&D$8,JU_KODE,6,FALSE)=TRUE),"",VLOOKUP(A23&D$8,JU_KODE,6,FALSE)) | E23: =IF(ISERROR(VLOOKUP(A23&D$8,JU_KODE,7,FALSE)=TRUE),"",VLOOKUP(A23&D$8,JU_KODE,7,FALSE)) | F23: =IF(ISERROR(VLOOKUP(A23&D$8,JU_KODE,12,FALSE)=TRUE),"",VLOOKUP(A23&D$8,JU_KODE,12,FALSE)) | G23: =IF(ISERROR(VLOOKUP(A23&D$8,JU_KODE,13,FALSE)=TRUE),"",VLOOKUP(A23&D$8,JU_KODE,13,FALSE)) | H23: =IF(OR(ERR=FALSE,AND(F23="",G23="")),0,$G$11-SUM($F$12:F23)+SUM($G$12:G23)) -> 0
... A818: =A817+1 -> 807 | B818: =IF(ISERROR(VLOOKUP(A818&D$8,JU_KODE,4,FALSE)=TRUE),"",VLOOKUP(A818&D$8,JU_KODE,4,FALSE)) | C818: =IF(ISERROR(VLOOKUP(A818&D$8,JU_KODE,5,FALSE)=TRUE),"",VLOOKUP(A818&D$8,JU_KODE,5,FALSE)) | D818: =IF(ISERROR(VLOOKUP(A818&D$8,JU_KODE,6,FALSE)=TRUE),"",VLOOKUP(A818&D$8,JU_KODE,6,FALSE)) | E818: =IF(ISERROR(VLOOKUP(A818&D$8,JU_KODE,7,FALSE)=TRUE),"",VLOOKUP(A818&D$8,JU_KODE,7,FALSE)) | F818: =IF(ISERROR(VLOOKUP(A818&D$8,JU_KODE,12,FALSE)=TRUE),"",VLOOKUP(A818&D$8,JU_KODE,12,FALSE)) | G818: =IF(ISERROR(VLOOKUP(A818&D$8,JU_KODE,13,FALSE)=TRUE),"",VLOOKUP(A818&D$8,JU_KODE,13,FALSE)) | H818: =IF(OR(ERR=FALSE,AND(F818="",G818="")),0,$G$11-SUM($F$12:F818)+SUM($G$12:G818)) -> 0

Sheet Neraca Lajur
A1: ='Data GL'!E6 -> CV. SPEKTRA DIGITAL ARTWORK
A2: ='Data GL'!E4 -> PERCETAKAN
A3: ='Data GL'!E5 -> JL. Prof Dr. Yohannes 1099 YK
A5: NERACA LAJUR
A6: =CONCATENATE('Data GL'!E7," -"," TAHUN"," ",'Data GL'!E8) -> Jan - TAHUN 2026
A8: Kode | B8: Nama Akun | C8: Pos Saldo | D8: Neraca Saldo | F8: Pos Lapr | G8: Laba Rugi | I8: Neraca
A9: Akun | D9: Debet | E9: Kredit | G9: Debet | H9: Kredit | I9: Debet | J9: Kredit
A10: 10000 | B10: =VLOOKUP(A10,DAF_AKUN,2,FALSE) -> AKTIVA
A11: 11000 | B11: =VLOOKUP(A11,DAF_AKUN,2,FALSE) -> AKTIVA LANCAR
A12: 11100 | B12: =VLOOKUP(A12,DAF_AKUN,2,FALSE) -> Kas | C12: =VLOOKUP(A12,DAF_AKUN,3,FALSE) -> D | D12: =IF(C12="D",SUMIF(Akun!A:A,A12,Akun!F:F)+SUMIF(Jurnal!K:K,A12,Jurnal!N:N)-SUMIF(Jurnal!K:K,A12,Jurnal!O:O),0) -> 1434652025 | E12: =IF(C12="K",SUMIF(Akun!A:A,A12,Akun!G:G)-SUMIF(Jurnal!K:K,A12,Jurnal!N:N)+SUMIF(Jurnal!K:K,A12,Jurnal!O:O),0) -> 0 | F12: =VLOOKUP(A12,DAF_AKUN,4,FALSE) -> NR | G12: =IF(F12="LR",D12,0) -> 0 | H12: =IF(F12="LR",E12,0) -> 0 | I12: =IF(F12="NR",D12,0) -> 1434652025 | J12: =IF(F12="NR",E12,0) -> 0
A13: 11101 | B13: =VLOOKUP(A13,DAF_AKUN,2,FALSE) -> Bank | C13: =VLOOKUP(A13,DAF_AKUN,3,FALSE) -> D | D13: =IF(C13="D",SUMIF(Akun!A:A,A13,Akun!F:F)+SUMIF(Jurnal!K:K,A13,Jurnal!N:N)-SUMIF(Jurnal!K:K,A13,Jurnal!O:O),0) -> 0 | E13: =IF(C13="K",SUMIF(Akun!A:A,A13,Akun!G:G)-SUMIF(Jurnal!K:K,A13,Jurnal!N:N)+SUMIF(Jurnal!K:K,A13,Jurnal!O:O),0) -> 0 | F13: =VLOOKUP(A13,DAF_AKUN,4,FALSE) -> NR | G13: =IF(F13="LR",D13,0) -> 0 | H13: =IF(F13="LR",E13,0) -> 0 | I13: =IF(F13="NR",D13,0) -> 0 | J13: =IF(F13="NR",E13,0) -> 0
A14: 11102 | B14: =VLOOKUP(A14,DAF_AKUN,2,FALSE) -> Piutang Dagang | C14: =VLOOKUP(A14,DAF_AKUN,3,FALSE) -> D | D14: =IF(C14="D",SUMIF(Akun!A:A,A14,Akun!F:F)+SUMIF(Jurnal!K:K,A14,Jurnal!N:N)-SUMIF(Jurnal!K:K,A14,Jurnal!O:O),0) -> 1.2702828e+09 | E14: =IF(C14="K",SUMIF(Akun!A:A,A14,Akun!G:G)-SUMIF(Jurnal!K:K,A14,Jurnal!N:N)+SUMIF(Jurnal!K:K,A14,Jurnal!O:O),0) -> 0 | F14: =VLOOKUP(A14,DAF_AKUN,4,FALSE) -> NR | G14: =IF(F14="LR",D14,0) -> 0 | H14: =IF(F14="LR",E14,0) -> 0 | I14: =IF(F14="NR",D14,0) -> 1.2702828e+09 | J14: =IF(F14="NR",E14,0) -> 0
A15: 11103 | B15: =VLOOKUP(A15,DAF_AKUN,2,FALSE) -> Piutang Karyawan | C15: =VLOOKUP(A15,DAF_AKUN,3,FALSE) -> D | D15: =IF(C15="D",SUMIF(Akun!A:A,A15,Akun!F:F)+SUMIF(Jurnal!K:K,A15,Jurnal!N:N)-SUMIF(Jurnal!K:K,A15,Jurnal!O:O),0) -> 0 | E15: =IF(C15="K",SUMIF(Akun!A:A,A15,Akun!G:G)-SUMIF(Jurnal!K:K,A15,Jurnal!N:N)+SUMIF(Jurnal!K:K,A15,Jurnal!O:O),0) -> 0 | F15: =VLOOKUP(A15,DAF_AKUN,4,FALSE) -> NR | G15: =IF(F15="LR",D15,0) -> 0 | H15: =IF(F15="LR",E15,0) -> 0 | I15: =IF(F15="NR",D15,0) -> 0 | J15: =IF(F15="NR",E15,0) -> 0
A16: 11200 | B16: =VLOOKUP(A16,DAF_AKUN,2,FALSE) -> Persediaan Barang Jadi | C16: =VLOOKUP(A16,DAF_AKUN,3,FALSE) -> D | D16: =IF(C16="D",SUMIF(Akun!A:A,A16,Akun!F:F)+SUMIF(Jurnal!K:K,A16,Jurnal!N:N)-SUMIF(Jurnal!K:K,A16,Jurnal!O:O),0) -> 1553000000 | E16: =IF(C16="K",SUMIF(Akun!A:A,A16,Akun!G:G)-SUMIF(Jurnal!K:K,A16,Jurnal!N:N)+SUMIF(Jurnal!K:K,A16,Jurnal!O:O),0) -> 0 | F16: =VLOOKUP(A16,DAF_AKUN,4,FALSE) -> NR | G16: =IF(F16="LR",D16,0) -> 0 | H16: =IF(F16="LR",E16,0) -> 0 | I16: =IF(F16="NR",D16,0) -> 1553000000 | J16: =IF(F16="NR",E16,0) -> 0
A17: 11300 | B17: =VLOOKUP(A17,DAF_AKUN,2,FALSE) -> Persediaan Barang Proses | C17: =VLOOKUP(A17,DAF_AKUN,3,FALSE) -> D | D17: =IF(C17="D",SUMIF(Akun!A:A,A17,Akun!F:F)+SUMIF(Jurnal!K:K,A17,Jurnal!N:N)-SUMIF(Jurnal!K:K,A17,Jurnal!O:O),0) -> 0 | E17: =IF(C17="K",SUMIF(Akun!A:A,A17,Akun!G:G)-SUMIF(Jurnal!K:K,A17,Jurnal!N:N)+SUMIF(Jurnal!K:K,A17,Jurnal!O:O),0) -> 0 | F17: =VLOOKUP(A17,DAF_AKUN,4,FALSE) -> NR | G17: =IF(F17="LR",D17,0) -> 0 | H17: =IF(F17="LR",E17,0) -> 0 | I17: =IF(F17="NR",D17,0) -> 0 | J17: =IF(F17="NR",E17,0) -> 0
A18: 11301 | B18: =VLOOKUP(A18,DAF_AKUN,2,FALSE) -> Persediaan Bahan Baku | C18: =VLOOKUP(A18,DAF_AKUN,3,FALSE) -> D | D18: =IF(C18="D",SUMIF(Akun!A:A,A18,Akun!F:F)+SUMIF(Jurnal!K:K,A18,Jurnal!N:N)-SUMIF(Jurnal!K:K,A18,Jurnal!O:O),0) -> 10187858027 | E18: =IF(C18="K",SUMIF(Akun!A:A,A18,Akun!G:G)-SUMIF(Jurnal!K:K,A18,Jurnal!N:N)+SUMIF(Jurnal!K:K,A18,Jurnal!O:O),0) -> 0 | F18: =VLOOKUP(A18,DAF_AKUN,4,FALSE) -> NR | G18: =IF(F18="LR",D18,0) -> 0 | H18: =IF(F18="LR",E18,0) -> 0 | I18: =IF(F18="NR",D18,0) -> 10187858027 | J18: =IF(F18="NR",E18,0) -> 0
A19: 11400 | B19: =VLOOKUP(A19,DAF_AKUN,2,FALSE) -> Persediaan Bahan Penolong | C19: =VLOOKUP(A19,DAF_AKUN,3,FALSE) -> D | D19: =IF(C19="D",SUMIF(Akun!A:A,A19,Akun!F:F)+SUMIF(Jurnal!K:K,A19,Jurnal!N:N)-SUMIF(Jurnal!K:K,A19,Jurnal!O:O),0) -> 0 | E19: =IF(C19="K",SUMIF(Akun!A:A,A19,Akun!G:G)-SUMIF(Jurnal!K:K,A19,Jurnal!N:N)+SUMIF(Jurnal!K:K,A19,Jurnal!O:O),0) -> 0 | F19: =VLOOKUP(A19,DAF_AKUN,4,FALSE) -> NR | G19: =IF(F19="LR",D19,0) -> 0 | H19: =IF(F19="LR",E19,0) -> 0 | I19: =IF(F19="NR",D19,0) -> 0 | J19: =IF(F19="NR",E19,0) -> 0
A20: 11401 | B20: =VLOOKUP(A20,DAF_AKUN,2,FALSE) -> Persediaan Lain-lain | C20: =VLOOKUP(A20,DAF_AKUN,3,FALSE) -> D | D20: =IF(C20="D",SUMIF(Akun!A:A,A20,Akun!F:F)+SUMIF(Jurnal!K:K,A20,Jurnal!N:N)-SUMIF(Jurnal!K:K,A20,Jurnal!O:O),0) -> 5860000 | E20: =IF(C20="K",SUMIF(Akun!A:A,A20,Akun!G:G)-SUMIF(Jurnal!K:K,A20,Jurnal!N:N)+SUMIF(Jurnal!K:K,A20,Jurnal!O:O),0) -> 0 | F20: =VLOOKUP(A20,DAF_AKUN,4,FALSE) -> NR | G20: =IF(F20="LR",D20,0) -> 0 | H20: =IF(F20="LR",E20,0) -> 0 | I20: =IF(F20="NR",D20,0) -> 5860000 | J20: =IF(F20="NR",E20,0) -> 0
A21: 11402 | B21: =VLOOKUP(A21,DAF_AKUN,2,FALSE) -> Ppn Dibayar dimuka | C21: =VLOOKUP(A21,DAF_AKUN,3,FALSE) -> D | D21: =IF(C21="D",SUMIF(Akun!A:A,A21,Akun!F:F)+SUMIF(Jurnal!K:K,A21,Jurnal!N:N)-SUMIF(Jurnal!K:K,A21,Jurnal!O:O),0) -> 0 | E21: =IF(C21="K",SUMIF(Akun!A:A,A21,Akun!G:G)-SUMIF(Jurnal!K:K,A21,Jurnal!N:N)+SUMIF(Jurnal!K:K,A21,Jurnal!O:O),0) -> 0 | F21: =VLOOKUP(A21,DAF_AKUN,4,FALSE) -> NR | G21: =IF(F21="LR",D21,0) -> 0 | H21: =IF(F21="LR",E21,0) -> 0 | I21: =IF(F21="NR",D21,0) -> 0 | J21: =IF(F21="NR",E21,0) -> 0
A22: 11403 | B22: =VLOOKUP(A22,DAF_AKUN,2,FALSE) -> Pph Pasal 23 | C22: =VLOOKUP(A22,DAF_AKUN,3,FALSE) -> D | D22: =IF(C22="D",SUMIF(Akun!A:A,A22,Akun!F:F)+SUMIF(Jurnal!K:K,A22,Jurnal!N:N)-SUMIF(Jurnal!K:K,A22,Jurnal!O:O),0) -> 14360087 | E22: =IF(C22="K",SUMIF(Akun!A:A,A22,Akun!G:G)-SUMIF(Jurnal!K:K,A22,Jurnal!N:N)+SUMIF(Jurnal!K:K,A22,Jurnal!O:O),0) -> 0 | F22: =VLOOKUP(A22,DAF_AKUN,4,FALSE) -> NR | G22: =IF(F22="LR",D22,0) -> 0 | H22: =IF(F22="LR",E22,0) -> 0 | I22: =IF(F22="NR",D22,0) -> 14360087 | J22: =IF(F22="NR",E22,0) -> 0
A23: 11500 | B23: =VLOOKUP(A23,DAF_AKUN,2,FALSE) -> Pph Pasal 25 | C23: =VLOOKUP(A23,DAF_AKUN,3,FALSE) -> D | D23: =IF(C23="D",SUMIF(Akun!A:A,A23,Akun!F:F)+SUMIF(Jurnal!K:K,A23,Jurnal!N:N)-SUMIF(Jurnal!K:K,A23,Jurnal!O:O),0) -> 12140000 | E23: =IF(C23="K",SUMIF(Akun!A:A,A23,Akun!G:G)-SUMIF(Jurnal!K:K,A23,Jurnal!N:N)+SUMIF(Jurnal!K:K,A23,Jurnal!O:O),0) -> 0 | F23: =VLOOKUP(A23,DAF_AKUN,4,FALSE) -> NR | G23: =IF(F23="LR",D23,0) -> 0 | H23: =IF(F23="LR",E23,0) -> 0 | I23: =IF(F23="NR",D23,0) -> 12140000 | J23: =IF(F23="NR",E23,0) -> 0
... A26: 11800 | B26: =VLOOKUP(A26,DAF_AKUN,2,FALSE) -> Uang Muka Sewa | C26: =VLOOKUP(A26,DAF_AKUN,3,FALSE) -> D | D26: =IF(C26="D",SUMIF(Akun!A:A,A26,Akun!F:F)+SUMIF(Jurnal!K:K,A26,Jurnal!N:N)-SUMIF(Jurnal!K:K,A26,Jurnal!O:O),0) -> 0 | E26: =IF(C26="K",SUMIF(Akun!A:A,A26,Akun!G:G)-SUMIF(Jurnal!K:K,A26,Jurnal!N:N)+SUMIF(Jurnal!K:K,A26,Jurnal!O:O),0) -> 0 | F26: =VLOOKUP(A26,DAF_AKUN,4,FALSE) -> NR | G26: =IF(F26="LR",D26,0) -> 0 | H26: =IF(F26="LR",E26,0) -> 0 | I26: =IF(F26="NR",D26,0) -> 0 | J26: =IF(F26="NR",E26,0) -> 0
A27: 12000 | B27: =VLOOKUP(A27,DAF_AKUN,2,FALSE) -> AKTIVA TETAP
A28: 12100 | B28: =VLOOKUP(A28,DAF_AKUN,2,FALSE) -> Gedung dan Listrik | C28: =VLOOKUP(A28,DAF_AKUN,3,FALSE) -> D | D28: =IF(C28="D",SUMIF(Akun!A:A,A28,Akun!F:F)+SUMIF(Jurnal!K:K,A28,Jurnal!N:N)-SUMIF(Jurnal!K:K,A28,Jurnal!O:O),0) -> 48589042 | E28: =IF(C28="K",SUMIF(Akun!A:A,A28,Akun!G:G)-SUMIF(Jurnal!K:K,A28,Jurnal!N:N)+SUMIF(Jurnal!K:K,A28,Jurnal!O:O),0) -> 0 | F28: =IF(ERR=FALSE,0,VLOOKUP(A28,DAF_AKUN,4,FALSE)) -> NR | G28: =IF(F28="LR",D28,0) -> 0 | H28: =IF(F28="LR",E28,0) -> 0 | I28: =IF(F28="NR",D28,0) -> 48589042 | J28: =IF(F28="NR",E28,0) -> 0
A29: 12200 | B29: =VLOOKUP(A29,DAF_AKUN,2,FALSE) -> Peralatan Pabrik | C29: =VLOOKUP(A29,DAF_AKUN,3,FALSE) -> D | D29: =IF(C29="D",SUMIF(Akun!A:A,A29,Akun!F:F)+SUMIF(Jurnal!K:K,A29,Jurnal!N:N)-SUMIF(Jurnal!K:K,A29,Jurnal!O:O),0) -> 6747617604 | E29: =IF(C29="K",SUMIF(Akun!A:A,A29,Akun!G:G)-SUMIF(Jurnal!K:K,A29,Jurnal!N:N)+SUMIF(Jurnal!K:K,A29,Jurnal!O:O),0) -> 0 | F29: =IF(ERR=FALSE,0,VLOOKUP(A29,DAF_AKUN,4,FALSE)) -> NR | G29: =IF(F29="LR",D29,0) -> 0 | H29: =IF(F29="LR",E29,0) -> 0 | I29: =IF(F29="NR",D29,0) -> 6747617604 | J29: =IF(F29="NR",E29,0) -> 0
A30: 12300 | B30: =VLOOKUP(A30,DAF_AKUN,2,FALSE) -> Peralatan Kantor | C30: =VLOOKUP(A30,DAF_AKUN,3,FALSE) -> D | D30: =IF(C30="D",SUMIF(Akun!A:A,A30,Akun!F:F)+SUMIF(Jurnal!K:K,A30,Jurnal!N:N)-SUMIF(Jurnal!K:K,A30,Jurnal!O:O),0) -> 214765469 | E30: =IF(C30="K",SUMIF(Akun!A:A,A30,Akun!G:G)-SUMIF(Jurnal!K:K,A30,Jurnal!N:N)+SUMIF(Jurnal!K:K,A30,Jurnal!O:O),0) -> 0 | F30: =IF(ERR=FALSE,0,VLOOKUP(A30,DAF_AKUN,4,FALSE)) -> NR | G30: =IF(F30="LR",D30,0) -> 0 | H30: =IF(F30="LR",E30,0) -> 0 | I30: =IF(F30="NR",D30,0) -> 214765469 | J30: =IF(F30="NR",E30,0) -> 0
A31: 12400 | B31: =VLOOKUP(A31,DAF_AKUN,2,FALSE) -> Kendaraan | C31: =VLOOKUP(A31,DAF_AKUN,3,FALSE) -> D | D31: =IF(C31="D",SUMIF(Akun!A:A,A31,Akun!F:F)+SUMIF(Jurnal!K:K,A31,Jurnal!N:N)-SUMIF(Jurnal!K:K,A31,Jurnal!O:O),0) -> 0 | E31: =IF(C31="K",SUMIF(Akun!A:A,A31,Akun!G:G)-SUMIF(Jurnal!K:K,A31,Jurnal!N:N)+SUMIF(Jurnal!K:K,A31,Jurnal!O:O),0) -> 0 | F31: =IF(ERR=FALSE,0,VLOOKUP(A31,DAF_AKUN,4,FALSE)) -> NR | G31: =IF(F31="LR",D31,0) -> 0 | H31: =IF(F31="LR",E31,0) -> 0 | I31: =IF(F31="NR",D31,0) -> 0 | J31: =IF(F31="NR",E31,0) -> 0
A32: 12500 | B32: =VLOOKUP(A32,DAF_AKUN,2,FALSE) -> Investaris Kantor | C32: =VLOOKUP(A32,DAF_AKUN,3,FALSE) -> D | D32: =IF(C32="D",SUMIF(Akun!A:A,A32,Akun!F:F)+SUMIF(Jurnal!K:K,A32,Jurnal!N:N)-SUMIF(Jurnal!K:K,A32,Jurnal!O:O),0) -> 0 | E32: =IF(C32="K",SUMIF(Akun!A:A,A32,Akun!G:G)-SUMIF(Jurnal!K:K,A32,Jurnal!N:N)+SUMIF(Jurnal!K:K,A32,Jurnal!O:O),0) -> 0 | F32: =IF(ERR=FALSE,0,VLOOKUP(A32,DAF_AKUN,4,FALSE)) -> NR | G32: =IF(F32="LR",D32,0) -> 0 | H32: =IF(F32="LR",E32,0) -> 0 | I32: =IF(F32="NR",D32,0) -> 0 | J32: =IF(F32="NR",E32,0) -> 0
A33: 12601 | B33: =VLOOKUP(A33,DAF_AKUN,2,FALSE) -> Akm. Penyusutan Bangunan | C33: =VLOOKUP(A33,DAF_AKUN,3,FALSE) -> D | D33: =IF(C33="D",SUMIF(Akun!A:A,A33,Akun!F:F)+SUMIF(Jurnal!K:K,A33,Jurnal!N:N)-SUMIF(Jurnal!K:K,A33,Jurnal!O:O),0) -> 0 | E33: =IF(C33="K",SUMIF(Akun!A:A,A33,Akun!G:G)-SUMIF(Jurnal!K:K,A33,Jurnal!N:N)+SUMIF(Jurnal!K:K,A33,Jurnal!O:O),0) -> 0 | F33: =IF(ERR=FALSE,0,VLOOKUP(A33,DAF_AKUN,4,FALSE)) -> NR | G33: =IF(F33="LR",D33,0) -> 0 | H33: =IF(F33="LR",E33,0) -> 0 | I33: =IF(F33="NR",D33,0) -> 0 | J33: =IF(F33="NR",E33,0) -> 0
A34: 12602 | B34: =VLOOKUP(A34,DAF_AKUN,2,FALSE) -> Akm. Penyusutan Mesin | C34: =VLOOKUP(A34,DAF_AKUN,3,FALSE) -> D | D34: =IF(C34="D",SUMIF(Akun!A:A,A34,Akun!F:F)+SUMIF(Jurnal!K:K,A34,Jurnal!N:N)-SUMIF(Jurnal!K:K,A34,Jurnal!O:O),0) -> 0 | E34: =IF(C34="K",SUMIF(Akun!A:A,A34,Akun!G:G)-SUMIF(Jurnal!K:K,A34,Jurnal!N:N)+SUMIF(Jurnal!K:K,A34,Jurnal!O:O),0) -> 0 | F34: =IF(ERR=FALSE,0,VLOOKUP(A34,DAF_AKUN,4,FALSE)) -> NR | G34: =IF(F34="LR",D34,0) -> 0 | H34: =IF(F34="LR",E34,0) -> 0 | I34: =IF(F34="NR",D34,0) -> 0 | J34: =IF(F34="NR",E34,0) -> 0
A35: 12603 | B35: =VLOOKUP(A35,DAF_AKUN,2,FALSE) -> Akm. Penyusutan Peralatan Kantor | C35: =VLOOKUP(A35,DAF_AKUN,3,FALSE) -> D | D35: =IF(C35="D",SUMIF(Akun!A:A,A35,Akun!F:F)+SUMIF(Jurnal!K:K,A35,Jurnal!N:N)-SUMIF(Jurnal!K:K,A35,Jurnal!O:O),0) -> 0 | E35: =IF(C35="K",SUMIF(Akun!A:A,A35,Akun!G:G)-SUMIF(Jurnal!K:K,A35,Jurnal!N:N)+SUMIF(Jurnal!K:K,A35,Jurnal!O:O),0) -> 0 | F35: =IF(ERR=FALSE,0,VLOOKUP(A35,DAF_AKUN,4,FALSE)) -> NR | G35: =IF(F35="LR",D35,0) -> 0 | H35: =IF(F35="LR",E35,0) -> 0 | I35: =IF(F35="NR",D35,0) -> 0 | J35: =IF(F35="NR",E35,0) -> 0
A36: 12604 | B36: =VLOOKUP(A36,DAF_AKUN,2,FALSE) -> Akm. Penyusutan Kendaraan | C36: =VLOOKUP(A36,DAF_AKUN,3,FALSE) -> D | D36: =IF(C36="D",SUMIF(Akun!A:A,A36,Akun!F:F)+SUMIF(Jurnal!K:K,A36,Jurnal!N:N)-SUMIF(Jurnal!K:K,A36,Jurnal!O:O),0) -> 0 | E36: =IF(C36="K",SUMIF(Akun!A:A,A36,Akun!G:G)-SUMIF(Jurnal!K:K,A36,Jurnal!N:N)+SUMIF(Jurnal!K:K,A36,Jurnal!O:O),0) -> 0 | F36: =IF(ERR=FALSE,0,VLOOKUP(A36,DAF_AKUN,4,FALSE)) -> NR | G36: =IF(F36="LR",D36,0) -> 0 | H36: =IF(F36="LR",E36,0) -> 0 | I36: =IF(F36="NR",D36,0) -> 0 | J36: =IF(F36="NR",E36,0) -> 0
A37: 20000 | B37: =VLOOKUP(A37,DAF_AKUN,2,FALSE) -> KEWAJIBAN
A38: 21100 | B38: =VLOOKUP(A38,DAF_AKUN,2,FALSE) -> Hutang Dagang | C38: =VLOOKUP(A38,DAF_AKUN,3,FALSE) -> K | D38: =IF(C38="D",SUMIF(Akun!A:A,A38,Akun!F:F)+SUMIF(Jurnal!K:K,A38,Jurnal!N:N)-SUMIF(Jurnal!K:K,A38,Jurnal!O:O),0) -> 0 | E38: =IF(C38="K",SUMIF(Akun!A:A,A38,Akun!G:G)-SUMIF(Jurnal!K:K,A38,Jurnal!N:N)+SUMIF(Jurnal!K:K,A38,Jurnal!O:O),0) -> 7976548589 | F38: =IF(ERR=FALSE,0,VLOOKUP(A38,DAF_AKUN,4,FALSE)) -> NR | G38: =IF(F38="LR",D38,0) -> 0 | H38: =IF(F38="LR",E38,0) -> 0 | I38: =IF(F38="NR",D38,0) -> 0 | J38: =IF(F38="NR",E38,0) -> 7976548589
A39: 22101 | B39: =VLOOKUP(A39,DAF_AKUN,2,FALSE) -> Hutang Pph Final PP 46 | C39: =VLOOKUP(A39,DAF_AKUN,3,FALSE) -> K | D39: =IF(C39="D",SUMIF(Akun!A:A,A39,Akun!F:F)+SUMIF(Jurnal!K:K,A39,Jurnal!N:N)-SUMIF(Jurnal!K:K,A39,Jurnal!O:O),0) -> 0 | E39: =IF(C39="K",SUMIF(Akun!A:A,A39,Akun!G:G)-SUMIF(Jurnal!K:K,A39,Jurnal!N:N)+SUMIF(Jurnal!K:K,A39,Jurnal!O:O),0) -> 31589467 | F39: =IF(ERR=FALSE,0,VLOOKUP(A39,DAF_AKUN,4,FALSE)) -> NR | G39: =IF(F39="LR",D39,0) -> 0 | H39: =IF(F39="LR",E39,0) -> 0 | I39: =IF(F39="NR",D39,0) -> 0 | J39: =IF(F39="NR",E39,0) -> 31589467
A40: 22102 | B40: =VLOOKUP(A40,DAF_AKUN,2,FALSE) -> Hutang Pph Pasal 23 | C40: =VLOOKUP(A40,DAF_AKUN,3,FALSE) -> K | D40: =IF(C40="D",SUMIF(Akun!A:A,A40,Akun!F:F)+SUMIF(Jurnal!K:K,A40,Jurnal!N:N)-SUMIF(Jurnal!K:K,A40,Jurnal!O:O),0) -> 0 | E40: =IF(C40="K",SUMIF(Akun!A:A,A40,Akun!G:G)-SUMIF(Jurnal!K:K,A40,Jurnal!N:N)+SUMIF(Jurnal!K:K,A40,Jurnal!O:O),0) -> 0 | F40: =IF(ERR=FALSE,0,VLOOKUP(A40,DAF_AKUN,4,FALSE)) -> NR | G40: =IF(F40="LR",D40,0) -> 0 | H40: =IF(F40="LR",E40,0) -> 0 | I40: =IF(F40="NR",D40,0) -> 0 | J40: =IF(F40="NR",E40,0) -> 0
A41: 22103 | B41: =VLOOKUP(A41,DAF_AKUN,2,FALSE) -> Hutang Pph Pasal 4(2) | C41: =VLOOKUP(A41,DAF_AKUN,3,FALSE) -> K | D41: =IF(C41="D",SUMIF(Akun!A:A,A41,Akun!F:F)+SUMIF(Jurnal!K:K,A41,Jurnal!N:N)-SUMIF(Jurnal!K:K,A41,Jurnal!O:O),0) -> 0 | E41: =IF(C41="K",SUMIF(Akun!A:A,A41,Akun!G:G)-SUMIF(Jurnal!K:K,A41,Jurnal!N:N)+SUMIF(Jurnal!K:K,A41,Jurnal!O:O),0) -> 0 | F41: =IF(ERR=FALSE,0,VLOOKUP(A41,DAF_AKUN,4,FALSE)) -> NR | G41: =IF(F41="LR",D41,0) -> 0 | H41: =IF(F41="LR",E41,0) -> 0 | I41: =IF(F41="NR",D41,0) -> 0 | J41: =IF(F41="NR",E41,0) -> 0
A42: 22104 | B42: =VLOOKUP(A42,DAF_AKUN,2,FALSE) -> Hutang Pph Pasal 25/29 | C42: =VLOOKUP(A42,DAF_AKUN,3,FALSE) -> K | D42: =IF(C42="D",SUMIF(Akun!A:A,A42,Akun!F:F)+SUMIF(Jurnal!K:K,A42,Jurnal!N:N)-SUMIF(Jurnal!K:K,A42,Jurnal!O:O),0) -> 0 | E42: =IF(C42="K",SUMIF(Akun!A:A,A42,Akun!G:G)-SUMIF(Jurnal!K:K,A42,Jurnal!N:N)+SUMIF(Jurnal!K:K,A42,Jurnal!O:O),0) -> 0 | F42: =IF(ERR=FALSE,0,VLOOKUP(A42,DAF_AKUN,4,FALSE)) -> NR | G42: =IF(F42="LR",D42,0) -> 0 | H42: =IF(F42="LR",E42,0) -> 0 | I42: =IF(F42="NR",D42,0) -> 0 | J42: =IF(F42="NR",E42,0) -> 0
A43: 22105 | B43: =VLOOKUP(A43,DAF_AKUN,2,FALSE) -> PPN Keluaran | C43: =VLOOKUP(A43,DAF_AKUN,3,FALSE) -> K | D43: =IF(C43="D",SUMIF(Akun!A:A,A43,Akun!F:F)+SUMIF(Jurnal!K:K,A43,Jurnal!N:N)-SUMIF(Jurnal!K:K,A43,Jurnal!O:O),0) -> 0 | E43: =IF(C43="K",SUMIF(Akun!A:A,A43,Akun!G:G)-SUMIF(Jurnal!K:K,A43,Jurnal!N:N)+SUMIF(Jurnal!K:K,A43,Jurnal!O:O),0) -> 1.2607648e+08 | F43: =IF(ERR=FALSE,0,VLOOKUP(A43,DAF_AKUN,4,FALSE)) -> NR | G43: =IF(F43="LR",D43,0) -> 0 | H43: =IF(F43="LR",E43,0) -> 0 | I43: =IF(F43="NR",D43,0) -> 0 | J43: =IF(F43="NR",E43,0) -> 1.2607648e+08
A44: 23100 | B44: =VLOOKUP(A44,DAF_AKUN,2,FALSE) -> Hutang Bank | C44: =VLOOKUP(A44,DAF_AKUN,3,FALSE) -> K | D44: =IF(C44="D",SUMIF(Akun!A:A,A44,Akun!F:F)+SUMIF(Jurnal!K:K,A44,Jurnal!N:N)-SUMIF(Jurnal!K:K,A44,Jurnal!O:O),0) -> 0 | E44: =IF(C44="K",SUMIF(Akun!A:A,A44,Akun!G:G)-SUMIF(Jurnal!K:K,A44,Jurnal!N:N)+SUMIF(Jurnal!K:K,A44,Jurnal!O:O),0) -> 0 | F44: =IF(ERR=FALSE,0,VLOOKUP(A44,DAF_AKUN,4,FALSE)) -> NR | G44: =IF(F44="LR",D44,0) -> 0 | H44: =IF(F44="LR",E44,0) -> 0 | I44: =IF(F44="NR",D44,0) -> 0 | J44: =IF(F44="NR",E44,0) -> 0
A45: 24100 | B45: =VLOOKUP(A45,DAF_AKUN,2,FALSE) -> Hutang Biaya | C45: =VLOOKUP(A45,DAF_AKUN,3,FALSE) -> K | D45: =IF(C45="D",SUMIF(Akun!A:A,A45,Akun!F:F)+SUMIF(Jurnal!K:K,A45,Jurnal!N:N)-SUMIF(Jurnal!K:K,A45,Jurnal!O:O),0) -> 0 | E45: =IF(C45="K",SUMIF(Akun!A:A,A45,Akun!G:G)-SUMIF(Jurnal!K:K,A45,Jurnal!N:N)+SUMIF(Jurnal!K:K,A45,Jurnal!O:O),0) -> 6504600 | F45: =IF(ERR=FALSE,0,VLOOKUP(A45,DAF_AKUN,4,FALSE)) -> NR | G45: =IF(F45="LR",D45,0) -> 0 | H45: =IF(F45="LR",E45,0) -> 0 | I45: =IF(F45="NR",D45,0) -> 0 | J45: =IF(F45="NR",E45,0) -> 6504600
A46: 25100 | B46: =VLOOKUP(A46,DAF_AKUN,2,FALSE) -> Hutang Lain-lain | C46: =VLOOKUP(A46,DAF_AKUN,3,FALSE) -> K | D46: =IF(C46="D",SUMIF(Akun!A:A,A46,Akun!F:F)+SUMIF(Jurnal!K:K,A46,Jurnal!N:N)-SUMIF(Jurnal!K:K,A46,Jurnal!O:O),0) -> 0 | E46: =IF(C46="K",SUMIF(Akun!A:A,A46,Akun!G:G)-SUMIF(Jurnal!K:K,A46,Jurnal!N:N)+SUMIF(Jurnal!K:K,A46,Jurnal!O:O),0) -> 0 | F46: =IF(ERR=FALSE,0,VLOOKUP(A46,DAF_AKUN,4,FALSE)) -> NR | G46: =IF(F46="LR",D46,0) -> 0 | H46: =IF(F46="LR",E46,0) -> 0 | I46: =IF(F46="NR",D46,0) -> 0 | J46: =IF(F46="NR",E46,0) -> 0
A47: 26100 | B47: =VLOOKUP(A47,DAF_AKUN,2,FALSE) -> Hutang Pemegang Saham | C47: =VLOOKUP(A47,DAF_AKUN,3,FALSE) -> K | D47: =IF(C47="D",SUMIF(Akun!A:A,A47,Akun!F:F)+SUMIF(Jurnal!K:K,A47,Jurnal!N:N)-SUMIF(Jurnal!K:K,A47,Jurnal!O:O),0) -> 0 | E47: =IF(C47="K",SUMIF(Akun!A:A,A47,Akun!G:G)-SUMIF(Jurnal!K:K,A47,Jurnal!N:N)+SUMIF(Jurnal!K:K,A47,Jurnal!O:O),0) -> 0 | F47: =IF(ERR=FALSE,0,VLOOKUP(A47,DAF_AKUN,4,FALSE)) -> NR | G47: =IF(F47="LR",D47,0) -> 0 | H47: =IF(F47="LR",E47,0) -> 0 | I47: =IF(F47="NR",D47,0) -> 0 | J47: =IF(F47="NR",E47,0) -> 0
A48: 27100 | B48: =VLOOKUP(A48,DAF_AKUN,2,FALSE) -> Uang Muka Penjualan | C48: =VLOOKUP(A48,DAF_AKUN,3,FALSE) -> K | D48: =IF(C48="D",SUMIF(Akun!A:A,A48,Akun!F:F)+SUMIF(Jurnal!K:K,A48,Jurnal!N:N)-SUMIF(Jurnal!K:K,A48,Jurnal!O:O),0) -> 0 | E48: =IF(C48="K",SUMIF(Akun!A:A,A48,Akun!G:G)-SUMIF(Jurnal!K:K,A48,Jurnal!N:N)+SUMIF(Jurnal!K:K,A48,Jurnal!O:O),0) -> 18857 | F48: =IF(ERR=FALSE,0,VLOOKUP(A48,DAF_AKUN,4,FALSE)) -> NR | G48: =IF(F48="LR",D48,0) -> 0 | H48: =IF(F48="LR",E48,0) -> 0 | I48: =IF(F48="NR",D48,0) -> 0 | J48: =IF(F48="NR",E48,0) -> 18857
A49: 30000 | B49: =VLOOKUP(A49,DAF_AKUN,2,FALSE) -> EKUITAS
A50: 31000 | B50: =VLOOKUP(A50,DAF_AKUN,2,FALSE) -> Modal | C50: =VLOOKUP(A50,DAF_AKUN,3,FALSE) -> K | D50: =IF(C50="D",SUMIF(Akun!A:A,A50,Akun!F:F)+SUMIF(Jurnal!K:K,A50,Jurnal!N:N)-SUMIF(Jurnal!K:K,A50,Jurnal!O:O),0) -> 0 | E50: =IF(C50="K",SUMIF(Akun!A:A,A50,Akun!G:G)-SUMIF(Jurnal!K:K,A50,Jurnal!N:N)+SUMIF(Jurnal!K:K,A50,Jurnal!O:O),0) -> 11488144544 | F50: =IF(ERR=FALSE,0,VLOOKUP(A50,DAF_AKUN,4,FALSE)) -> NR | G50: =IF(F50="LR",D50,0) -> 0 | H50: =IF(F50="LR",E50,0) -> 0 | I50: =IF(F50="NR",D50,0) -> 0 | J50: =IF(F50="NR",E50,0) -> 11488144544
A51: 32000 | B51: =VLOOKUP(A51,DAF_AKUN,2,FALSE) -> Laba Ditahan Amnesty | C51: =VLOOKUP(A51,DAF_AKUN,3,FALSE) -> K | D51: =IF(C51="D",SUMIF(Akun!A:A,A51,Akun!F:F)+SUMIF(Jurnal!K:K,A51,Jurnal!N:N)-SUMIF(Jurnal!K:K,A51,Jurnal!O:O),0) -> 0 | E51: =IF(C51="K",SUMIF(Akun!A:A,A51,Akun!G:G)-SUMIF(Jurnal!K:K,A51,Jurnal!N:N)+SUMIF(Jurnal!K:K,A51,Jurnal!O:O),0) -> 1500000000 | F51: =IF(ERR=FALSE,0,VLOOKUP(A51,DAF_AKUN,4,FALSE)) -> NR | G51: =IF(F51="LR",D51,0) -> 0 | H51: =IF(F51="LR",E51,0) -> 0 | I51: =IF(F51="NR",D51,0) -> 0 | J51: =IF(F51="NR",E51,0) -> 1500000000
A52: 33000 | B52: =VLOOKUP(A52,DAF_AKUN,2,FALSE) -> Prive | C52: =VLOOKUP(A52,DAF_AKUN,3,FALSE) -> D | D52: =IF(C52="D",SUMIF(Akun!A:A,A52,Akun!F:F)+SUMIF(Jurnal!K:K,A52,Jurnal!N:N)-SUMIF(Jurnal!K:K,A52,Jurnal!O:O),0) -> 0 | E52: =IF(C52="K",SUMIF(Akun!A:A,A52,Akun!G:G)-SUMIF(Jurnal!K:K,A52,Jurnal!N:N)+SUMIF(Jurnal!K:K,A52,Jurnal!O:O),0) -> 0 | F52: =IF(ERR=FALSE,0,VLOOKUP(A52,DAF_AKUN,4,FALSE)) -> LR | G52: =IF(F52="LR",D52,0) -> 0 | H52: =IF(F52="LR",E52,0) -> 0 | I52: =IF(F52="NR",D52,0) -> 0 | J52: =IF(F52="NR",E52,0) -> 0
A53: 34000 | B53: =VLOOKUP(A53,DAF_AKUN,2,FALSE) -> Pajak Penghasilan | C53: =VLOOKUP(A53,DAF_AKUN,3,FALSE) -> D | D53: =IF(C53="D",SUMIF(Akun!A:A,A53,Akun!F:F)+SUMIF(Jurnal!K:K,A53,Jurnal!N:N)-SUMIF(Jurnal!K:K,A53,Jurnal!O:O),0) -> 0 | E53: =IF(C53="K",SUMIF(Akun!A:A,A53,Akun!G:G)-SUMIF(Jurnal!K:K,A53,Jurnal!N:N)+SUMIF(Jurnal!K:K,A53,Jurnal!O:O),0) -> 0 | F53: =IF(ERR=FALSE,0,VLOOKUP(A53,DAF_AKUN,4,FALSE)) -> LR | G53: =IF(F53="LR",D53,0) -> 0 | H53: =IF(F53="LR",E53,0) -> 0 | I53: =IF(F53="NR",D53,0) -> 0 | J53: =IF(F53="NR",E53,0) -> 0
A54: 40000 | B54: =VLOOKUP(A54,DAF_AKUN,2,FALSE) -> PENDAPATAN
A55: 41000 | B55: =VLOOKUP(A55,DAF_AKUN,2,FALSE) -> Penjualan Barang | C55: =VLOOKUP(A55,DAF_AKUN,3,FALSE) -> K | D55: =IF(C55="D",SUMIF(Akun!A:A,A55,Akun!F:F)+SUMIF(Jurnal!K:K,A55,Jurnal!N:N)-SUMIF(Jurnal!K:K,A55,Jurnal!O:O),0) -> 0 | E55: =IF(C55="K",SUMIF(Akun!A:A,A55,Akun!G:G)-SUMIF(Jurnal!K:K,A55,Jurnal!N:N)+SUMIF(Jurnal!K:K,A55,Jurnal!O:O),0) -> 1.1471778e+09 | F55: =IF(ERR=FALSE,0,VLOOKUP(A55,DAF_AKUN,4,FALSE)) -> LR | G55: =IF(F55="LR",D55,0) -> 0 | H55: =IF(F55="LR",E55,0) -> 1.1471778e+09 | I55: =IF(F55="NR",D55,0) -> 0 | J55: =IF(F55="NR",E55,0) -> 0
A56: 41001 | B56: =VLOOKUP(A56,DAF_AKUN,2,FALSE) -> Retur Penjualan Barang | C56: =VLOOKUP(A56,DAF_AKUN,3,FALSE) -> K | D56: =IF(C56="D",SUMIF(Akun!A:A,A56,Akun!F:F)+SUMIF(Jurnal!K:K,A56,Jurnal!N:N)-SUMIF(Jurnal!K:K,A56,Jurnal!O:O),0) -> 0 | E56: =IF(C56="K",SUMIF(Akun!A:A,A56,Akun!G:G)-SUMIF(Jurnal!K:K,A56,Jurnal!N:N)+SUMIF(Jurnal!K:K,A56,Jurnal!O:O),0) -> 0 | F56: =IF(ERR=FALSE,0,VLOOKUP(A56,DAF_AKUN,4,FALSE)) -> LR | G56: =IF(F56="LR",D56,0) -> 0 | H56: =IF(F56="LR",E56,0) -> 0 | I56: =IF(F56="NR",D56,0) -> 0 | J56: =IF(F56="NR",E56,0) -> 0
A57: 41002 | B57: =VLOOKUP(A57,DAF_AKUN,2,FALSE) -> Pendapatan Lain-lain | C57: =VLOOKUP(A57,DAF_AKUN,3,FALSE) -> K | D57: =IF(C57="D",SUMIF(Akun!A:A,A57,Akun!F:F)+SUMIF(Jurnal!K:K,A57,Jurnal!N:N)-SUMIF(Jurnal!K:K,A57,Jurnal!O:O),0) -> 0 | E57: =IF(C57="K",SUMIF(Akun!A:A,A57,Akun!G:G)-SUMIF(Jurnal!K:K,A57,Jurnal!N:N)+SUMIF(Jurnal!K:K,A57,Jurnal!O:O),0) -> 18400 | F57: =IF(ERR=FALSE,0,VLOOKUP(A57,DAF_AKUN,4,FALSE)) -> LR | G57: =IF(F57="LR",D57,0) -> 0 | H57: =IF(F57="LR",E57,0) -> 18400 | I57: =IF(F57="NR",D57,0) -> 0 | J57: =IF(F57="NR",E57,0) -> 0
A58: 50000 | B58: =VLOOKUP(A58,DAF_AKUN,2,FALSE) -> HARGA POKOK PENJUALAN
A59: 51000 | B59: =VLOOKUP(A59,DAF_AKUN,2,FALSE) -> Persediaan Bahan Baku Awal | C59: =VLOOKUP(A59,DAF_AKUN,3,FALSE) -> D | D59: =IF(C59="D",SUMIF(Akun!A:A,A59,Akun!F:F)+SUMIF(Jurnal!K:K,A59,Jurnal!N:N)-SUMIF(Jurnal!K:K,A59,Jurnal!O:O),0) -> 0 | E59: =IF(C59="K",SUMIF(Akun!A:A,A59,Akun!G:G)-SUMIF(Jurnal!K:K,A59,Jurnal!N:N)+SUMIF(Jurnal!K:K,A59,Jurnal!O:O),0) -> 0 | F59: =IF(ERR=FALSE,0,VLOOKUP(A59,DAF_AKUN,4,FALSE)) -> LR | G59: =IF(F59="LR",D59,0) -> 0 | H59: =IF(F59="LR",E59,0) -> 0 | I59: =IF(F59="NR",D59,0) -> 0 | J59: =IF(F59="NR",E59,0) -> 0
A60: 52000 | B60: =VLOOKUP(A60,DAF_AKUN,2,FALSE) -> Persediaan Bahan Baku Akhir | C60: =VLOOKUP(A60,DAF_AKUN,3,FALSE) -> D | D60: =IF(C60="D",SUMIF(Akun!A:A,A60,Akun!F:F)+SUMIF(Jurnal!K:K,A60,Jurnal!N:N)-SUMIF(Jurnal!K:K,A60,Jurnal!O:O),0) -> 0 | E60: =IF(C60="K",SUMIF(Akun!A:A,A60,Akun!G:G)-SUMIF(Jurnal!K:K,A60,Jurnal!N:N)+SUMIF(Jurnal!K:K,A60,Jurnal!O:O),0) -> 0 | F60: =IF(ERR=FALSE,0,VLOOKUP(A60,DAF_AKUN,4,FALSE)) -> LR | G60: =IF(F60="LR",D60,0) -> 0 | H60: =IF(F60="LR",E60,0) -> 0 | I60: =IF(F60="NR",D60,0) -> 0 | J60: =IF(F60="NR",E60,0) -> 0
A61: 53000 | B61: =VLOOKUP(A61,DAF_AKUN,2,FALSE) -> Pembelian Bahan Baku | C61: =VLOOKUP(A61,DAF_AKUN,3,FALSE) -> D | D61: =IF(C61="D",SUMIF(Akun!A:A,A61,Akun!F:F)+SUMIF(Jurnal!K:K,A61,Jurnal!N:N)-SUMIF(Jurnal!K:K,A61,Jurnal!O:O),0) -> 581342640 | E61: =IF(C61="K",SUMIF(Akun!A:A,A61,Akun!G:G)-SUMIF(Jurnal!K:K,A61,Jurnal!N:N)+SUMIF(Jurnal!K:K,A61,Jurnal!O:O),0) -> 0 | F61: =IF(ERR=FALSE,0,VLOOKUP(A61,DAF_AKUN,4,FALSE)) -> LR | G61: =IF(F61="LR",D61,0) -> 581342640 | H61: =IF(F61="LR",E61,0) -> 0 | I61: =IF(F61="NR",D61,0) -> 0 | J61: =IF(F61="NR",E61,0) -> 0
A62: 53001 | B62: =VLOOKUP(A62,DAF_AKUN,2,FALSE) -> Persediaan Bahan Penolong Awal | C62: =VLOOKUP(A62,DAF_AKUN,3,FALSE) -> D | D62: =IF(C62="D",SUMIF(Akun!A:A,A62,Akun!F:F)+SUMIF(Jurnal!K:K,A62,Jurnal!N:N)-SUMIF(Jurnal!K:K,A62,Jurnal!O:O),0) -> 0 | E62: =IF(C62="K",SUMIF(Akun!A:A,A62,Akun!G:G)-SUMIF(Jurnal!K:K,A62,Jurnal!N:N)+SUMIF(Jurnal!K:K,A62,Jurnal!O:O),0) -> 0 | F62: =IF(ERR=FALSE,0,VLOOKUP(A62,DAF_AKUN,4,FALSE)) -> LR | G62: =IF(F62="LR",D62,0) -> 0 | H62: =IF(F62="LR",E62,0) -> 0 | I62: =IF(F62="NR",D62,0) -> 0 | J62: =IF(F62="NR",E62,0) -> 0
A63: 53002 | B63: =VLOOKUP(A63,DAF_AKUN,2,FALSE) -> Persediaan Bahan Penolong Akhir | C63: =VLOOKUP(A63,DAF_AKUN,3,FALSE) -> D | D63: =IF(C63="D",SUMIF(Akun!A:A,A63,Akun!F:F)+SUMIF(Jurnal!K:K,A63,Jurnal!N:N)-SUMIF(Jurnal!K:K,A63,Jurnal!O:O),0) -> 0 | E63: =IF(C63="K",SUMIF(Akun!A:A,A63,Akun!G:G)-SUMIF(Jurnal!K:K,A63,Jurnal!N:N)+SUMIF(Jurnal!K:K,A63,Jurnal!O:O),0) -> 0 | F63: =IF(ERR=FALSE,0,VLOOKUP(A63,DAF_AKUN,4,FALSE)) -> LR | G63: =IF(F63="LR",D63,0) -> 0 | H63: =IF(F63="LR",E63,0) -> 0 | I63: =IF(F63="NR",D63,0) -> 0 | J63: =IF(F63="NR",E63,0) -> 0
A64: 53003 | B64: =VLOOKUP(A64,DAF_AKUN,2,FALSE) -> Pembelian Bahan Penolong | C64: =VLOOKUP(A64,DAF_AKUN,3,FALSE) -> D | D64: =IF(C64="D",SUMIF(Akun!A:A,A64,Akun!F:F)+SUMIF(Jurnal!K:K,A64,Jurnal!N:N)-SUMIF(Jurnal!K:K,A64,Jurnal!O:O),0) -> 13661887 | E64: =IF(C64="K",SUMIF(Akun!A:A,A64,Akun!G:G)-SUMIF(Jurnal!K:K,A64,Jurnal!N:N)+SUMIF(Jurnal!K:K,A64,Jurnal!O:O),0) -> 0 | F64: =IF(ERR=FALSE,0,VLOOKUP(A64,DAF_AKUN,4,FALSE)) -> LR | G64: =IF(F64="LR",D64,0) -> 13661887 | H64: =IF(F64="LR",E64,0) -> 0 | I64: =IF(F64="NR",D64,0) -> 0 | J64: =IF(F64="NR",E64,0) -> 0
A65: 53004 | B65: =VLOOKUP(A65,DAF_AKUN,2,FALSE) -> Tenaga Kerja Langsung | C65: =VLOOKUP(A65,DAF_AKUN,3,FALSE) -> D | D65: =IF(C65="D",SUMIF(Akun!A:A,A65,Akun!F:F)+SUMIF(Jurnal!K:K,A65,Jurnal!N:N)-SUMIF(Jurnal!K:K,A65,Jurnal!O:O),0) -> 0 | E65: =IF(C65="K",SUMIF(Akun!A:A,A65,Akun!G:G)-SUMIF(Jurnal!K:K,A65,Jurnal!N:N)+SUMIF(Jurnal!K:K,A65,Jurnal!O:O),0) -> 0 | F65: =IF(ERR=FALSE,0,VLOOKUP(A65,DAF_AKUN,4,FALSE)) -> LR | G65: =IF(F65="LR",D65,0) -> 0 | H65: =IF(F65="LR",E65,0) -> 0 | I65: =IF(F65="NR",D65,0) -> 0 | J65: =IF(F65="NR",E65,0) -> 0
A66: 53005 | B66: =VLOOKUP(A66,DAF_AKUN,2,FALSE) -> Biaya Listrik | C66: =VLOOKUP(A66,DAF_AKUN,3,FALSE) -> D | D66: =IF(C66="D",SUMIF(Akun!A:A,A66,Akun!F:F)+SUMIF(Jurnal!K:K,A66,Jurnal!N:N)-SUMIF(Jurnal!K:K,A66,Jurnal!O:O),0) -> 0 | E66: =IF(C66="K",SUMIF(Akun!A:A,A66,Akun!G:G)-SUMIF(Jurnal!K:K,A66,Jurnal!N:N)+SUMIF(Jurnal!K:K,A66,Jurnal!O:O),0) -> 0 | F66: =IF(ERR=FALSE,0,VLOOKUP(A66,DAF_AKUN,4,FALSE)) -> LR | G66: =IF(F66="LR",D66,0) -> 0 | H66: =IF(F66="LR",E66,0) -> 0 | I66: =IF(F66="NR",D66,0) -> 0 | J66: =IF(F66="NR",E66,0) -> 0
A67: 60000 | B67: =VLOOKUP(A67,DAF_AKUN,2,FALSE) -> BIAYA OPERASIONAL
A68: 61000 | B68: =VLOOKUP(A68,DAF_AKUN,2,FALSE) -> BIAYA MANAJEMEN :
A69: 61001 | B69: =VLOOKUP(A69,DAF_AKUN,2,FALSE) -> Gaji & Tunjangan | C69: =VLOOKUP(A69,DAF_AKUN,3,FALSE) -> D | D69: =IF(C69="D",SUMIF(Akun!A:A,A69,Akun!F:F)+SUMIF(Jurnal!K:K,A69,Jurnal!N:N)-SUMIF(Jurnal!K:K,A69,Jurnal!O:O),0) -> 0 | E69: =IF(C69="K",SUMIF(Akun!A:A,A69,Akun!G:G)-SUMIF(Jurnal!K:K,A69,Jurnal!N:N)+SUMIF(Jurnal!K:K,A69,Jurnal!O:O),0) -> 0 | F69: =IF(ERR=FALSE,0,VLOOKUP(A69,DAF_AKUN,4,FALSE)) -> LR | G69: =IF(F69="LR",D69,0) -> 0 | H69: =IF(F69="LR",E69,0) -> 0 | I69: =IF(F69="NR",D69,0) -> 0 | J69: =IF(F69="NR",E69,0) -> 0
A70: 61002 | B70: =VLOOKUP(A70,DAF_AKUN,2,FALSE) -> Asuransi Tenaga Kerja | C70: =VLOOKUP(A70,DAF_AKUN,3,FALSE) -> D | D70: =IF(C70="D",SUMIF(Akun!A:A,A70,Akun!F:F)+SUMIF(Jurnal!K:K,A70,Jurnal!N:N)-SUMIF(Jurnal!K:K,A70,Jurnal!O:O),0) -> 10128075 | E70: =IF(C70="K",SUMIF(Akun!A:A,A70,Akun!G:G)-SUMIF(Jurnal!K:K,A70,Jurnal!N:N)+SUMIF(Jurnal!K:K,A70,Jurnal!O:O),0) -> 0 | F70: =IF(ERR=FALSE,0,VLOOKUP(A70,DAF_AKUN,4,FALSE)) -> LR | G70: =IF(F70="LR",D70,0) -> 10128075 | H70: =IF(F70="LR",E70,0) -> 0 | I70: =IF(F70="NR",D70,0) -> 0 | J70: =IF(F70="NR",E70,0) -> 0
A71: 61003 | B71: =VLOOKUP(A71,DAF_AKUN,2,FALSE) -> Perjalanan Dinas | C71: =VLOOKUP(A71,DAF_AKUN,3,FALSE) -> D | D71: =IF(C71="D",SUMIF(Akun!A:A,A71,Akun!F:F)+SUMIF(Jurnal!K:K,A71,Jurnal!N:N)-SUMIF(Jurnal!K:K,A71,Jurnal!O:O),0) -> 0 | E71: =IF(C71="K",SUMIF(Akun!A:A,A71,Akun!G:G)-SUMIF(Jurnal!K:K,A71,Jurnal!N:N)+SUMIF(Jurnal!K:K,A71,Jurnal!O:O),0) -> 0 | F71: =IF(ERR=FALSE,0,VLOOKUP(A71,DAF_AKUN,4,FALSE)) -> LR | G71: =IF(F71="LR",D71,0) -> 0 | H71: =IF(F71="LR",E71,0) -> 0 | I71: =IF(F71="NR",D71,0) -> 0 | J71: =IF(F71="NR",E71,0) -> 0
A72: 61004 | B72: =VLOOKUP(A72,DAF_AKUN,2,FALSE) -> Biaya Konsultan Pajak | C72: =VLOOKUP(A72,DAF_AKUN,3,FALSE) -> D | D72: =IF(C72="D",SUMIF(Akun!A:A,A72,Akun!F:F)+SUMIF(Jurnal!K:K,A72,Jurnal!N:N)-SUMIF(Jurnal!K:K,A72,Jurnal!O:O),0) -> 2000000 | E72: =IF(C72="K",SUMIF(Akun!A:A,A72,Akun!G:G)-SUMIF(Jurnal!K:K,A72,Jurnal!N:N)+SUMIF(Jurnal!K:K,A72,Jurnal!O:O),0) -> 0 | F72: =IF(ERR=FALSE,0,VLOOKUP(A72,DAF_AKUN,4,FALSE)) -> LR | G72: =IF(F72="LR",D72,0) -> 2000000 | H72: =IF(F72="LR",E72,0) -> 0 | I72: =IF(F72="NR",D72,0) -> 0 | J72: =IF(F72="NR",E72,0) -> 0
A73: 62000 | B73: =VLOOKUP(A73,DAF_AKUN,2,FALSE) -> BIAYA PENJUALAN :
A74: 62001 | B74: =VLOOKUP(A74,DAF_AKUN,2,FALSE) -> Ongkos Kirim | C74: =VLOOKUP(A74,DAF_AKUN,3,FALSE) -> D | D74: =IF(C74="D",SUMIF(Akun!A:A,A74,Akun!F:F)+SUMIF(Jurnal!K:K,A74,Jurnal!N:N)-SUMIF(Jurnal!K:K,A74,Jurnal!O:O),0) -> 0 | E74: =IF(C74="K",SUMIF(Akun!A:A,A74,Akun!G:G)-SUMIF(Jurnal!K:K,A74,Jurnal!N:N)+SUMIF(Jurnal!K:K,A74,Jurnal!O:O),0) -> 0 | F74: =IF(ERR=FALSE,0,VLOOKUP(A74,DAF_AKUN,4,FALSE)) -> LR | G74: =IF(F74="LR",D74,0) -> 0 | H74: =IF(F74="LR",E74,0) -> 0 | I74: =IF(F74="NR",D74,0) -> 0 | J74: =IF(F74="NR",E74,0) -> 0
A75: 62002 | B75: =VLOOKUP(A75,DAF_AKUN,2,FALSE) -> BBM dan Parkir | C75: =VLOOKUP(A75,DAF_AKUN,3,FALSE) -> D | D75: =IF(C75="D",SUMIF(Akun!A:A,A75,Akun!F:F)+SUMIF(Jurnal!K:K,A75,Jurnal!N:N)-SUMIF(Jurnal!K:K,A75,Jurnal!O:O),0) -> 0 | E75: =IF(C75="K",SUMIF(Akun!A:A,A75,Akun!G:G)-SUMIF(Jurnal!K:K,A75,Jurnal!N:N)+SUMIF(Jurnal!K:K,A75,Jurnal!O:O),0) -> 0 | F75: =IF(ERR=FALSE,0,VLOOKUP(A75,DAF_AKUN,4,FALSE)) -> LR | G75: =IF(F75="LR",D75,0) -> 0 | H75: =IF(F75="LR",E75,0) -> 0 | I75: =IF(F75="NR",D75,0) -> 0 | J75: =IF(F75="NR",E75,0) -> 0
A76: 62003 | B76: =VLOOKUP(A76,DAF_AKUN,2,FALSE) -> Pamflet & Brosur | C76: =VLOOKUP(A76,DAF_AKUN,3,FALSE) -> D | D76: =IF(C76="D",SUMIF(Akun!A:A,A76,Akun!F:F)+SUMIF(Jurnal!K:K,A76,Jurnal!N:N)-SUMIF(Jurnal!K:K,A76,Jurnal!O:O),0) -> 0 | E76: =IF(C76="K",SUMIF(Akun!A:A,A76,Akun!G:G)-SUMIF(Jurnal!K:K,A76,Jurnal!N:N)+SUMIF(Jurnal!K:K,A76,Jurnal!O:O),0) -> 0 | F76: =IF(ERR=FALSE,0,VLOOKUP(A76,DAF_AKUN,4,FALSE)) -> LR | G76: =IF(F76="LR",D76,0) -> 0 | H76: =IF(F76="LR",E76,0) -> 0 | I76: =IF(F76="NR",D76,0) -> 0 | J76: =IF(F76="NR",E76,0) -> 0
A77: 63000 | B77: =VLOOKUP(A77,DAF_AKUN,2,FALSE) -> BIAYA UMUM & ADMINISTRASI :
A78: 63001 | B78: =VLOOKUP(A78,DAF_AKUN,2,FALSE) -> Penyusutan | C78: =VLOOKUP(A78,DAF_AKUN,3,FALSE) -> D | D78: =IF(C78="D",SUMIF(Akun!A:A,A78,Akun!F:F)+SUMIF(Jurnal!K:K,A78,Jurnal!N:N)-SUMIF(Jurnal!K:K,A78,Jurnal!O:O),0) -> 0 | E78: =IF(C78="K",SUMIF(Akun!A:A,A78,Akun!G:G)-SUMIF(Jurnal!K:K,A78,Jurnal!N:N)+SUMIF(Jurnal!K:K,A78,Jurnal!O:O),0) -> 0 | F78: =IF(ERR=FALSE,0,VLOOKUP(A78,DAF_AKUN,4,FALSE)) -> LR | G78: =IF(F78="LR",D78,0) -> 0 | H78: =IF(F78="LR",E78,0) -> 0 | I78: =IF(F78="NR",D78,0) -> 0 | J78: =IF(F78="NR",E78,0) -> 0
A79: 63002 | B79: =VLOOKUP(A79,DAF_AKUN,2,FALSE) -> Telepon | C79: =VLOOKUP(A79,DAF_AKUN,3,FALSE) -> D | D79: =IF(C79="D",SUMIF(Akun!A:A,A79,Akun!F:F)+SUMIF(Jurnal!K:K,A79,Jurnal!N:N)-SUMIF(Jurnal!K:K,A79,Jurnal!O:O),0) -> 2130762 | E79: =IF(C79="K",SUMIF(Akun!A:A,A79,Akun!G:G)-SUMIF(Jurnal!K:K,A79,Jurnal!N:N)+SUMIF(Jurnal!K:K,A79,Jurnal!O:O),0) -> 0 | F79: =IF(ERR=FALSE,0,VLOOKUP(A79,DAF_AKUN,4,FALSE)) -> LR | G79: =IF(F79="LR",D79,0) -> 2130762 | H79: =IF(F79="LR",E79,0) -> 0 | I79: =IF(F79="NR",D79,0) -> 0 | J79: =IF(F79="NR",E79,0) -> 0
A80: 63003 | B80: =VLOOKUP(A80,DAF_AKUN,2,FALSE) -> Internet | C80: =VLOOKUP(A80,DAF_AKUN,3,FALSE) -> D | D80: =IF(C80="D",SUMIF(Akun!A:A,A80,Akun!F:F)+SUMIF(Jurnal!K:K,A80,Jurnal!N:N)-SUMIF(Jurnal!K:K,A80,Jurnal!O:O),0) -> 0 | E80: =IF(C80="K",SUMIF(Akun!A:A,A80,Akun!G:G)-SUMIF(Jurnal!K:K,A80,Jurnal!N:N)+SUMIF(Jurnal!K:K,A80,Jurnal!O:O),0) -> 0 | F80: =IF(ERR=FALSE,0,VLOOKUP(A80,DAF_AKUN,4,FALSE)) -> LR | G80: =IF(F80="LR",D80,0) -> 0 | H80: =IF(F80="LR",E80,0) -> 0 | I80: =IF(F80="NR",D80,0) -> 0 | J80: =IF(F80="NR",E80,0) -> 0
A81: 63004 | B81: =VLOOKUP(A81,DAF_AKUN,2,FALSE) -> Listrik & Air | C81: =VLOOKUP(A81,DAF_AKUN,3,FALSE) -> D | D81: =IF(C81="D",SUMIF(Akun!A:A,A81,Akun!F:F)+SUMIF(Jurnal!K:K,A81,Jurnal!N:N)-SUMIF(Jurnal!K:K,A81,Jurnal!O:O),0) -> 38500099 | E81: =IF(C81="K",SUMIF(Akun!A:A,A81,Akun!G:G)-SUMIF(Jurnal!K:K,A81,Jurnal!N:N)+SUMIF(Jurnal!K:K,A81,Jurnal!O:O),0) -> 0 | F81: =IF(ERR=FALSE,0,VLOOKUP(A81,DAF_AKUN,4,FALSE)) -> LR | G81: =IF(F81="LR",D81,0) -> 38500099 | H81: =IF(F81="LR",E81,0) -> 0 | I81: =IF(F81="NR",D81,0) -> 0 | J81: =IF(F81="NR",E81,0) -> 0
A82: 63005 | B82: =VLOOKUP(A82,DAF_AKUN,2,FALSE) -> Rapat/Pelatihan Karyawan | C82: =VLOOKUP(A82,DAF_AKUN,3,FALSE) -> D | D82: =IF(C82="D",SUMIF(Akun!A:A,A82,Akun!F:F)+SUMIF(Jurnal!K:K,A82,Jurnal!N:N)-SUMIF(Jurnal!K:K,A82,Jurnal!O:O),0) -> 0 | E82: =IF(C82="K",SUMIF(Akun!A:A,A82,Akun!G:G)-SUMIF(Jurnal!K:K,A82,Jurnal!N:N)+SUMIF(Jurnal!K:K,A82,Jurnal!O:O),0) -> 0 | F82: =IF(ERR=FALSE,0,VLOOKUP(A82,DAF_AKUN,4,FALSE)) -> LR | G82: =IF(F82="LR",D82,0) -> 0 | H82: =IF(F82="LR",E82,0) -> 0 | I82: =IF(F82="NR",D82,0) -> 0 | J82: =IF(F82="NR",E82,0) -> 0
A83: 63006 | B83: =VLOOKUP(A83,DAF_AKUN,2,FALSE) -> Perlengkapan Kantor | C83: =VLOOKUP(A83,DAF_AKUN,3,FALSE) -> D | D83: =IF(C83="D",SUMIF(Akun!A:A,A83,Akun!F:F)+SUMIF(Jurnal!K:K,A83,Jurnal!N:N)-SUMIF(Jurnal!K:K,A83,Jurnal!O:O),0) -> 0 | E83: =IF(C83="K",SUMIF(Akun!A:A,A83,Akun!G:G)-SUMIF(Jurnal!K:K,A83,Jurnal!N:N)+SUMIF(Jurnal!K:K,A83,Jurnal!O:O),0) -> 0 | F83: =IF(ERR=FALSE,0,VLOOKUP(A83,DAF_AKUN,4,FALSE)) -> LR | G83: =IF(F83="LR",D83,0) -> 0 | H83: =IF(F83="LR",E83,0) -> 0 | I83: =IF(F83="NR",D83,0) -> 0 | J83: =IF(F83="NR",E83,0) -> 0
A84: 63007 | B84: =VLOOKUP(A84,DAF_AKUN,2,FALSE) -> Administrasi Kantor (ATK) | C84: =VLOOKUP(A84,DAF_AKUN,3,FALSE) -> D | D84: =IF(C84="D",SUMIF(Akun!A:A,A84,Akun!F:F)+SUMIF(Jurnal!K:K,A84,Jurnal!N:N)-SUMIF(Jurnal!K:K,A84,Jurnal!O:O),0) -> 0 | E84: =IF(C84="K",SUMIF(Akun!A:A,A84,Akun!G:G)-SUMIF(Jurnal!K:K,A84,Jurnal!N:N)+SUMIF(Jurnal!K:K,A84,Jurnal!O:O),0) -> 0 | F84: =IF(ERR=FALSE,0,VLOOKUP(A84,DAF_AKUN,4,FALSE)) -> LR | G84: =IF(F84="LR",D84,0) -> 0 | H84: =IF(F84="LR",E84,0) -> 0 | I84: =IF(F84="NR",D84,0) -> 0 | J84: =IF(F84="NR",E84,0) -> 0
A85: 63008 | B85: =VLOOKUP(A85,DAF_AKUN,2,FALSE) -> Biaya Brosur, dan Pamflet | C85: =VLOOKUP(A85,DAF_AKUN,3,FALSE) -> D | D85: =IF(C85="D",SUMIF(Akun!A:A,A85,Akun!F:F)+SUMIF(Jurnal!K:K,A85,Jurnal!N:N)-SUMIF(Jurnal!K:K,A85,Jurnal!O:O),0) -> 0 | E85: =IF(C85="K",SUMIF(Akun!A:A,A85,Akun!G:G)-SUMIF(Jurnal!K:K,A85,Jurnal!N:N)+SUMIF(Jurnal!K:K,A85,Jurnal!O:O),0) -> 0 | F85: =IF(ERR=FALSE,0,VLOOKUP(A85,DAF_AKUN,4,FALSE)) -> LR | G85: =IF(F85="LR",D85,0) -> 0 | H85: =IF(F85="LR",E85,0) -> 0 | I85: =IF(F85="NR",D85,0) -> 0 | J85: =IF(F85="NR",E85,0) -> 0
A86: 63009 | B86: =VLOOKUP(A86,DAF_AKUN,2,FALSE) -> Pajak Kendaraan & Retribusi | C86: =VLOOKUP(A86,DAF_AKUN,3,FALSE) -> D | D86: =IF(C86="D",SUMIF(Akun!A:A,A86,Akun!F:F)+SUMIF(Jurnal!K:K,A86,Jurnal!N:N)-SUMIF(Jurnal!K:K,A86,Jurnal!O:O),0) -> 0 | E86: =IF(C86="K",SUMIF(Akun!A:A,A86,Akun!G:G)-SUMIF(Jurnal!K:K,A86,Jurnal!N:N)+SUMIF(Jurnal!K:K,A86,Jurnal!O:O),0) -> 0 | F86: =IF(ERR=FALSE,0,VLOOKUP(A86,DAF_AKUN,4,FALSE)) -> LR | G86: =IF(F86="LR",D86,0) -> 0 | H86: =IF(F86="LR",E86,0) -> 0 | I86: =IF(F86="NR",D86,0) -> 0 | J86: =IF(F86="NR",E86,0) -> 0
A87: 63010 | B87: =VLOOKUP(A87,DAF_AKUN,2,FALSE) -> Paket/Kurir | C87: =VLOOKUP(A87,DAF_AKUN,3,FALSE) -> D | D87: =IF(C87="D",SUMIF(Akun!A:A,A87,Akun!F:F)+SUMIF(Jurnal!K:K,A87,Jurnal!N:N)-SUMIF(Jurnal!K:K,A87,Jurnal!O:O),0) -> 0 | E87: =IF(C87="K",SUMIF(Akun!A:A,A87,Akun!G:G)-SUMIF(Jurnal!K:K,A87,Jurnal!N:N)+SUMIF(Jurnal!K:K,A87,Jurnal!O:O),0) -> 0 | F87: =IF(ERR=FALSE,0,VLOOKUP(A87,DAF_AKUN,4,FALSE)) -> LR | G87: =IF(F87="LR",D87,0) -> 0 | H87: =IF(F87="LR",E87,0) -> 0 | I87: =IF(F87="NR",D87,0) -> 0 | J87: =IF(F87="NR",E87,0) -> 0
A88: 63011 | B88: =VLOOKUP(A88,DAF_AKUN,2,FALSE) -> Materai & Benda Pos | C88: =VLOOKUP(A88,DAF_AKUN,3,FALSE) -> D | D88: =IF(C88="D",SUMIF(Akun!A:A,A88,Akun!F:F)+SUMIF(Jurnal!K:K,A88,Jurnal!N:N)-SUMIF(Jurnal!K:K,A88,Jurnal!O:O),0) -> 0 | E88: =IF(C88="K",SUMIF(Akun!A:A,A88,Akun!G:G)-SUMIF(Jurnal!K:K,A88,Jurnal!N:N)+SUMIF(Jurnal!K:K,A88,Jurnal!O:O),0) -> 0 | F88: =IF(ERR=FALSE,0,VLOOKUP(A88,DAF_AKUN,4,FALSE)) -> LR | G88: =IF(F88="LR",D88,0) -> 0 | H88: =IF(F88="LR",E88,0) -> 0 | I88: =IF(F88="NR",D88,0) -> 0 | J88: =IF(F88="NR",E88,0) -> 0
A89: 63012 | B89: =VLOOKUP(A89,DAF_AKUN,2,FALSE) -> Biaya Sparepart Investaris | C89: =VLOOKUP(A89,DAF_AKUN,3,FALSE) -> D | D89: =IF(C89="D",SUMIF(Akun!A:A,A89,Akun!F:F)+SUMIF(Jurnal!K:K,A89,Jurnal!N:N)-SUMIF(Jurnal!K:K,A89,Jurnal!O:O),0) -> 0 | E89: =IF(C89="K",SUMIF(Akun!A:A,A89,Akun!G:G)-SUMIF(Jurnal!K:K,A89,Jurnal!N:N)+SUMIF(Jurnal!K:K,A89,Jurnal!O:O),0) -> 0 | F89: =IF(ERR=FALSE,0,VLOOKUP(A89,DAF_AKUN,4,FALSE)) -> LR | G89: =IF(F89="LR",D89,0) -> 0 | H89: =IF(F89="LR",E89,0) -> 0 | I89: =IF(F89="NR",D89,0) -> 0 | J89: =IF(F89="NR",E89,0) -> 0
... A92: 63015 | B92: =VLOOKUP(A92,DAF_AKUN,2,FALSE) -> Biaya Rumah Tangga Perusahaan | C92: =VLOOKUP(A92,DAF_AKUN,3,FALSE) -> D | D92: =IF(C92="D",SUMIF(Akun!A:A,A92,Akun!F:F)+SUMIF(Jurnal!K:K,A92,Jurnal!N:N)-SUMIF(Jurnal!K:K,A92,Jurnal!O:O),0) -> 0 | E92: =IF(C92="K",SUMIF(Akun!A:A,A92,Akun!G:G)-SUMIF(Jurnal!K:K,A92,Jurnal!N:N)+SUMIF(Jurnal!K:K,A92,Jurnal!O:O),0) -> 0 | F92: =IF(ERR=FALSE,0,VLOOKUP(A92,DAF_AKUN,4,FALSE)) -> LR | G92: =IF(F92="LR",D92,0) -> 0 | H92: =IF(F92="LR",E92,0) -> 0 | I92: =IF(F92="NR",D92,0) -> 0 | J92: =IF(F92="NR",E92,0) -> 0
A93: 64000 | B93: =VLOOKUP(A93,DAF_AKUN,2,FALSE) -> BIAYA KEUANGAN :
A94: 64001 | B94: =VLOOKUP(A94,DAF_AKUN,2,FALSE) -> Biaya Bunga Bank | C94: =VLOOKUP(A94,DAF_AKUN,3,FALSE) -> D | D94: =IF(C94="D",SUMIF(Akun!A:A,A94,Akun!F:F)+SUMIF(Jurnal!K:K,A94,Jurnal!N:N)-SUMIF(Jurnal!K:K,A94,Jurnal!O:O),0) -> 0 | E94: =IF(C94="K",SUMIF(Akun!A:A,A94,Akun!G:G)-SUMIF(Jurnal!K:K,A94,Jurnal!N:N)+SUMIF(Jurnal!K:K,A94,Jurnal!O:O),0) -> 0 | F94: =IF(ERR=FALSE,0,VLOOKUP(A94,DAF_AKUN,4,FALSE)) -> LR | G94: =IF(F94="LR",D94,0) -> 0 | H94: =IF(F94="LR",E94,0) -> 0 | I94: =IF(F94="NR",D94,0) -> 0 | J94: =IF(F94="NR",E94,0) -> 0
A95: 64002 | B95: =VLOOKUP(A95,DAF_AKUN,2,FALSE) -> Biaya Administrasi Bank | C95: =VLOOKUP(A95,DAF_AKUN,3,FALSE) -> D | D95: =IF(C95="D",SUMIF(Akun!A:A,A95,Akun!F:F)+SUMIF(Jurnal!K:K,A95,Jurnal!N:N)-SUMIF(Jurnal!K:K,A95,Jurnal!O:O),0) -> 5000 | E95: =IF(C95="K",SUMIF(Akun!A:A,A95,Akun!G:G)-SUMIF(Jurnal!K:K,A95,Jurnal!N:N)+SUMIF(Jurnal!K:K,A95,Jurnal!O:O),0) -> 0 | F95: =IF(ERR=FALSE,0,VLOOKUP(A95,DAF_AKUN,4,FALSE)) -> LR | G95: =IF(F95="LR",D95,0) -> 5000 | H95: =IF(F95="LR",E95,0) -> 0 | I95: =IF(F95="NR",D95,0) -> 0 | J95: =IF(F95="NR",E95,0) -> 0
A96: 70000 | B96: =VLOOKUP(A96,DAF_AKUN,2,FALSE) -> PENDAPATAN & BIAYA LAIN-LAIN
A97: 71000 | B97: =VLOOKUP(A97,DAF_AKUN,2,FALSE) -> Penghasilan klain asuransi | C97: =VLOOKUP(A97,DAF_AKUN,3,FALSE) -> K | D97: =IF(C97="D",SUMIF(Akun!A:A,A97,Akun!F:F)+SUMIF(Jurnal!K:K,A97,Jurnal!N:N)-SUMIF(Jurnal!K:K,A97,Jurnal!O:O),0) -> 0 | E97: =IF(C97="K",SUMIF(Akun!A:A,A97,Akun!G:G)-SUMIF(Jurnal!K:K,A97,Jurnal!N:N)+SUMIF(Jurnal!K:K,A97,Jurnal!O:O),0) -> 0 | F97: =IF(ERR=FALSE,0,VLOOKUP(A97,DAF_AKUN,4,FALSE)) -> LR | G97: =IF(F97="LR",D97,0) -> 0 | H97: =IF(F97="LR",E97,0) -> 0 | I97: =IF(F97="NR",D97,0) -> 0 | J97: =IF(F97="NR",E97,0) -> 0
A98: 72000 | B98: =VLOOKUP(A98,DAF_AKUN,2,FALSE) -> Bunga Bank/ Jasa Giro | C98: =VLOOKUP(A98,DAF_AKUN,3,FALSE) -> K | D98: =IF(C98="D",SUMIF(Akun!A:A,A98,Akun!F:F)+SUMIF(Jurnal!K:K,A98,Jurnal!N:N)-SUMIF(Jurnal!K:K,A98,Jurnal!O:O),0) -> 0 | E98: =IF(C98="K",SUMIF(Akun!A:A,A98,Akun!G:G)-SUMIF(Jurnal!K:K,A98,Jurnal!N:N)+SUMIF(Jurnal!K:K,A98,Jurnal!O:O),0) -> 0 | F98: =IF(ERR=FALSE,0,VLOOKUP(A98,DAF_AKUN,4,FALSE)) -> LR | G98: =IF(F98="LR",D98,0) -> 0 | H98: =IF(F98="LR",E98,0) -> 0 | I98: =IF(F98="NR",D98,0) -> 0 | J98: =IF(F98="NR",E98,0) -> 0
A99: 73000 | B99: =VLOOKUP(A99,DAF_AKUN,2,FALSE) -> Selisih Kurs | C99: =VLOOKUP(A99,DAF_AKUN,3,FALSE) -> K | D99: =IF(C99="D",SUMIF(Akun!A:A,A99,Akun!F:F)+SUMIF(Jurnal!K:K,A99,Jurnal!N:N)-SUMIF(Jurnal!K:K,A99,Jurnal!O:O),0) -> 0 | E99: =IF(C99="K",SUMIF(Akun!A:A,A99,Akun!G:G)-SUMIF(Jurnal!K:K,A99,Jurnal!N:N)+SUMIF(Jurnal!K:K,A99,Jurnal!O:O),0) -> 0 | F99: =IF(ERR=FALSE,0,VLOOKUP(A99,DAF_AKUN,4,FALSE)) -> LR | G99: =IF(F99="LR",D99,0) -> 0 | H99: =IF(F99="LR",E99,0) -> 0 | I99: =IF(F99="NR",D99,0) -> 0 | J99: =IF(F99="NR",E99,0) -> 0
A100: 74000 | B100: =VLOOKUP(A100,DAF_AKUN,2,FALSE) -> Biaya Lain-lain diluar usaha | C100: =VLOOKUP(A100,DAF_AKUN,3,FALSE) -> K | D100: =IF(C100="D",SUMIF(Akun!A:A,A100,Akun!F:F)+SUMIF(Jurnal!K:K,A100,Jurnal!N:N)-SUMIF(Jurnal!K:K,A100,Jurnal!O:O),0) -> 0 | E100: =IF(C100="K",SUMIF(Akun!A:A,A100,Akun!G:G)-SUMIF(Jurnal!K:K,A100,Jurnal!N:N)+SUMIF(Jurnal!K:K,A100,Jurnal!O:O),0) -> 0 | F100: =IF(ERR=FALSE,0,VLOOKUP(A100,DAF_AKUN,4,FALSE)) -> LR | G100: =IF(F100="LR",D100,0) -> 0 | H100: =IF(F100="LR",E100,0) -> 0 | I100: =IF(F100="NR",D100,0) -> 0 | J100: =IF(F100="NR",E100,0) -> 0
B102: Jumlah | D102: =SUM(D10:D101) -> 2.2276079e+10 | E102: =SUM(E10:E101) -> 2.2276079e+10 | G102: =SUM(G10:G101) -> 666335792 | H102: =SUM(H10:H101) -> 1.1471962e+09 | I102: =SUM(I10:I101) -> 2.1609743e+10 | J102: =SUM(J10:J101) -> 2.1128883e+10
B103: Laba (Rugi) Bersih | H103: =H102-G102 -> 4.808604e+08 | J103: =H103 -> 4.808604e+08
B104: Jumlah | I104: =SUM(I102:I103) -> 2.1609743e+10 | J104: =SUM(J102:J103) -> 2.1609743e+10
E105: =+D102-E102 -> 0 | J105: =+I104-J104 -> 0

Sheet Laba Rugi
A1: ='Data GL'!E6 -> CV. SPEKTRA DIGITAL ARTWORK
A2: ='Data GL'!E4 -> PERCETAKAN
A3: ='Data GL'!E5 -> JL. Prof Dr. Yohannes 1099 YK
A5: LAPORAN LABA RUGI
A6: =CONCATENATE('Data GL'!E7," -"," TAHUN"," ",'Data GL'!E8) -> Jan - TAHUN 2026
A8: Kode Akun | B8: Nama Akun | C8: Jumlah (Rp)
A10: 40000 | B10: =VLOOKUP(A10,DAF_AKUN,2,FALSE) -> PENDAPATAN
A11: 41000 | B11: =VLOOKUP(A11,DAF_AKUN,2,FALSE) -> Penjualan Barang | C11: =SUMIF('Neraca Lajur'!A:A,A11,'Neraca Lajur'!G:G)+SUMIF('Neraca Lajur'!A:A,A11,'Neraca Lajur'!H:H) -> 1.1471778e+09 | F11: 17335817214
A12: 41001 | B12: =VLOOKUP(A12,DAF_AKUN,2,FALSE) -> Retur Penjualan Barang | C12: =SUMIF('Neraca Lajur'!A:A,A12,'Neraca Lajur'!G:G)+SUMIF('Neraca Lajur'!A:A,A12,'Neraca Lajur'!H:H) -> 0
A13: 41002 | B13: =VLOOKUP(A13,DAF_AKUN,2,FALSE) -> Pendapatan Lain-lain | C13: =SUMIF('Neraca Lajur'!A:A,A13,'Neraca Lajur'!G:G)+SUMIF('Neraca Lajur'!A:A,A13,'Neraca Lajur'!H:H) -> 18400 | G13: =C11 -> 1.1471778e+09
D14: =SUM(C10:C13) -> 1.1471962e+09 | F14: PS AWAL | G14: 12574772584
G15: =C18 -> 581342640
A16: 50000 | B16: HARGA POKOK PENJUALAN | F16: PERSENAN | G16: =C21 -> 0 | H16: =G14+G15+G16+C19 -> 13156115224
A17: 51000 | B17: =IF(ERR=TRUE,VLOOKUP(A17,DAF_AKUN,2,FALSE),0) -> Persediaan Bahan Baku Awal | C17: =SUMIF('Neraca Lajur'!A:A,A17,'Neraca Lajur'!G:G)+SUMIF('Neraca Lajur'!A:A,A17,'Neraca Lajur'!H:H) -> 0 | H17: =G13-H16 -> -1.2008937e+10 | I17: =D60 -> 71331265 | J17: =H17-I17 -> -1.2080269e+10
A18: 53000 | B18: =IF(ERR=TRUE,VLOOKUP(A18,DAF_AKUN,2,FALSE),0) -> Pembelian Bahan Baku | C18: =SUMIF('Neraca Lajur'!A:A,A18,'Neraca Lajur'!G:G)+SUMIF('Neraca Lajur'!A:A,A18,'Neraca Lajur'!H:H) -> 581342640 | F18: 12337377931 | G18: 17335817214
A19: 53001 | B19: =IF(ERR=TRUE,VLOOKUP(A19,DAF_AKUN,2,FALSE),0) -> Persediaan Bahan Penolong Awal | C19: =SUMIF('Neraca Lajur'!A:A,A19,'Neraca Lajur'!G:G)+SUMIF('Neraca Lajur'!A:A,A19,'Neraca Lajur'!H:H) -> 0 | F19: 12574772584 | G19: 10128579539 | J19: =J17+D74 -> -1.1558018e+10
A20: 53002 | B20: =IF(ERR=TRUE,VLOOKUP(A20,DAF_AKUN,2,FALSE),0) -> Persediaan Bahan Penolong Akhir | C20: =SUMIF('Neraca Lajur'!A:A,A20,'Neraca Lajur'!G:G)+SUMIF('Neraca Lajur'!A:A,A20,'Neraca Lajur'!H:H) -> 0 | F20: 14782160976
A21: 52000 | B21: =IF(ERR=TRUE,VLOOKUP(A21,DAF_AKUN,2,FALSE),0) -> Persediaan Bahan Baku Akhir | C21: =SUMIF('Neraca Lajur'!A:A,A21,'Neraca Lajur'!G:G)+SUMIF('Neraca Lajur'!A:A,A21,'Neraca Lajur'!H:H) -> 0 | F21: 1410000
D22: =SUM(C17:C21) -> 581342640 | F22: =+C18+C19 -> 581342640
B23: LABA KOTOR | D23: =D14-D22 -> 5.6585355e+08 | E23: =+D23/D14 -> 0.49324915 | F23: 12335967931
A25: 60000 | B25: =IF(ERR=TRUE,VLOOKUP(A25,DAF_AKUN,2,FALSE),0) -> BIAYA OPERASIONAL
A26: 61000 | B26: =VLOOKUP(A26,DAF_AKUN,2,FALSE) -> BIAYA MANAJEMEN :
A27: 61001 | B27: =VLOOKUP(A27,DAF_AKUN,2,FALSE) -> Gaji & Tunjangan | C27: =SUMIF('Neraca Lajur'!A:A,A27,'Neraca Lajur'!G:G)+SUMIF('Neraca Lajur'!A:A,A27,'Neraca Lajur'!H:H) -> 0 | F27: 3673349143
A28: 61002 | B28: =VLOOKUP(A28,DAF_AKUN,2,FALSE) -> Asuransi Tenaga Kerja | C28: =SUMIF('Neraca Lajur'!A:A,A28,'Neraca Lajur'!G:G)+SUMIF('Neraca Lajur'!A:A,A28,'Neraca Lajur'!H:H) -> 10128075
A29: 61003 | B29: =VLOOKUP(A29,DAF_AKUN,2,FALSE) -> Perjalanan Dinas | C29: =SUMIF('Neraca Lajur'!A:A,A29,'Neraca Lajur'!G:G)+SUMIF('Neraca Lajur'!A:A,A29,'Neraca Lajur'!H:H) -> 0
A30: 61004 | B30: =VLOOKUP(A30,DAF_AKUN,2,FALSE) -> Biaya Konsultan Pajak | C30: =SUMIF('Neraca Lajur'!A:A,A30,'Neraca Lajur'!G:G)+SUMIF('Neraca Lajur'!A:A,A30,'Neraca Lajur'!H:H) -> 2000000
A31: 61005 | B31: =VLOOKUP(A31,DAF_AKUN,2,FALSE) -> #N/A | C31: =SUMIF('Neraca Lajur'!A:A,A31,'Neraca Lajur'!G:G)+SUMIF('Neraca Lajur'!A:A,A31,'Neraca Lajur'!H:H) -> 0
A32: 61006 | B32: =VLOOKUP(A32,DAF_AKUN,2,FALSE) -> #N/A | C32: =SUMIF('Neraca Lajur'!A:A,A32,'Neraca Lajur'!G:G)+SUMIF('Neraca Lajur'!A:A,A32,'Neraca Lajur'!H:H) -> 0
D33: =SUM(C27:C30) -> 12128075
A34: 62000 | B34: =VLOOKUP(A34,DAF_AKUN,2,FALSE) -> BIAYA PENJUALAN :
A35: 62001 | B35: =VLOOKUP(A35,DAF_AKUN,2,FALSE) -> Ongkos Kirim | C35: =SUMIF('Neraca Lajur'!A:A,A35,'Neraca Lajur'!G:G)+SUMIF('Neraca Lajur'!A:A,A35,'Neraca Lajur'!H:H) -> 0 | F35: 145387050
A36: 62002 | B36: =VLOOKUP(A36,DAF_AKUN,2,FALSE) -> BBM dan Parkir | C36: =SUMIF('Neraca Lajur'!A:A,A36,'Neraca Lajur'!G:G)+SUMIF('Neraca Lajur'!A:A,A36,'Neraca Lajur'!H:H) -> 0 | F36: 942155228
A37: 62003 | B37: =VLOOKUP(A37,DAF_AKUN,2,FALSE) -> Pamflet & Brosur | C37: =SUMIF('Neraca Lajur'!A:A,A37,'Neraca Lajur'!G:G)+SUMIF('Neraca Lajur'!A:A,A37,'Neraca Lajur'!H:H) -> 0 | F37: =+C36+C40+C43+C45+C46+C49+C52+#REF!+#REF!+#REF!+C57+C58 -> #REF!
A38: 63000 | B38: =VLOOKUP(A38,DAF_AKUN,2,FALSE) -> BIAYA UMUM & ADMINISTRASI : | C38: =SUMIF('Neraca Lajur'!A:A,A38,'Neraca Lajur'!G:G)+SUMIF('Neraca Lajur'!A:A,A38,'Neraca Lajur'!H:H) -> 0 | F38: 2019409879
A39: 63001 | B39: =VLOOKUP(A39,DAF_AKUN,2,FALSE) -> Penyusutan | C39: =SUMIF('Neraca Lajur'!A:A,A39,'Neraca Lajur'!G:G)+SUMIF('Neraca Lajur'!A:A,A39,'Neraca Lajur'!H:H) -> 0 | F39: =+C39-C73 -> -424622159
A40: 63002 | B40: =VLOOKUP(A40,DAF_AKUN,2,FALSE) -> Telepon | C40: =SUMIF('Neraca Lajur'!A:A,A40,'Neraca Lajur'!G:G)+SUMIF('Neraca Lajur'!A:A,A40,'Neraca Lajur'!H:H) -> 2130762 | F40: 942155228
A41: 63003 | B41: =VLOOKUP(A41,DAF_AKUN,2,FALSE) -> Internet | C41: =SUMIF('Neraca Lajur'!A:A,A41,'Neraca Lajur'!G:G)+SUMIF('Neraca Lajur'!A:A,A41,'Neraca Lajur'!H:H) -> 0
A42: 63004 | B42: =VLOOKUP(A42,DAF_AKUN,2,FALSE) -> Listrik & Air | C42: =SUMIF('Neraca Lajur'!A:A,A42,'Neraca Lajur'!G:G)+SUMIF('Neraca Lajur'!A:A,A42,'Neraca Lajur'!H:H) -> 38500099
A43: 63005 | B43: =VLOOKUP(A43,DAF_AKUN,2,FALSE) -> Rapat/Pelatihan Karyawan | C43: =SUMIF('Neraca Lajur'!A:A,A43,'Neraca Lajur'!G:G)+SUMIF('Neraca Lajur'!A:A,A43,'Neraca Lajur'!H:H) -> 0
A44: 63006 | B44: =VLOOKUP(A44,DAF_AKUN,2,FALSE) -> Perlengkapan Kantor | C44: =SUMIF('Neraca Lajur'!A:A,A44,'Neraca Lajur'!G:G)+SUMIF('Neraca Lajur'!A:A,A44,'Neraca Lajur'!H:H) -> 0
A45: 63007 | B45: =VLOOKUP(A45,DAF_AKUN,2,FALSE) -> Administrasi Kantor (ATK) | C45: =SUMIF('Neraca Lajur'!A:A,A45,'Neraca Lajur'!G:G)+SUMIF('Neraca Lajur'!A:A,A45,'Neraca Lajur'!H:H) -> 0
A46: 63008 | B46: =VLOOKUP(A46,DAF_AKUN,2,FALSE) -> Biaya Brosur, dan Pamflet | C46: =SUMIF('Neraca Lajur'!A:A,A46,'Neraca Lajur'!G:G)+SUMIF('Neraca Lajur'!A:A,A46,'Neraca Lajur'!H:H) -> 0
A47: 63009 | B47: =VLOOKUP(A47,DAF_AKUN,2,FALSE) -> Pajak Kendaraan & Retribusi | C47: =SUMIF('Neraca Lajur'!A:A,A47,'Neraca Lajur'!G:G)+SUMIF('Neraca Lajur'!A:A,A47,'Neraca Lajur'!H:H) -> 0 | G47: =+C18+C52+#REF! -> #REF!
A48: 63010 | B48: =VLOOKUP(A48,DAF_AKUN,2,FALSE) -> Paket/Kurir | C48: =SUMIF('Neraca Lajur'!A:A,A48,'Neraca Lajur'!G:G)+SUMIF('Neraca Lajur'!A:A,A48,'Neraca Lajur'!H:H) -> 0
A49: 63011 | B49: =VLOOKUP(A49,DAF_AKUN,2,FALSE) -> Materai & Benda Pos | C49: =SUMIF('Neraca Lajur'!A:A,A49,'Neraca Lajur'!G:G)+SUMIF('Neraca Lajur'!A:A,A49,'Neraca Lajur'!H:H) -> 0
A50: 63012 | B50: =VLOOKUP(A50,DAF_AKUN,2,FALSE) -> Biaya Sparepart Investaris | C50: =SUMIF('Neraca Lajur'!A:A,A50,'Neraca Lajur'!G:G)+SUMIF('Neraca Lajur'!A:A,A50,'Neraca Lajur'!H:H) -> 0
A51: 63013 | B51: =VLOOKUP(A51,DAF_AKUN,2,FALSE) -> Sanksi Pajak | C51: =SUMIF('Neraca Lajur'!A:A,A51,'Neraca Lajur'!G:G)+SUMIF('Neraca Lajur'!A:A,A51,'Neraca Lajur'!H:H) -> 0
A52: 63014 | B52: =VLOOKUP(A52,DAF_AKUN,2,FALSE) -> Biaya Lain-lain, Sumbangan | C52: =SUMIF('Neraca Lajur'!A:A,A52,'Neraca Lajur'!G:G)+SUMIF('Neraca Lajur'!A:A,A52,'Neraca Lajur'!H:H) -> 18567329
A53: 63015 | B53: =VLOOKUP(A53,DAF_AKUN,2,FALSE) -> Biaya Rumah Tangga Perusahaan | C53: =SUMIF('Neraca Lajur'!A:A,A53,'Neraca Lajur'!G:G)+SUMIF('Neraca Lajur'!A:A,A53,'Neraca Lajur'!H:H) -> 0
D54: =SUM(C35:C53) -> 59198190
A55: 64000 | B55: =VLOOKUP(A55,DAF_AKUN,2,FALSE) -> BIAYA KEUANGAN :
A56: 64001 | B56: =VLOOKUP(A56,DAF_AKUN,2,FALSE) -> Biaya Bunga Bank | C56: =SUMIF('Neraca Lajur'!A:A,A56,'Neraca Lajur'!G:G)+SUMIF('Neraca Lajur'!A:A,A56,'Neraca Lajur'!H:H) -> 0
A57: 64002 | B57: =VLOOKUP(A57,DAF_AKUN,2,FALSE) -> Biaya Administrasi Bank | C57: =SUMIF('Neraca Lajur'!A:A,A57,'Neraca Lajur'!G:G)+SUMIF('Neraca Lajur'!A:A,A57,'Neraca Lajur'!H:H) -> 5000
A58: 64003 | B58: =VLOOKUP(A58,DAF_AKUN,2,FALSE) -> #N/A | C58: =SUMIF('Neraca Lajur'!A:A,A58,'Neraca Lajur'!G:G)+SUMIF('Neraca Lajur'!A:A,A58,'Neraca Lajur'!H:H) -> 0
D59: =SUM(C56:C58) -> 5000
B60: JUMLAH BIAYA OPERASIONAL | D60: =D33+D54+D59 -> 71331265 | F60: 6780301300
B61: LABA BERSIH USAHA | D61: =D23-D60 -> 4.9452228e+08
A62: 70000 | B62: =VLOOKUP(A62,DAF_AKUN,2,FALSE) -> PENDAPATAN & BIAYA LAIN-LAIN
A63: 71000 | B63: =VLOOKUP(A63,DAF_AKUN,2,FALSE) -> Penghasilan klain asuransi | C63: =SUMIF('Neraca Lajur'!A:A,A63,'Neraca Lajur'!G:G)+SUMIF('Neraca Lajur'!A:A,A63,'Neraca Lajur'!H:H) -> 0
A64: 72000 | B64: =VLOOKUP(A64,DAF_AKUN,2,FALSE) -> Bunga Bank/ Jasa Giro | C64: =SUMIF('Neraca Lajur'!A:A,A64,'Neraca Lajur'!G:G)+SUMIF('Neraca Lajur'!A:A,A64,'Neraca Lajur'!H:H) -> 0
A65: 73000 | B65: =VLOOKUP(A65,DAF_AKUN,2,FALSE) -> Selisih Kurs | C65: =SUMIF('Neraca Lajur'!A:A,A65,'Neraca Lajur'!G:G)+SUMIF('Neraca Lajur'!A:A,A65,'Neraca Lajur'!H:H) -> 0
A66: 74000 | B66: =VLOOKUP(A66,DAF_AKUN,2,FALSE) -> Biaya Lain-lain diluar usaha | C66: =SUMIF('Neraca Lajur'!A:A,A66,'Neraca Lajur'!G:G)+SUMIF('Neraca Lajur'!A:A,A66,'Neraca Lajur'!H:H) -> 0
D67: =SUM(C63:C66) -> 0
B69: JUMLAH LABA BERSIH | D69: =D61+D67 -> 4.9452228e+08
B70: Koreksi Fiskal Positif | F70: 144106587
B71: Biaya Asuransi | C71: =C28 -> 10128075
B72: PPh Pasal 21 | C72: 87500000
B73: Penyusutan | C73: 424622159
D74: =SUM(C71:C73) -> 522250234 | F74: 656228746
B75: Koreksi Fiskal Negatif | D75: =D69+D74 -> 1.0167725e+09
B76: =B63 -> Penghasilan klain asuransi | C76: =C63 -> 0
D77: =C76 -> 0 | F77: 2312975
B78: LABA BERSIH SETELAH PAJAK | D78: =D75-D77 -> 1.0167725e+09 | F78: 1083165121
C80: Yogyakarta, 31 Desember 2026
C86: HERMAWAN ALWAN
C87: DIEKTUR

Sheet Lap Modal
A1: ='Data GL'!E6 -> CV. SPEKTRA DIGITAL ARTWORK
A2: ='Data GL'!E4 -> PERCETAKAN
A3: ='Data GL'!E5 -> JL. Prof Dr. Yohannes 1099 YK
A5: LAPORAN PERUBAHAN MODAL
A6: =CONCATENATE('Data GL'!E7," -"," TAHUN"," ",'Data GL'!E8) -> Jan - TAHUN 2026
A8: No | B8: Pos-Pos | C8: Jumlah
A9: Akun
C10: =SUMIF('Neraca Lajur'!A:A,A14,'Neraca Lajur'!D:D)+SUMIF('Neraca Lajur'!A:A,A14,'Neraca Lajur'!E:E)*-1 -> -1500000000
A11: 31000 | B11: Modal Awal | D11: =SUMIF('Neraca Lajur'!A:A,A11,'Neraca Lajur'!I:I)+SUMIF('Neraca Lajur'!A:A,A11,'Neraca Lajur'!J:J) -> 11488144544
B12: Laba Tahun Berjalan | C12: =SUMIF('Neraca Lajur'!A:A,A15,'Neraca Lajur'!D:D)+SUMIF('Neraca Lajur'!A:A,A15,'Neraca Lajur'!E:E) -> 0
A13: 35000 | B13: =VLOOKUP(A13,DAF_AKUN,2,FALSE) -> #N/A | C13: ='Neraca Lajur'!#REF! -> #REF!
A14: 32000 | B14: =VLOOKUP(A14,DAF_AKUN,2,FALSE) -> Laba Ditahan Amnesty | C14: =C10*-1 -> 1500000000 | G14: 207347580 | I14: 205310556
A15: 33000 | B15: =VLOOKUP(A15,DAF_AKUN,2,FALSE) -> Prive | C15: 0
B16: Kenaikan/(Penurunan) | D16: =SUM(C12:C15) -> #REF! | G16: 223938794
B17: Modal Akhir | D17: =SUM(D11:D16) -> #REF!
C20: Yogyakarta, 31 Desember 2026
C26: HERMAWAN ALWAN
C27: DIEKTUR

Sheet Neraca
A1: ='Data GL'!E6 -> CV. SPEKTRA DIGITAL ARTWORK
A2: ='Data GL'!E4 -> PERCETAKAN
A3: ='Data GL'!E5 -> JL. Prof Dr. Yohannes 1099 YK
A5: NERACA
A6: =CONCATENATE('Data GL'!E7," -"," TAHUN"," ",'Data GL'!E8) -> Jan - TAHUN 2026
A8: Kode Akun | B8: Nama Akun | C8: Jumlah (Rp)
A9: 10000 | B9: =VLOOKUP(A9,DAF_AKUN,2,FALSE) -> AKTIVA
A10: 11000 | B10: =VLOOKUP(A10,DAF_AKUN,2,FALSE) -> AKTIVA LANCAR
A11: 11100 | B11: =VLOOKUP(A11,DAF_AKUN,2,FALSE) -> Kas | C11: =SUMIF('Neraca Lajur'!A:A,A11,'Neraca Lajur'!I:I)+SUMIF('Neraca Lajur'!A:A,A11,'Neraca Lajur'!J:J) -> 1434652025 | F11: =+C11+C12+C13 -> 2.7049348e+09
A12: 11101 | B12: =VLOOKUP(A12,DAF_AKUN,2,FALSE) -> Bank | C12: =SUMIF('Neraca Lajur'!A:A,A12,'Neraca Lajur'!I:I)+SUMIF('Neraca Lajur'!A:A,A12,'Neraca Lajur'!J:J) -> 0 | F12: 1228969600
A13: 11102 | B13: =VLOOKUP(A13,DAF_AKUN,2,FALSE) -> Piutang Dagang | C13: =SUMIF('Neraca Lajur'!A:A,A13,'Neraca Lajur'!I:I)+SUMIF('Neraca Lajur'!A:A,A13,'Neraca Lajur'!J:J) -> 1.2702828e+09
A14: 11103 | B14: =VLOOKUP(A14,DAF_AKUN,2,FALSE) -> Piutang Karyawan | C14: =SUMIF('Neraca Lajur'!A:A,A14,'Neraca Lajur'!I:I)+SUMIF('Neraca Lajur'!A:A,A14,'Neraca Lajur'!J:J) -> 0 | F14: 78554589
A15: 11200 | B15: =VLOOKUP(A15,DAF_AKUN,2,FALSE) -> Persediaan Barang Jadi | C15: =SUMIF('Neraca Lajur'!A:A,A15,'Neraca Lajur'!I:I)+SUMIF('Neraca Lajur'!A:A,A15,'Neraca Lajur'!J:J) -> 1553000000
A16: 11300 | B16: =VLOOKUP(A16,DAF_AKUN,2,FALSE) -> Persediaan Barang Proses | C16: =SUMIF('Neraca Lajur'!A:A,A16,'Neraca Lajur'!I:I)+SUMIF('Neraca Lajur'!A:A,A16,'Neraca Lajur'!J:J) -> 0
A17: 11301 | B17: =VLOOKUP(A17,DAF_AKUN,2,FALSE) -> Persediaan Bahan Baku | C17: =SUMIF('Neraca Lajur'!A:A,A17,'Neraca Lajur'!I:I)+SUMIF('Neraca Lajur'!A:A,A17,'Neraca Lajur'!J:J) -> 10187858027
A18: 11400 | B18: =VLOOKUP(A18,DAF_AKUN,2,FALSE) -> Persediaan Bahan Penolong | C18: =SUMIF('Neraca Lajur'!A:A,A18,'Neraca Lajur'!I:I)+SUMIF('Neraca Lajur'!A:A,A18,'Neraca Lajur'!J:J) -> 0 | F18: =+C23+C28 -> 0
A19: 11401 | B19: =VLOOKUP(A19,DAF_AKUN,2,FALSE) -> Persediaan Lain-lain | C19: =SUMIF('Neraca Lajur'!A:A,A19,'Neraca Lajur'!I:I)+SUMIF('Neraca Lajur'!A:A,A19,'Neraca Lajur'!J:J) -> 5860000 | F19: 37918883
A20: 11402 | B20: =VLOOKUP(A20,DAF_AKUN,2,FALSE) -> Ppn Dibayar dimuka | C20: =SUMIF('Neraca Lajur'!A:A,A20,'Neraca Lajur'!I:I)+SUMIF('Neraca Lajur'!A:A,A20,'Neraca Lajur'!J:J) -> 0
A21: 11403 | B21: =VLOOKUP(A21,DAF_AKUN,2,FALSE) -> Pph Pasal 23 | C21: =SUMIF('Neraca Lajur'!A:A,A21,'Neraca Lajur'!I:I)+SUMIF('Neraca Lajur'!A:A,A21,'Neraca Lajur'!J:J) -> 14360087
A22: 11404 | B22: =VLOOKUP(A22,DAF_AKUN,2,FALSE) -> #N/A | C22: =SUMIF('Neraca Lajur'!A:A,A22,'Neraca Lajur'!I:I)+SUMIF('Neraca Lajur'!A:A,A22,'Neraca Lajur'!J:J) -> 0
A23: 11405 | B23: =VLOOKUP(A23,DAF_AKUN,2,FALSE) -> #N/A | C23: =SUMIF('Neraca Lajur'!A:A,A23,'Neraca Lajur'!I:I)+SUMIF('Neraca Lajur'!A:A,A23,'Neraca Lajur'!J:J) -> 0
A24: 11500 | B24: =VLOOKUP(A24,DAF_AKUN,2,FALSE) -> Pph Pasal 25 | C24: =SUMIF('Neraca Lajur'!A:A,A24,'Neraca Lajur'!I:I)+SUMIF('Neraca Lajur'!A:A,A24,'Neraca Lajur'!J:J) -> 12140000 | F24: 14782160976
A25: 11600 | B25: =VLOOKUP(A25,DAF_AKUN,2,FALSE) -> PPN Masukan | C25: =SUMIF('Neraca Lajur'!A:A,A25,'Neraca Lajur'!I:I)+SUMIF('Neraca Lajur'!A:A,A25,'Neraca Lajur'!J:J) -> 120617895
A26: 11700 | B26: =VLOOKUP(A26,DAF_AKUN,2,FALSE) -> Uang Muka Pembelian | C26: =SUMIF('Neraca Lajur'!A:A,A26,'Neraca Lajur'!I:I)+SUMIF('Neraca Lajur'!A:A,A26,'Neraca Lajur'!J:J) -> 0
A27: 11800 | B27: =VLOOKUP(A27,DAF_AKUN,2,FALSE) -> Uang Muka Sewa | C27: =SUMIF('Neraca Lajur'!A:A,A27,'Neraca Lajur'!I:I)+SUMIF('Neraca Lajur'!A:A,A27,'Neraca Lajur'!J:J) -> 0
A28: 11801 | B28: =VLOOKUP(A28,DAF_AKUN,2,FALSE) -> #N/A | C28: =SUMIF('Neraca Lajur'!A:A,A28,'Neraca Lajur'!I:I)+SUMIF('Neraca Lajur'!A:A,A28,'Neraca Lajur'!J:J) -> 0
B29: Jumlah Aktiva Lancar | D29: =SUM(C11:C28) -> 1.4598771e+10
A30: 12000 | B30: =VLOOKUP(A30,DAF_AKUN,2,FALSE) -> AKTIVA TETAP
A31: 12100 | B31: =VLOOKUP(A31,DAF_AKUN,2,FALSE) -> Gedung dan Listrik | C31: =SUMIF('Neraca Lajur'!A:A,A31,'Neraca Lajur'!I:I)+SUMIF('Neraca Lajur'!A:A,A31,'Neraca Lajur'!J:J) -> 48589042 | F31: =+C31+C32+C33 -> 7010972115
A32: 12200 | B32: =VLOOKUP(A32,DAF_AKUN,2,FALSE) -> Peralatan Pabrik | C32: =SUMIF('Neraca Lajur'!A:A,A32,'Neraca Lajur'!I:I)+SUMIF('Neraca Lajur'!A:A,A32,'Neraca Lajur'!J:J) -> 6747617604 | F32: =+C34+C35+C36 -> 0
A33: 12300 | B33: =VLOOKUP(A33,DAF_AKUN,2,FALSE) -> Peralatan Kantor | C33: =SUMIF('Neraca Lajur'!A:A,A33,'Neraca Lajur'!I:I)+SUMIF('Neraca Lajur'!A:A,A33,'Neraca Lajur'!J:J) -> 214765469 | F33: 15268274384
A34: 12301 | B34: =VLOOKUP(A34,DAF_AKUN,2,FALSE) -> #N/A | C34: =SUMIF('Neraca Lajur'!A:A,A34,'Neraca Lajur'!I:I)+SUMIF('Neraca Lajur'!A:A,A34,'Neraca Lajur'!J:J) -> 0 | F34: =+C34+C35+C36 -> 0
A35: 12302 | B35: =VLOOKUP(A35,DAF_AKUN,2,FALSE) -> #N/A | C35: =SUMIF('Neraca Lajur'!A:A,A35,'Neraca Lajur'!I:I)+SUMIF('Neraca Lajur'!A:A,A35,'Neraca Lajur'!J:J) -> 0 | F35: 8947512726
A36: 12303 | B36: =VLOOKUP(A36,DAF_AKUN,2,FALSE) -> #N/A | C36: =SUMIF('Neraca Lajur'!A:A,A36,'Neraca Lajur'!I:I)+SUMIF('Neraca Lajur'!A:A,A36,'Neraca Lajur'!J:J) -> 0
B37: Jumlah Aktiva Tetap | D37: =SUM(C31:C36) -> 7010972115
B39: TOTAL AKTIVA | D39: =D29+D37 -> 2.1609743e+10
A41: 20000 | B41: =VLOOKUP(A41,DAF_AKUN,2,FALSE) -> KEWAJIBAN
A42: 21100 | B42: =VLOOKUP(A42,DAF_AKUN,2,FALSE) -> Hutang Dagang | C42: =SUMIF('Neraca Lajur'!A:A,A42,'Neraca Lajur'!I:I)+SUMIF('Neraca Lajur'!A:A,A42,'Neraca Lajur'!J:J) -> 7976548589 | F42: 2375021873
A43: 22101 | B43: =VLOOKUP(A43,DAF_AKUN,2,FALSE) -> Hutang Pph Final PP 46 | C43: =SUMIF('Neraca Lajur'!A:A,A43,'Neraca Lajur'!I:I)+SUMIF('Neraca Lajur'!A:A,A43,'Neraca Lajur'!J:J) -> 31589467 | F43: 2375021873
A44: 22102 | B44: =VLOOKUP(A44,DAF_AKUN,2,FALSE) -> Hutang Pph Pasal 23 | C44: =SUMIF('Neraca Lajur'!A:A,A44,'Neraca Lajur'!I:I)+SUMIF('Neraca Lajur'!A:A,A44,'Neraca Lajur'!J:J) -> 0 | F44: =+C43+C46+C47+C49 -> 31589467
A45: 22103 | B45: =VLOOKUP(A45,DAF_AKUN,2,FALSE) -> Hutang Pph Pasal 4(2) | C45: =SUMIF('Neraca Lajur'!A:A,A45,'Neraca Lajur'!I:I)+SUMIF('Neraca Lajur'!A:A,A45,'Neraca Lajur'!J:J) -> 0 | F45: 142169796
A46: 22104 | B46: =VLOOKUP(A46,DAF_AKUN,2,FALSE) -> Hutang Pph Pasal 25/29 | C46: =SUMIF('Neraca Lajur'!A:A,A46,'Neraca Lajur'!I:I)+SUMIF('Neraca Lajur'!A:A,A46,'Neraca Lajur'!J:J) -> 0 | F46: 75000000
A47: 22114 | B47: =VLOOKUP(A47,DAF_AKUN,2,FALSE) -> #N/A | C47: =SUMIF('Neraca Lajur'!A:A,A47,'Neraca Lajur'!I:I)+SUMIF('Neraca Lajur'!A:A,A47,'Neraca Lajur'!J:J) -> 0
A48: 22105 | B48: =VLOOKUP(A48,DAF_AKUN,2,FALSE) -> PPN Keluaran | C48: =SUMIF('Neraca Lajur'!A:A,A48,'Neraca Lajur'!I:I)+SUMIF('Neraca Lajur'!A:A,A48,'Neraca Lajur'!J:J) -> 1.2607648e+08
A49: 22106 | B49: =VLOOKUP(A49,DAF_AKUN,2,FALSE) -> #N/A | C49: =SUMIF('Neraca Lajur'!A:A,A49,'Neraca Lajur'!I:I)+SUMIF('Neraca Lajur'!A:A,A49,'Neraca Lajur'!J:J) -> 0
A50: 23100 | B50: =VLOOKUP(A50,DAF_AKUN,2,FALSE) -> Hutang Bank | C50: =SUMIF('Neraca Lajur'!A:A,A50,'Neraca Lajur'!I:I)+SUMIF('Neraca Lajur'!A:A,A50,'Neraca Lajur'!J:J) -> 0
A51: 24100 | B51: =VLOOKUP(A51,DAF_AKUN,2,FALSE) -> Hutang Biaya | C51: =SUMIF('Neraca Lajur'!A:A,A51,'Neraca Lajur'!I:I)+SUMIF('Neraca Lajur'!A:A,A51,'Neraca Lajur'!J:J) -> 6504600 | F51: =+C60+C59 -> 1.9808604e+09
A52: 25100 | B52: =VLOOKUP(A52,DAF_AKUN,2,FALSE) -> Hutang Lain-lain | C52: =SUMIF('Neraca Lajur'!A:A,A52,'Neraca Lajur'!I:I)+SUMIF('Neraca Lajur'!A:A,A52,'Neraca Lajur'!J:J) -> 0 | F52: 223938794
A53: 26100 | B53: =VLOOKUP(A53,DAF_AKUN,2,FALSE) -> Hutang Pemegang Saham | C53: =SUMIF('Neraca Lajur'!A:A,A53,'Neraca Lajur'!I:I)+SUMIF('Neraca Lajur'!A:A,A53,'Neraca Lajur'!J:J) -> 0
A54: 27100 | B54: =VLOOKUP(A54,DAF_AKUN,2,FALSE) -> Uang Muka Penjualan | C54: =SUMIF('Neraca Lajur'!A:A,A54,'Neraca Lajur'!I:I)+SUMIF('Neraca Lajur'!A:A,A54,'Neraca Lajur'!J:J) -> 18857
B55: Jumlah Kewajiban | D55: =SUM(C42:C54) -> 8.140738e+09
A57: 30000 | B57: =VLOOKUP(A57,DAF_AKUN,2,FALSE) -> EKUITAS
A58: 31000 | B58: =VLOOKUP(A58,DAF_AKUN,2,FALSE) -> Modal | C58: ='Lap Modal'!D11 -> 11488144544 | F58: 375764757
A59: 32000 | B59: =VLOOKUP(A59,DAF_AKUN,2,FALSE) -> Laba Ditahan Amnesty | C59: =-'Lap Modal'!C10 -> 1500000000 | F59: =+C59+C60 -> 1.9808604e+09
A60: 33100 | B60: =VLOOKUP(A60,DAF_AKUN,2,FALSE) -> #N/A | C60: =+'Neraca Lajur'!J103 -> 4.808604e+08 | F60: 221901770
A61: 33000 | B61: =VLOOKUP(A61,DAF_AKUN,2,FALSE) -> Prive | C61: ='Lap Modal'!D19 -> 0
A62: 34000 | B62: =VLOOKUP(A62,DAF_AKUN,2,FALSE) -> Pajak Penghasilan | C62: =SUMIF('Neraca Lajur'!A:A,A62,'Neraca Lajur'!I:I)+SUMIF('Neraca Lajur'!A:A,A62,'Neraca Lajur'!J:J) -> 0
B63: Jumlah Ekuitas | D63: =SUM(C58:C62) -> 1.3469005e+10
B65: TOTAL KEWAJIBAN & EKUITAS | D65: =D55+D63 -> 2.1609743e+10 | E65: =D65-D39 -> 0
C67: Yogyakarta, 31 Desember 2026
C73: HERMAWAN ALWAN
C74: DIEKTUR
F257: 42977
F258: 42977
F259: 42977
F260: 42977
F261: 42977
F262: 42977
F263: 42977
F264: 42977
F265: 42977
F266: 42977
F267: 42977
F268: 42977
... F273: 42978

Sheet PYS
DV1: A1
A2: LAMPIRAN KHUSUS
A3: SPT TAHUNAN PAJAK PENGHASILAN WAJIB PAJAK BADAN
B4: TAHUN PAJAK 2023
A5: DAFTAR PENYUSUTAN DAN AMORTISASI FISKAL
B6: NAMA WAJIB PAJAK : | C6: PT. CAHAYA TIMUR OFFSET
B7: N P W P : | C7: =[4]KOMERSIL!$C$6 -> 81.027.758.2.541.000 | BZ7: NAMA WAJIB PAJAK: | CB7: INDRAYANA INDRAATMADJA | CD7: NAMA : | CG7: NAMA :CV. MULTINDO ENGINEERING | CO7: CV. | CU7: NAMA WAJIB PAJAK : | CZ7: NAMA WAJIB PAJAK: | DB7: CV. | DC7: NAMA WAJIB PAJAK: | DG7: NAMA | DH7: : | DJ7: Nama : | DM7: Nama : | DN7: =[4]KOMERSIL!$DJ$6 -> PT. CAHAYA TIMUR OFFSET
C9: =MID(C7,14,3) -> 541 | G9: =MID(C7,14,3) -> 541
C11: Jan | D11: 1 | E11: BP
C12: Feb | D12: 2 | E12: BNP
C13: Mar | D13: 3
C14: Apr | D14: 4
C15: Mei | D15: 5
C16: Jun | D16: 6
C17: Jul | D17: 7
C18: Agt | D18: 8
C19: Sep | D19: 9
C20: Okt | D20: 10
C21: Nop | D21: 11
C22: Des | D22: 12
A23: NO | B23: KELOMPOK/JENIS HARTA | C23: GOL / KEL HARTA | D23: PEROLEHAN | G23: Masa Manfaat | J23: Penyusutan sd. 1994 | K23: Nilai Perolehan 01-01-95 | L23: Tarip Lama | M23: Kel. Harta | N23: Penyusutan | O23: Akumulai | P23: NSBF | Q23: Penyusutan | R23: Akumulai | S23: NSBF | T23: Penyusutan | U23: Akumulai | V23: NSBF | W23: Penyusutan | X23: Akumulai | Y23: NSBF | Z23: Penyusutan | AA23: Akumulai | AB23: NSBF | AC23: Penyusutan | AD23: Akumulai | AE23: Disusutkan | AF23: NSBF 01-01-2001 | AG23: Penyusutan | AH23: Akumulai | AI23: NSBF 01-01-2002 | AJ23: Penyusutan Tahun 2002 | AK23: Akumulai Penyusutan sd. 2002 | AL23: Masa Penyusutan | BH23: NSBF 01-01-2003 | BI23: Penyusutan / Amortisasi Tahun 2003 | BJ23: Akumulai Penyusutan sd. 2003 | BK23: NSBF 01-01-2004 | BL23: Penyusutan / Amortisasi Tahun 2004 | BM23: Akumulai Penyusutan sd. 2004 | BN23: NSBF 01-01-2005 | BO23: Penyusutan / Amortisasi Tahun 2005 | BP23: Akumulasi Penyusutan sd. 2005 | BQ23: NSBF 01-01-2006 | BR23: Penyusutan / Amortisasi Tahun 2006 | BS23: Akumulasi Penyusutan sd. 2006 | BT23: NSBF 01-01-2007 | BU23: Penyusutan / Amortisasi Tahun 2007 | BV23: Akumulasi Penyusutan sd. 2007 | BW23: NSBF 01-01-2008 | BX23: Penyusutan / Amortisasi Tahun 2008 | BY23: Akumulasi Penyusutan sd. 2008 | BZ23: NSBF 01-01-2009 | CA23: Penyusutan / Amortisasi Tahun 2009 | CB23: Akumulasi Penyusutan sd. 2009 | CC23: Nilai Sisa Buku Fiskal Awal Tahun 2010 | CD23: Penyusutan / Amortisasi Tahun 2010 | CE23: Akumulasi Penyusutan sd. 2010 | CF23: Nilai Sisa Buku Fiskal Awal Tahun 2011 | CG23: Penyusutan / Amortisasi Tahun 2011 | CH23: Akumulasi Penyusutan sd. 2011 | CI23: NILAI SISA BUKU AWAL TAHUN (RUPIAH) | CJ23: METODE | CL23: PENYUSUTAN/ AMORTISASI FISKAL TAHUN 2012 | CM23: AKUMULASI PENYUSUTAN SAMPAI DENGAN TAHUN 2012 | CN23: NILAI SISA BUKU AWAL TAHUN (RUPIAH) | CO23: PENYUSUTAN/ AMORTISASI FISKAL TAHUN 2013 | CP23: AKUMULASI PENYUSUTAN SAMPAI DENGAN TAHUN 2013 | CQ23: NILAI SISA BUKU AWAL TAHUN (RUPIAH) | CR23: PENYUSUTAN/ AMORTISASI FISKAL TAHUN 2014 (RUPIAH) | CS23: AKUMULASI PENYUSUTAN SAMPAI DENGAN TAHUN 2014 | CT23: NILAI SISA BUKU AWAL TAHUN (RUPIAH) | CU23: PENYUSUTAN/ AMORTISASI FISKAL TAHUN 2015 (RUPIAH) | CV23: AKUMULASI PENYUSUTAN SAMPAI DENGAN TAHUN 2015 | CW23: NILAI SISA BUKU AWAL TAHUN 2016 (RUPIAH) | CX23: PENYUSUTAN/ AMORTISASI FISKAL TAHUN 2016 (RUPIAH) | CY23: AKUMULASI PENYUSUTAN SAMPAI DENGAN TAHUN 2016 | CZ23: NILAI SISA BUKU AWAL TAHUN 2017 (RUPIAH) | DA23: PENYUSUTAN/ AMORTISASI FISKAL TAHUN 2017 (RUPIAH) | DB23: AKUMULASI PENYUSUTAN SAMPAI DENGAN TAHUN 2017 | DC23: NILAI SISA BUKU AWAL TAHUN 2018 (RUPIAH) | DD23: PENYUSUTAN/ AMORTISASI FISKAL TAHUN 2018 (RUPIAH) | DE23: AKUMULASI PENYUSUTAN SAMPAI DENGAN TAHUN 2018 | DF23: NILAI SISA BUKU AWAL TAHUN 2019 (RUPIAH) | DG23: PENYUSUTAN/ AMORTISASI FISKAL TAHUN 2019 (RUPIAH) | DH23: AKUMULASI PENYUSUTAN SAMPAI DENGAN TAHUN 2019 | DI23: NILAI SISA BUKU AWAL TAHUN 2020 (RUPIAH) | DJ23: PENYUSUTAN/ AMORTISASI FISKAL TAHUN 2020 (RUPIAH) | DK23: AKUMULASI PENYUSUTAN SAMPAI DENGAN TAHUN 2020 | DL23: NILAI SISA BUKU AWAL TAHUN 2021 (RUPIAH) | DM23: PENYUSUTAN/ AMORTISASI FISKAL TAHUN 2021(RUPIAH) | DN23: AKUMULASI PENYUSUTAN SAMPAI DENGAN TAHUN 2021 | DO23: NILAI SISA BUKU AWAL TAHUN 2022 (RUPIAH) | DP23: PENYUSUTAN/ AMORTISASI FISKAL TAHUN 2022(RUPIAH) | DQ23: AKUMULASI PENYUSUTAN SAMPAI DENGAN TAHUN 2022 | DR23: NILAI SISA BUKU AWAL TAHUN 2023 (RUPIAH) | DS23: PENYUSUTAN/ AMORTISASI FISKAL TAHUN 2023(RUPIAH) | DT23: AKUMULASI PENYUSUTAN SAMPAI DENGAN TAHUN 2023 | DU23: NILAI SISA BUKU AKHIR TAHUN 2023 (RUPIAH) | DV23: CATATAN
D24: BULAN | E24: TAHUN | F24: HARGA | G24: Max | H24: Dipakai sd. 1994 | I24: Sisa | N24: Tahun | O24: Penyusutan | P24: 01-01-1996 | Q24: Tahun | R24: Penyusutan | S24: 01-01-1997 | T24: Tahun | U24: Penyusutan | V24: 01-01-1998 | W24: Tahun | X24: Penyusutan | Y24: 01-01-1999 | Z24: Tahun | AA24: Penyusutan | AB24: 01-01-2000 | AC24: Tahun | AD24: Penyusutan | AE24: Sekaligus | AG24: Tahun | AH24: Penyusutan | CJ24: PENYUSUTAN/AMORTISASI
N25: 1995 | O25: sd. 1995 | Q25: 1996 | R25: sd. 1996 | T25: 1997 | U25: sd. 1997 | W25: 1998 | X25: sd. 1998 | Z25: 1999 | AA25: sd. 1999 | AC25: 2000 | AD25: sd. 2000 | AE25: Pada Thn | AG25: 2001 | AH25: sd. 2001 | AM25: 2001 | AN25: 2002 | AO25: 2003 | AP25: 2004 | AQ25: 2005 | AR25: 2006 | AS25: 2007 | AT25: 2008 | AU25: 2009 | AV25: 2010 | AW25: 2011 | AX25: 2012 | AY25: 2013 | AZ25: 2014 | BA25: 2015 | BB25: 2016 | BC25: 2017 | BD25: 2018 | BE25: 2019 | BF25: 2020 | BG25: 2020 | CJ25: KOMERSIAL | CK25: FISKAL
A26: -1 | B26: -2 | C26: -3 | D26: -4 | E26: -5 | F26: -6 | K26: -10 | AK26: -11 | BH26: -12 | BI26: -13 | BJ26: -7 | BK26: -7 | BL26: -8 | BM26: -9 | BN26: -10 | BO26: -8 | BQ26: -7 | BR26: -8 | BS26: -9 | BT26: -10 | BU26: -8 | BV26: -9 | BW26: -10 | CF26: -7 | CG26: -8 | CH26: -9 | CI26: -7 | CJ26: -7 | CK26: -8 | CL26: -10 | CM26: -11 | CN26: -9 | CO26: -10 | CP26: -11 | CQ26: -12 | CR26: -10 | CS26: -11 | CT26: -12 | CU26: -10 | CV26: -11 | CW26: -12 | CX26: -10 | CY26: -11 | CZ26: -12 | DA26: -10 | DB26: -11 | DC26: -12 | DD26: -10 | DE26: -11 | DF26: -12 | DG26: -10 | DH26: -11 | DI26: -12 | DJ26: -10 | DK26: -11 | DL26: -7 | DM26: -8 | DN26: -9 | DO26: -10 | DV26: -11
A27: A | B27: KELOMPOK BANGUNAN
B28: Permanen
A29: 1 | G29: =IF(M29=1,20,10) -> 10 | H29: =IF(E29<=1995,1994+1-E29,0) -> 1995 | I29: =IF(H29=0,G29,G29-H29) -> -1985 | J29: =IF(H29=0,0,IF(H29>=20,F29,F29*0.05*H29)) -> 0 | K29: =IF(J29=0,F29,F29-J29) -> 0 | M29: =IF(C29="BP",1,2) -> 2 | N29: =IF($E29>=1996,0,IF($AE29-1995<=0,K29,IF($M29=1,0.05*$F29,0.1*$F29))) -> 0 | O29: =N29+J29 -> 0 | P29: =IF($E29>=1996,$F29,$F29-O29) -> 0 | Q29: =IF($E29>=1997,0,IF($AE29-1996<=0,P29,IF($M29=1,0.05*$F29,0.1*$F29))) -> 0 | R29: =Q29+O29 -> 0 | S29: =IF($E29>=1997,$F29,$F29-R29) -> 0 | T29: =IF($E29>=1998,0,IF($AE29-1997<=0,S29,IF($M29=1,0.05*$F29,0.1*$F29))) -> 0 | U29: =T29+R29 -> 0 | V29: =IF($E29>=1998,$F29,$F29-U29) -> 0 | W29: =IF($E29>=1999,0,IF($AE29-1998<=0,V29,IF($M29=1,0.05*$F29,0.1*$F29))) -> 0 | X29: =W29+U29 -> 0 | Y29: =IF($E29>=1999,$F29,$F29-X29) -> 0 | Z29: =IF($E29>=2000,0,IF($AE29-1999<=0,Y29,IF($M29=1,0.05*$F29,0.1*$F29))) -> 0 | AA29: =Z29+X29 -> 0 | AB29: =IF($E29>=2000,$F29,$F29-AA29) -> 0 | AC29: =IF($E29>=2001,0,IF($AE29-2000<=0,AB29,IF($M29=1,0.05*$F29,0.1*$F29))) -> 0 | AD29: =AC29+AA29 -> 0 | AE29: =(E29+G29)-1 -> 9 | AF29: =IF($E29>=2001,$F29,$F29-AD29) -> 0 | AG29: =IF($E29>=2002,0,IF($AE29-2001<=0,AF29,IF($M29=1,0.05*$F29*AM29/12,0.1*$F29*AM29/12))) -> 0 | AH29: =AG29+AD29 -> 0 | AI29: =IF($E29>=2002,$F29,$F29-AH29) -> 0 | AJ29: =IF($E29>=2003,0,IF($AE29-2002<=0,AI29,IF($M29=1,0.05*$F29*AN29/12,0.1*$F29*AN29/12))) -> 0 | AK29: =AJ29+AH29 -> 0 | AL29: =VLOOKUP(D29,$C$11:$D$22,2,0) -> #N/A | AM29: =IF(E29>=2001,13-AL29,12) -> 12 | AN29: =IF(E29>=2002,13-AL29,12) -> 12 | AO29: =IF(E29>=2003,13-AL29,12) -> 12 | AP29: =IF(E29>=2004,13-AL29,12) -> 12 | AQ29: =IF(E29>=2005,13-AL29,12) -> 12 | AR29: =IF(E29>=2006,13-AL29,12) -> 12 | AS29: =IF(E29>=2007,13-AL29,12) -> 12 | AT29: =IF(E29>=2008,13-AL29,12) -> 12 | AU29: =IF(E29>=2009,13-AL29,12) -> 12 | AV29: =IF(E29>=2010,13-AL29,12) -> 12 | AW29: =IF(E29>=2011,13-AL29,12) -> 12 | AX29: =IF(E29>=2012,13-AL29,12) -> 12 | AY29: =IF(E29>=2013,13-AL29,12) -> 12 | AZ29: =IF(E29>=2014,13-AL29,12) -> 12 | BA29: =IF(E29>=2015,13-AL29,12) -> 12 | BB29: =IF(E29>=2016,13-AL29,12) -> 12 | BC29: =IF(E29>=2017,13-AL29,12) -> 12 | BD29: =IF(E29>=2018,13-AL29,12) -> 12 | BE29: =IF(E29>=2019,13-AL29,12) -> 12 | BF29: =IF(E29>=2020,13-AL29,12) -> 12 | BG29: =IF(E29>=2021,13-AL29,12) -> 12 | BH29: =IF($E29>=2003,$F29,$F29-AK29) -> 0 | BI29: =IF($E29>=2004,0,IF($AE29-2003<=0,BH29,IF($M29=1,0.05*$F29*AO29/12,0.1*$F29*AO29/12))) -> 0 | BJ29: =BI29+AK29 -> 0 | BK29: =IF($E29>=2004,$F29,$F29-BJ29) -> 0 | BL29: =IF($E29>=2005,0,IF($AE29-2004<=0,BK29,IF($M29=1,0.05*$F29*AP29/12,0.1*$F29*AP29/12))) -> 0 | BM29: =BJ29+BL29 -> 0 | BN29: =IF($E29>=2005,$F29,$F29-BM29) -> 0 | BO29: =IF($E29>=2006,0,IF($AE29-2005<=0,BN29,IF($M29=1,0.05*$F29*AQ29/12,0.1*$F29*AQ29/12))) -> 0 | BP29: =BM29+BO29 -> 0 | BQ29: =IF($E29>=2006,$F29,$F29-BP29) -> 0 | BR29: =IF($E29>=2007,0,IF($AE29-2006<=0,BQ29,IF($M29=1,0.05*$F29*AR29/12,0.1*$F29*AR29/12))) -> 0 | BS29: =BP29+BR29 -> 0 | BT29: =IF($E29>=2007,$F29,$F29-BS29) -> 0 | BU29: =IF($E29>=2008,0,IF($AE29-2007<=0,BT29,IF($M29=1,0.05*$F29*AS29/12,0.1*$F29*AS29/12))) -> 0 | BV29: =BS29+BU29 -> 0 | BW29: =IF($E29>=2008,$F29,$F29-BV29) -> 0 | BX29: =IF($E29>=2009,0,IF($AE29-2008<=0,BW29,IF($M29=1,0.05*$F29*AT29/12,0.1*$F29*AT29/12))) -> 0 | BY29: =BV29+BX29 -> 0 | BZ29: =IF($E29>=2009,$F29,$F29-BY29) -> 0 | CA29: =IF($E29>=2010,0,IF($AE29-2009<=0,BZ29,IF($M29=1,0.05*$F29*AU29/12,0.1*$F29*AU29/12))) -> 0 | CB29: =BY29+CA29 -> 0 | CC29: =IF($E29>=2010,$F29,$F29-CB29) -> 0 | CD29: =IF($E29>=2011,0,IF($AE29-2010<=0,CC29,IF($M29=1,0.05*$F29*AV29/12,0.1*$F29*AV29/12))) -> 0 | CE29: =CB29+CD29 -> 0 | CF29: =IF($E29>=2011,$F29,$F29-CE29) -> 0 | CG29: =IF($E29>=2012,0,IF($AE29-2011<=0,CF29,IF($M29=1,0.05*$F29*AW29/12,0.1*$F29*AW29/12))) -> 0 | CH29: =CE29+CG29 -> 0 | CI29: =IF($E29>=2012,$F29,$F29-CH29) -> 0 | CK29: GL | CL29: =IF($E29>=2013,0,IF($AE29-2012<=0,CI29,IF($M29=1,0.05*$F29*AX29/12,0.1*$F29*AX29/12))) -> 0 | CM29: =CH29+CL29 -> 0 | CN29: =IF($E29>=2013,$F29,$F29-CM29) -> 0 | CO29: =IF($E29>=2014,0,IF($AE29-2013<=0,CN29,IF($M29=1,0.05*$F29*AY29/12,0.1*$F29*AY29/12))) -> 0 | CP29: =CM29+CO29 -> 0 | CQ29: =IF($E29>=2014,$F29,$F29-CP29) -> 0 | CR29: =IF($E29>=2015,0,IF($AE29-2014<=0,CQ29,IF($M29=1,0.05*$F29*AZ29/12,0.1*$F29*AZ29/12))) -> 0 | CS29: =CP29+CR29 -> 0 | CT29: =IF($E29>=2015,$F29,$F29-CS29) -> 0 | CU29: =IF($E29>=2016,0,IF($AE29-2015<=0,CT29,IF($M29=1,0.05*$F29*BA29/12,0.1*$F29*BA29/12))) -> 0 | CV29: =CS29+CU29 -> 0 | CW29: =IF($E29>=2016,$F29,$F29-CV29) -> 0 | CX29: =IF($E29>=2017,0,IF($AE29-2016<=0,CW29,IF($M29=1,0.05*$F29*BB29/12,0.1*$F29*BB29/12))) -> 0 | CY29: =CV29+CX29 -> 0 | CZ29: =IF($E29>=2017,$F29,$F29-CY29) -> 0 | DA29: =IF($E29>=2018,0,IF($AE29-2017<=0,CZ29,IF($M29=1,0.05*$F29*BC29/12,0.1*$F29*BC29/12))) -> 0 | DB29: =CY29+DA29 -> 0 | DC29: =IF($E29>=2018,$F29,$F29-DB29) -> 0 | DD29: =IF($E29>=2019,0,IF($AE29-2018<=0,DC29,IF($M29=1,0.05*$F29*BD29/12,0.1*$F29*BD29/12))) -> 0 | DE29: =DB29+DD29 -> 0 | DF29: =IF($E29>=2019,$F29,$F29-DE29) -> 0 | DG29: =IF($E29>=2020,0,IF($AE29-2019<=0,DF29,IF($M29=1,0.05*$F29*BE29/12,0.1*$F29*BE29/12))) -> 0 | DH29: =DE29+DG29 -> 0 | DI29: =IF($E29>=2020,$F29,$F29-DH29) -> 0 | DJ29: =IF($E29>=2021,0,IF($AE29-2020<=0,DI29,IF($M29=1,0.05*$F29*BF29/12,0.1*$F29*BF29/12))) -> 0 | DK29: =DH29+DJ29 -> 0 | DL29: =IF($E29>=2021,$F29,$F29-DK29) -> 0 | DM29: =IF($E29>=2022,0,IF($AE29-2021<=0,DL29,IF($M29=1,0.05*$F29*BG29/12,0.1*$F29*BG29/12))) -> 0 | DN29: =DK29+DM29 -> 0 | DO29: =IF($E29>=2022,$F29,$F29-DN29) -> 0 | DX29: ='[5]Depr GL 2019'!$DJ$29+DM29 -> 335000000
A30: 2 | G30: =IF(M30=1,20,10) -> 10 | H30: =IF(E30<=1995,1994+1-E30,0) -> 1995 | I30: =IF(H30=0,G30,G30-H30) -> -1985 | J30: =IF(H30=0,0,IF(H30>=20,F30,F30*0.05*H30)) -> 0 | K30: =IF(J30=0,F30,F30-J30) -> 0 | M30: =IF(C30="BP",1,2) -> 2 | N30: =IF($E30>=1996,0,IF($AE30-1995<=0,K30,IF($M30=1,0.05*$F30,0.1*$F30))) -> 0 | O30: =N30+J30 -> 0 | P30: =IF($E30>=1996,$F30,$F30-O30) -> 0 | Q30: =IF($E30>=1997,0,IF($AE30-1996<=0,P30,IF($M30=1,0.05*$F30,0.1*$F30))) -> 0 | R30: =Q30+O30 -> 0 | S30: =IF($E30>=1997,$F30,$F30-R30) -> 0 | T30: =IF($E30>=1998,0,IF($AE30-1997<=0,S30,IF($M30=1,0.05*$F30,0.1*$F30))) -> 0 | U30: =T30+R30 -> 0 | V30: =IF($E30>=1998,$F30,$F30-U30) -> 0 | W30: =IF($E30>=1999,0,IF($AE30-1998<=0,V30,IF($M30=1,0.05*$F30,0.1*$F30))) -> 0 | X30: =W30+U30 -> 0 | Y30: =IF($E30>=1999,$F30,$F30-X30) -> 0 | Z30: =IF($E30>=2000,0,IF($AE30-1999<=0,Y30,IF($M30=1,0.05*$F30,0.1*$F30))) -> 0 | AA30: =Z30+X30 -> 0 | AB30: =IF($E30>=2000,$F30,$F30-AA30) -> 0 | AC30: =IF($E30>=2001,0,IF($AE30-2000<=0,AB30,IF($M30=1,0.05*$F30,0.1*$F30))) -> 0 | AD30: =AC30+AA30 -> 0 | AE30: =(E30+G30)-1 -> 9 | AF30: =IF($E30>=2001,$F30,$F30-AD30) -> 0 | AG30: =IF($E30>=2002,0,IF($AE30-2001<=0,AF30,IF($M30=1,0.05*$F30*AM30/12,0.1*$F30*AM30/12))) -> 0 | AH30: =AG30+AD30 -> 0 | AI30: =IF($E30>=2002,$F30,$F30-AH30) -> 0 | AJ30: =IF($E30>=2003,0,IF($AE30-2002<=0,AI30,IF($M30=1,0.05*$F30*AN30/12,0.1*$F30*AN30/12))) -> 0 | AK30: =AJ30+AH30 -> 0 | AL30: =VLOOKUP(D30,$C$11:$D$22,2,0) -> #N/A | AM30: =IF(E30>=2001,13-AL30,12) -> 12 | AN30: =IF(E30>=2002,13-AL30,12) -> 12 | AO30: =IF(E30>=2003,13-AL30,12) -> 12 | AP30: =IF(E30>=2004,13-AL30,12) -> 12 | AQ30: =IF(E30>=2005,13-AL30,12) -> 12 | AR30: =IF(E30>=2006,13-AL30,12) -> 12 | AS30: =IF(E30>=2007,13-AL30,12) -> 12 | AT30: =IF(E30>=2008,13-AL30,12) -> 12 | AU30: =IF(E30>=2009,13-AL30,12) -> 12 | AV30: =IF(E30>=2010,13-AL30,12) -> 12 | AW30: =IF(E30>=2011,13-AL30,12) -> 12 | AX30: =IF(E30>=2012,13-AL30,12) -> 12 | AY30: =IF(E30>=2013,13-AL30,12) -> 12 | AZ30: =IF(E30>=2014,13-AL30,12) -> 12 | BA30: =IF(E30>=2015,13-AL30,12) -> 12 | BB30: =IF(E30>=2016,13-AL30,12) -> 12 | BC30: =IF(E30>=2017,13-AL30,12) -> 12 | BD30: =IF(E30>=2018,13-AL30,12) -> 12 | BE30: =IF(E30>=2019,13-AL30,12) -> 12 | BF30: =IF(E30>=2020,13-AL30,12) -> 12 | BG30: =IF(E30>=2021,13-AL30,12) -> 12 | BH30: =IF($E30>=2003,$F30,$F30-AK30) -> 0 | BI30: =IF($E30>=2004,0,IF($AE30-2003<=0,BH30,IF($M30=1,0.05*$F30*AO30/12,0.1*$F30*AO30/12))) -> 0 | BJ30: =BI30+AK30 -> 0 | BK30: =IF($E30>=2004,$F30,$F30-BJ30) -> 0 | BL30: =IF($E30>=2005,0,IF($AE30-2004<=0,BK30,IF($M30=1,0.05*$F30*AP30/12,0.1*$F30*AP30/12))) -> 0 | BM30: =BJ30+BL30 -> 0 | BN30: =IF($E30>=2005,$F30,$F30-BM30) -> 0 | BO30: =IF($E30>=2006,0,IF($AE30-2005<=0,BN30,IF($M30=1,0.05*$F30*AQ30/12,0.1*$F30*AQ30/12))) -> 0 | BP30: =BM30+BO30 -> 0 | BQ30: =IF($E30>=2006,$F30,$F30-BP30) -> 0 | BR30: =IF($E30>=2007,0,IF($AE30-2006<=0,BQ30,IF($M30=1,0.05*$F30*AR30/12,0.1*$F30*AR30/12))) -> 0 | BS30: =BP30+BR30 -> 0 | BT30: =IF($E30>=2007,$F30,$F30-BS30) -> 0 | BU30: =IF($E30>=2008,0,IF($AE30-2007<=0,BT30,IF($M30=1,0.05*$F30*AS30/12,0.1*$F30*AS30/12))) -> 0 | BV30: =BS30+BU30 -> 0 | BW30: =IF($E30>=2008,$F30,$F30-BV30) -> 0 | BX30: =IF($E30>=2009,0,IF($AE30-2008<=0,BW30,IF($M30=1,0.05*$F30*AT30/12,0.1*$F30*AT30/12))) -> 0 | BY30: =BV30+BX30 -> 0 | BZ30: =IF($E30>=2009,$F30,$F30-BY30) -> 0 | CA30: =IF($E30>=2010,0,IF($AE30-2009<=0,BZ30,IF($M30=1,0.05*$F30*AU30/12,0.1*$F30*AU30/12))) -> 0 | CB30: =BY30+CA30 -> 0 | CC30: =IF($E30>=2010,$F30,$F30-CB30) -> 0 | CD30: =IF($E30>=2011,0,IF($AE30-2010<=0,CC30,IF($M30=1,0.05*$F30*AV30/12,0.1*$F30*AV30/12))) -> 0 | CE30: =CB30+CD30 -> 0 | CF30: =IF($E30>=2011,$F30,$F30-CE30) -> 0 | CG30: =IF($E30>=2012,0,IF($AE30-2011<=0,CF30,IF($M30=1,0.05*$F30*AW30/12,0.1*$F30*AW30/12))) -> 0 | CH30: =CE30+CG30 -> 0 | CI30: =IF($E30>=2012,$F30,$F30-CH30) -> 0 | CK30: GL | CL30: =IF($E30>=2013,0,IF($AE30-2012<=0,CI30,IF($M30=1,0.05*$F30*AX30/12,0.1*$F30*AX30/12))) -> 0 | CM30: =CH30+CL30 -> 0 | CN30: =IF($E30>=2013,$F30,$F30-CM30) -> 0 | CO30: =IF($E30>=2014,0,IF($AE30-2013<=0,CN30,IF($M30=1,0.05*$F30*AY30/12,0.1*$F30*AY30/12))) -> 0 | CP30: =CM30+CO30 -> 0 | CQ30: =IF($E30>=2014,$F30,$F30-CP30) -> 0 | CR30: =IF($E30>=2015,0,IF($AE30-2014<=0,CQ30,IF($M30=1,0.05*$F30*AZ30/12,0.1*$F30*AZ30/12))) -> 0 | CS30: =CP30+CR30 -> 0 | CT30: =IF($E30>=2015,$F30,$F30-CS30) -> 0 | CU30: =IF($E30>=2016,0,IF($AE30-2015<=0,CT30,IF($M30=1,0.05*$F30*BA30/12,0.1*$F30*BA30/12))) -> 0 | CV30: =CS30+CU30 -> 0 | CW30: =IF($E30>=2016,$F30,$F30-CV30) -> 0 | CX30: =IF($E30>=2017,0,IF($AE30-2016<=0,CW30,IF($M30=1,0.05*$F30*BB30/12,0.1*$F30*BB30/12))) -> 0 | CY30: =CV30+CX30 -> 0 | CZ30: =IF($E30>=2017,$F30,$F30-CY30) -> 0 | DA30: =IF($E30>=2018,0,IF($AE30-2017<=0,CZ30,IF($M30=1,0.05*$F30*BC30/12,0.1*$F30*BC30/12))) -> 0 | DB30: =CY30+DA30 -> 0 | DC30: =IF($E30>=2018,$F30,$F30-DB30) -> 0 | DD30: =IF($E30>=2019,0,IF($AE30-2018<=0,DC30,IF($M30=1,0.05*$F30*BD30/12,0.1*$F30*BD30/12))) -> 0 | DE30: =DB30+DD30 -> 0 | DF30: =IF($E30>=2019,$F30,$F30-DE30) -> 0 | DG30: =IF($E30>=2020,0,IF($AE30-2019<=0,DF30,IF($M30=1,0.05*$F30*BE30/12,0.1*$F30*BE30/12))) -> 0 | DH30: =DE30+DG30 -> 0 | DI30: =IF($E30>=2020,$F30,$F30-DH30) -> 0 | DJ30: =IF($E30>=2021,0,IF($AE30-2020<=0,DI30,IF($M30=1,0.05*$F30*BF30/12,0.1*$F30*BF30/12))) -> 0 | DK30: =DH30+DJ30 -> 0 | DL30: =IF($E30>=2021,$F30,$F30-DK30) -> 0 | DM30: =IF($E30>=2022,0,IF($AE30-2021<=0,DL30,IF($M30=1,0.05*$F30*BG30/12,0.1*$F30*BG30/12))) -> 0 | DN30: =DK30+DM30 -> 0 | DO30: =IF($E30>=2022,$F30,$F30-DN30) -> 0 | DX30: ='[5]Depr GL 2019'!$DJ$30+DM30 -> 22750000
B31: Tidak Permanen | BF31: =IF(E31>=2020,13-AL31,12) -> 12 | BG31: =IF(E31>=2021,13-AL31,12) -> 12 | DK31: =DH31+DJ31 -> 0 | DL31: =IF($E31>=2021,$F31,$F31-DK31) -> 0 | DM31: =IF($E31>=2022,0,IF($AE31-2021<=0,DL31,IF($M31=1,0.05*$F31*BG31/12,0.1*$F31*BG31/12))) -> 0 | DN31: =DK31+DM31 -> 0 | DO31: =IF($E31>=2022,$F31,$F31-DN31) -> 0
A32: 2 | B32: Gedung | C32: BNP | D32: Jan | E32: 2017 | G32: =IF(M32=1,20,10) -> 10 | H32: =IF(E32<=1995,1994+1-E32,0) -> 0 | I32: =IF(H32=0,G32,G32-H32) -> 10 | J32: =IF(H32=0,0,IF(H32>=20,F32,F32*0.05*H32)) -> 0 | K32: =IF(J32=0,F32,F32-J32) -> 0 | M32: =IF(C32="BP",1,2) -> 2 | N32: =IF($E32>=1996,0,IF($AE32-1995<=0,K32,IF($M32=1,0.05*$F32,0.1*$F32))) -> 0 | O32: =N32+J32 -> 0 | P32: =IF($E32>=1996,$F32,$F32-O32) -> 0 | Q32: =IF($E32>=1997,0,IF($AE32-1996<=0,P32,IF($M32=1,0.05*$F32,0.1*$F32))) -> 0 | R32: =Q32+O32 -> 0 | S32: =IF($E32>=1997,$F32,$F32-R32) -> 0 | T32: =IF($E32>=1998,0,IF($AE32-1997<=0,S32,IF($M32=1,0.05*$F32,0.1*$F32))) -> 0 | U32: =T32+R32 -> 0 | V32: =IF($E32>=1998,$F32,$F32-U32) -> 0 | W32: =IF($E32>=1999,0,IF($AE32-1998<=0,V32,IF($M32=1,0.05*$F32,0.1*$F32))) -> 0 | X32: =W32+U32 -> 0 | Y32: =IF($E32>=1999,$F32,$F32-X32) -> 0 | Z32: =IF($E32>=2000,0,IF($AE32-1999<=0,Y32,IF($M32=1,0.05*$F32,0.1*$F32))) -> 0 | AA32: =Z32+X32 -> 0 | AB32: =IF($E32>=2000,$F32,$F32-AA32) -> 0 | AC32: =IF($E32>=2001,0,IF($AE32-2000<=0,AB32,IF($M32=1,0.05*$F32,0.1*$F32))) -> 0 | AD32: =AC32+AA32 -> 0 | AE32: =(E32+G32)-1 -> 2026 | AF32: =IF($E32>=2001,$F32,$F32-AD32) -> 0 | AG32: =IF($E32>=2002,0,IF($AE32-2001<=0,AF32,IF($M32=1,0.05*$F32*AM32/12,0.1*$F32*AM32/12))) -> 0 | AH32: =AG32+AD32 -> 0 | AI32: =IF($E32>=2002,$F32,$F32-AH32) -> 0 | AJ32: =IF($E32>=2003,0,IF($AE32-2002<=0,AI32,IF($M32=1,0.05*$F32*AN32/12,0.1*$F32*AN32/12))) -> 0 | AK32: =AJ32+AH32 -> 0 | AL32: =VLOOKUP(D32,$C$11:$D$22,2,0) -> 1 | AM32: =IF(E32>=2001,13-AL32,12) -> 12 | AN32: =IF(E32>=2002,13-AL32,12) -> 12 | AO32: =IF(E32>=2003,13-AL32,12) -> 12 | AP32: =IF(E32>=2004,13-AL32,12) -> 12 | AQ32: =IF(E32>=2005,13-AL32,12) -> 12 | AR32: =IF(E32>=2006,13-AL32,12) -> 12 | AS32: =IF(E32>=2007,13-AL32,12) -> 12 | AT32: =IF(E32>=2008,13-AL32,12) -> 12 | AU32: =IF(E32>=2009,13-AL32,12) -> 12 | AV32: =IF(E32>=2010,13-AL32,12) -> 12 | AW32: =IF(E32>=2011,13-AL32,12) -> 12 | AX32: =IF(E32>=2012,13-AL32,12) -> 12 | AY32: =IF(E32>=2013,13-AL32,12) -> 12 | AZ32: =IF(E32>=2014,13-AL32,12) -> 12 | BA32: =IF(E32>=2015,13-AL32,12) -> 12 | BB32: =IF(E32>=2016,13-AL32,12) -> 12 | BC32: =IF(E32>=2017,13-AL32,12) -> 12 | BD32: =IF(E32>=2018,13-AL32,12) -> 12 | BE32: =IF(E32>=2019,13-AL32,12) -> 12 | BF32: =IF(E32>=2020,13-AL32,12) -> 12 | BG32: =IF(E32>=2021,13-AL32,12) -> 12 | BH32: =IF($E32>=2003,$F32,$F32-AK32) -> 0 | BI32: =IF($E32>=2004,0,IF($AE32-2003<=0,BH32,IF($M32=1,0.05*$F32*AO32/12,0.1*$F32*AO32/12))) -> 0 | BJ32: =BI32+AK32 -> 0 | BK32: =IF($E32>=2004,$F32,$F32-BJ32) -> 0 | BL32: =IF($E32>=2005,0,IF($AE32-2004<=0,BK32,IF($M32=1,0.05*$F32*AP32/12,0.1*$F32*AP32/12))) -> 0 | BM32: =BJ32+BL32 -> 0 | BN32: =IF($E32>=2005,$F32,$F32-BM32) -> 0 | BO32: =IF($E32>=2006,0,IF($AE32-2005<=0,BN32,IF($M32=1,0.05*$F32*AQ32/12,0.1*$F32*AQ32/12))) -> 0 | BP32: =BM32+BO32 -> 0 | BQ32: =IF($E32>=2006,$F32,$F32-BP32) -> 0 | BR32: =IF($E32>=2007,0,IF($AE32-2006<=0,BQ32,IF($M32=1,0.05*$F32*AR32/12,0.1*$F32*AR32/12))) -> 0 | BS32: =BP32+BR32 -> 0 | BT32: =IF($E32>=2007,$F32,$F32-BS32) -> 0 | BU32: =IF($E32>=2008,0,IF($AE32-2007<=0,BT32,IF($M32=1,0.05*$F32*AS32/12,0.1*$F32*AS32/12))) -> 0 | BV32: =BS32+BU32 -> 0 | BW32: =IF($E32>=2008,$F32,$F32-BV32) -> 0 | BX32: =IF($E32>=2009,0,IF($AE32-2008<=0,BW32,IF($M32=1,0.05*$F32*AT32/12,0.1*$F32*AT32/12))) -> 0 | BY32: =BV32+BX32 -> 0 | BZ32: =IF($E32>=2009,$F32,$F32-BY32) -> 0 | CA32: =IF($E32>=2010,0,IF($AE32-2009<=0,BZ32,IF($M32=1,0.05*$F32*AU32/12,0.1*$F32*AU32/12))) -> 0 | CB32: =BY32+CA32 -> 0 | CC32: =IF($E32>=2010,$F32,$F32-CB32) -> 0 | CD32: =IF($E32>=2011,0,IF($AE32-2010<=0,CC32,IF($M32=1,0.05*$F32*AV32/12,0.1*$F32*AV32/12))) -> 0 | CE32: =CB32+CD32 -> 0 | CF32: =IF($E32>=2011,$F32,$F32-CE32) -> 0 | CG32: =IF($E32>=2012,0,IF($AE32-2011<=0,CF32,IF($M32=1,0.05*$F32*AW32/12,0.1*$F32*AW32/12))) -> 0 | CH32: =CE32+CG32 -> 0 | CI32: =IF($E32>=2012,$F32,$F32-CH32) -> 0 | CK32: GL | CL32: =IF($E32>=2013,0,IF($AE32-2012<=0,CI32,IF($M32=1,0.05*$F32*AX32/12,0.1*$F32*AX32/12))) -> 0 | CM32: =CH32+CL32 -> 0 | CN32: =IF($E32>=2013,$F32,$F32-CM32) -> 0 | CO32: =IF($E32>=2014,0,IF($AE32-2013<=0,CN32,IF($M32=1,0.05*$F32*AY32/12,0.1*$F32*AY32/12))) -> 0 | CP32: =CM32+CO32 -> 0 | CQ32: =IF($E32>=2014,$F32,$F32-CP32) -> 0 | CR32: =IF($E32>=2015,0,IF($AE32-2014<=0,CQ32,IF($M32=1,0.05*$F32*AZ32/12,0.1*$F32*AZ32/12))) -> 0 | CS32: =CP32+CR32 -> 0 | CT32: =IF($E32>=2015,$F32,$F32-CS32) -> 0 | CU32: =IF($E32>=2016,0,IF($AE32-2015<=0,CT32,IF($M32=1,0.05*$F32*BA32/12,0.1*$F32*BA32/12))) -> 0 | CV32: =CS32+CU32 -> 0 | CW32: =IF($E32>=2016,$F32,$F32-CV32) -> 0 | CX32: =IF($E32>=2017,0,IF($AE32-2016<=0,CW32,IF($M32=1,0.05*$F32*BB32/12,0.1*$F32*BB32/12))) -> 0 | CY32: =CV32+CX32 -> 0 | CZ32: =IF($E32>=2017,$F32,$F32-CY32) -> 0 | DA32: =IF($E32>=2018,0,IF($AE32-2017<=0,CZ32,IF($M32=1,0.05*$F32*BC32/12,0.1*$F32*BC32/12))) -> 0 | DB32: =CY32+DA32 -> 0 | DC32: =IF($E32>=2018,$F32,$F32-DB32) -> 0 | DD32: =IF($E32>=2019,0,IF($AE32-2018<=0,DC32,IF($M32=1,0.05*$F32*BD32/12,0.1*$F32*BD32/12))) -> 0 | DE32: =DB32+DD32 -> 0 | DF32: =IF($E32>=2019,$F32,$F32-DE32) -> 0 | DG32: =IF($E32>=2020,0,IF($AE32-2019<=0,DF32,IF($M32=1,0.05*$F32*BE32/12,0.1*$F32*BE32/12))) -> 0 | DH32: =DE32+DG32 -> 0 | DI32: =IF($E32>=2020,$F32,$F32-DH32) -> 0 | DJ32: =IF($E32>=2020,0,IF($AE32-2019<=0,DI32,IF($M32=1,0.05*$F32*BI32/12,0.1*$F32*BI32/12))) -> 0 | DK32: =DH32+DJ32 -> 0 | DL32: =IF($E32>=2021,$F32,$F32-DK32) -> 0 | DM32: =IF($E32>=2022,0,IF($AE32-2021<=0,DL32,IF($M32=1,0.05*$F32*BG32/12,0.1*$F32*BG32/12))) -> 0 | DN32: =DK32+DM32 -> 0 | DO32: =IF($E32>=2022,$F32,$F32-DN32) -> 0
B33: HARTA BERWUJUD | DK33: =DH33+DJ33 -> 0 | DL33: =IF($E33>=2021,$F33,$F33-DK33) -> 0 | DM33: =IF($E33>=2022,0,IF($AE33-2021<=0,DL33,IF($M33=1,0.05*$F33*BG33/12,0.1*$F33*BG33/12))) -> 0 | DN33: =DK33+DM33 -> 0 | DO33: =IF($E33>=2022,$F33,$F33-DN33) -> 0
A34: 1 | B34: A | C34: I | E34: 1992 | G34: =IF(C34="I",4,IF(C34="II",8,16)) -> 4 | H34: =IF(E34<=1995,1994+1-E34,0) -> 3 | I34: =IF(H34=0,G34,G34-H34) -> 1 | J34: =F34-K34 -> 0 | K34: =IF(E34>=1995,F34,F34*(1-L34)^H34) -> 0 | L34: =IF(C34="I",0.5,IF(C34="II",0.25,0.1)) -> 0.5 | M34: =IF(E34>=1995,C34,IF(AND(I34>1,I34<6),"I",IF(AND(I34>=6,I34<12),"II",IF(I34>=12,"III","-")))) -> - | N34: =IF($E34>=1996,0,IF($AE34=N$25,K34,IF($M34="I",0.25*$K34,IF($M34="II",0.125*$K34,IF($M34="III",0.0625*$K34,IF($M34="IV",0.05*$K34,$K34)))))) -> 0 | O34: =N34+J34 -> 0 | P34: =IF($E34>=1996,$F34,$F34-O34) -> 0 | Q34: =IF($E34>=1997,0,IF($AE34-1996<=0,P34,IF($M34="I",0.25*$K34,IF($M34="II",0.125*$K34,IF($M34="III",0.0625*$K34,IF($M34="IV",0.05*$K34,$K34)))))) -> 0 | R34: =Q34+O34 -> 0 | S34: =IF($E34>=1997,$F34,$F34-R34) -> 0 | T34: =IF($E34>=1998,0,IF($AE34-1997<=0,S34,IF($M34="I",0.25*$K34,IF($M34="II",0.125*$K34,IF($M34="III",0.0625*$K34,IF($M34="IV",0.05*$K34,$K34)))))) -> 0 | U34: =T34+R34 -> 0 | V34: =IF($E34>=1998,$F34,$F34-U34) -> 0 | W34: =IF($E34>=1999,0,IF($AE34-1998<=0,V34,IF($M34="I",0.25*$K34,IF($M34="II",0.125*$K34,IF($M34="III",0.0625*$K34,IF($M34="IV",0.05*$K34,$K34)))))) -> 0 | X34: =W34+U34 -> 0 | Y34: =IF($E34>=1999,$F34,$F34-X34) -> 0 | Z34: =IF($E34>=2000,0,IF($AE34-1999<=0,Y34,IF($M34="I",0.25*$K34,IF($M34="II",0.125*$K34,IF($M34="III",0.0625*$K34,IF($M34="IV",0.05*$K34,$K34)))))) -> 0 | AA34: =Z34+X34 -> 0 | AB34: =IF($E34>=2000,$F34,$F34-AA34) -> 0 | AC34: =IF($E34>=2001,0,IF($AE34-2000<=0,AB34,IF($M34="I",0.25*$K34,IF($M34="II",0.125*$K34,IF($M34="III",0.0625*$K34,IF($M34="IV",0.05*$K34,$K34)))))) -> 0 | AD34: =AC34+AA34 -> 0 | AE34: =IF(AND($E34<=1994,$M34="I"),1995+3,IF(AND($E34<=1994,$M34="II"),1995+7,IF(AND($E34<=1994,$M34="III"),1995+15,IF(AND($E34<=1994,$M34="IV"),1995+19,IF($M34="I",$E34+3,IF($M34="II",$E34+7,IF($M34="III",$E34+15,IF($M34="IV",$E34+19,1995)))))))) -> 1995 | AF34: =IF($E34>=2001,$F34,$F34-AD34) -> 0 | AG34: =IF($E34>=2002,0,IF($AE34-2001<=0,AF34,IF($M34="I",0.25*$K34,IF($M34="II",0.125*$K34,IF($M34="III",0.0625*$K34,IF($M34="IV",0.05*$K34,$K34)))))) -> 0 | AH34: =AG34+AD34 -> 0 | AI34: =IF($E34>=2002,$F34,$F34-AH34) -> 0 | AJ34: =IF($E34>=2003,0,IF($AE34-2002<=0,AI34,IF($M34="I",0.25*$K34,IF($M34="II",0.125*$K34,IF($M34="III",0.0625*$K34,IF($M34="IV",0.05*$K34,$K34)))))) -> 0 | AK34: =AJ34+AH34 -> 0 | BH34: =IF($E34>=2003,$F34,$F34-AK34) -> 0 | BI34: =IF($E34>=2004,0,IF($AE34-2003<=0,BH34,IF($M34="I",0.25*$K34,IF($M34="II",0.125*$K34,IF($M34="III",0.0625*$K34,IF($M34="IV",0.05*$K34,$K34)))))) -> 0 | BJ34: =BI34+AK34 -> 0 | BK34: =IF($E34>=2004,$F34,$F34-BJ34) -> 0 | BL34: =IF($E34>=2005,0,IF($AE34-2004<=0,BK34,IF($M34="I",0.25*$K34,IF($M34="II",0.125*$K34,IF($M34="III",0.0625*$K34,IF($M34="IV",0.05*$K34,$K34)))))) -> 0 | BM34: =BJ34+BL34 -> 0 | BN34: =IF($E34>=2005,$F34,$F34-BM34) -> 0 | BO34: =IF($E34>=2006,0,IF($AE34-2005<=0,BN34,IF($M34="I",0.25*$K34,IF($M34="II",0.125*$K34,IF($M34="III",0.0625*$K34,IF($M34="IV",0.05*$K34,$K34)))))) -> 0 | BP34: =BM34+BO34 -> 0 | BQ34: =IF($E34>=2006,$F34,$F34-BP34) -> 0 | BR34: =IF($E34>=2007,0,IF($AE34-2006<=0,BQ34,IF($M34="I",0.25*$K34,IF($M34="II",0.125*$K34,IF($M34="III",0.0625*$K34,IF($M34="IV",0.05*$K34,$K34)))))) -> 0 | BS34: =BP34+BR34 -> 0 | BT34: =IF($E34>=2007,$F34,$F34-BS34) -> 0 | BU34: =IF($E34>=2008,0,IF($AE34-2007<=0,BT34,IF($M34="I",0.25*$K34,IF($M34="II",0.125*$K34,IF($M34="III",0.0625*$K34,IF($M34="IV",0.05*$K34,$K34)))))) -> 0 | BV34: =BS34+BU34 -> 0 | BW34: =IF($E34>=2008,$F34,$F34-BV34) -> 0 | BX34: =IF($E34>=2009,0,IF($AE34-2008<=0,BW34,IF($M34="I",0.25*$K34,IF($M34="II",0.125*$K34,IF($M34="III",0.0625*$K34,IF($M34="IV",0.05*$K34,$K34)))))) -> 0 | BY34: =BV34+BX34 -> 0 | BZ34: =IF($E34>=2009,$F34,$F34-BY34) -> 0 | CA34: =IF($E34>=2010,0,IF($AE34-2009<=0,BZ34,IF($M34="I",0.25*$K34,IF($M34="II",0.125*$K34,IF($M34="III",0.0625*$K34,IF($M34="IV",0.05*$K34,$K34)))))) -> 0 | CB34: =BY34+CA34 -> 0 | CC34: =IF($E34>=2010,$F34,$F34-CB34) -> 0 | CD34: =IF($E34>=2011,0,IF($AE34-2010<=0,CC34,IF($M34="I",0.25*$K34,IF($M34="II",0.125*$K34,IF($M34="III",0.0625*$K34,IF($M34="IV",0.05*$K34,$K34)))))) -> 0 | CE34: =CB34+CD34 -> 0 | CF34: =IF($E34>=2011,$F34,$F34-CE34) -> 0 | CG34: =IF($E34>=2012,0,IF($AE34-2011<=0,CF34,IF($M34="I",0.25*$K34,IF($M34="II",0.125*$K34,IF($M34="III",0.0625*$K34,IF($M34="IV",0.05*$K34,$K34)))))) -> 0 | CH34: =CE34+CG34 -> 0 | CI34: =IF($E34>=2012,$F34,$F34-CH34) -> 0 | CK34: GL | CL34: =IF($E34>=2013,0,IF($AE34-2012<=0,CI34,IF($M34="I",0.25*$K34,IF($M34="II",0.125*$K34,IF($M34="III",0.0625*$K34,IF($M34="IV",0.05*$K34,$K34)))))) -> 0 | CM34: =CH34+CL34 -> 0 | CN34: =IF($E34>=2013,$F34,$F34-CM34) -> 0 | CO34: =IF($E34>=2014,0,IF($AE34-2013<=0,CN34,IF($M34="I",0.25*$K34,IF($M34="II",0.125*$K34,IF($M34="III",0.0625*$K34,IF($M34="IV",0.05*$K34,$K34)))))) -> 0 | CP34: =CM34+CO34 -> 0 | CQ34: =IF($E34>=2014,$F34,$F34-CP34) -> 0 | CR34: =IF($E34>=2015,0,IF($AE34-2014<=0,CQ34,IF($M34="I",0.25*$K34,IF($M34="II",0.125*$K34,IF($M34="III",0.0625*$K34,IF($M34="IV",0.05*$K34,$K34)))))) -> 0 | CS34: =CP34+CR34 -> 0 | CT34: =IF($E34>=2015,$F34,$F34-CS34) -> 0 | CU34: =IF($E34>=2016,0,IF($AE34-2015<=0,CT34,IF($M34="I",0.25*$K34,IF($M34="II",0.125*$K34,IF($M34="III",0.0625*$K34,IF($M34="IV",0.05*$K34,$K34)))))) -> 0 | CV34: =CS34+CU34 -> 0 | CW34: =IF($E34>=2016,$F34,$F34-CV34) -> 0 | CX34: =IF($E34>=2017,0,IF($AE34-2016<=0,CW34,IF($M34="I",0.25*$K34,IF($M34="II",0.125*$K34,IF($M34="III",0.0625*$K34,IF($M34="IV",0.05*$K34,$K34)))))) -> 0 | CY34: =CV34+CX34 -> 0 | CZ34: =IF($E34>=2016,$F34,$F34-CY34) -> 0 | DA34: =IF($E34>=2018,0,IF($AE34-2017<=0,CZ34,IF($M34="I",0.25*$K34,IF($M34="II",0.125*$K34,IF($M34="III",0.0625*$K34,IF($M34="IV",0.05*$K34,$K34)))))) -> 0 | DB34: =CY34+DA34 -> 0 | DC34: =IF($E34>=2016,$F34,$F34-DB34) -> 0 | DD34: =IF($E34>=2019,0,IF($AE34-2018<=0,DC34,IF($M34="I",0.25*$K34,IF($M34="II",0.125*$K34,IF($M34="III",0.0625*$K34,IF($M34="IV",0.05*$K34,$K34)))))) -> 0 | DE34: =DB34+DD34 -> 0 | DF34: =IF($E34>=2019,$F34,$F34-DE34) -> 0 | DG34: =IF($E34>=2020,0,IF($AE34-2019<=0,DF34,IF($M34="I",0.25*$K34,IF($M34="II",0.125*$K34,IF($M34="III",0.0625*$K34,IF($M34="IV",0.05*$K34,$K34)))))) -> 0 | DH34: =DE34+DG34 -> 0 | DI34: =IF($E34>=2020,$F34,$F34-DH34) -> 0 | DJ34: =IF($E34>=2020,0,IF($AE34-2019<=0,DI34,IF($M34="I",0.25*$K34,IF($M34="II",0.125*$K34,IF($M34="III",0.0625*$K34,IF($M34="IV",0.05*$K34,$K34)))))) -> 0 | DK34: =DH34+DJ34 -> 0 | DL34: =IF($E34>=2021,$F34,$F34-DK34) -> 0 | DM34: =IF($E34>=2022,0,IF($AE34-2021<=0,DL34,IF($M34=1,0.05*$F34*BG34/12,0.1*$F34*BG34/12))) -> 0 | DN34: =DK34+DM34 -> 0 | DO34: =IF($E34>=2022,$F34,$F34-DN34) -> 0
A35: =A34+1 -> 2 | B35: B | C35: I | E35: 1992 | G35: =IF(C35="I",4,IF(C35="II",8,16)) -> 4 | H35: =IF(E35<=1995,1994+1-E35,0) -> 3 | I35: =IF(H35=0,G35,G35-H35) -> 1 | J35: =F35-K35 -> 0 | K35: =IF(E35>=1995,F35,F35*(1-L35)^H35) -> 0 | L35: =IF(C35="I",0.5,IF(C35="II",0.25,0.1)) -> 0.5 | M35: =IF(E35>=1995,C35,IF(AND(I35>1,I35<6),"I",IF(AND(I35>=6,I35<12),"II",IF(I35>=12,"III","-")))) -> - | N35: =IF($E35>=1996,0,IF($AE35=N$25,K35,IF($M35="I",0.25*$K35,IF($M35="II",0.125*$K35,IF($M35="III",0.0625*$K35,IF($M35="IV",0.05*$K35,$K35)))))) -> 0 | O35: =N35+J35 -> 0 | P35: =IF($E35>=1996,$F35,$F35-O35) -> 0 | Q35: =IF($E35>=1997,0,IF($AE35-1996<=0,P35,IF($M35="I",0.25*$K35,IF($M35="II",0.125*$K35,IF($M35="III",0.0625*$K35,IF($M35="IV",0.05*$K35,$K35)))))) -> 0 | R35: =Q35+O35 -> 0 | S35: =IF($E35>=1997,$F35,$F35-R35) -> 0 | T35: =IF($E35>=1998,0,IF($AE35-1997<=0,S35,IF($M35="I",0.25*$K35,IF($M35="II",0.125*$K35,IF($M35="III",0.0625*$K35,IF($M35="IV",0.05*$K35,$K35)))))) -> 0 | U35: =T35+R35 -> 0 | V35: =IF($E35>=1998,$F35,$F35-U35) -> 0 | W35: =IF($E35>=1999,0,IF($AE35-1998<=0,V35,IF($M35="I",0.25*$K35,IF($M35="II",0.125*$K35,IF($M35="III",0.0625*$K35,IF($M35="IV",0.05*$K35,$K35)))))) -> 0 | X35: =W35+U35 -> 0 | Y35: =IF($E35>=1999,$F35,$F35-X35) -> 0 | Z35: =IF($E35>=2000,0,IF($AE35-1999<=0,Y35,IF($M35="I",0.25*$K35,IF($M35="II",0.125*$K35,IF($M35="III",0.0625*$K35,IF($M35="IV",0.05*$K35,$K35)))))) -> 0 | AA35: =Z35+X35 -> 0 | AB35: =IF($E35>=2000,$F35,$F35-AA35) -> 0 | AC35: =IF($E35>=2001,0,IF($AE35-2000<=0,AB35,IF($M35="I",0.25*$K35,IF($M35="II",0.125*$K35,IF($M35="III",0.0625*$K35,IF($M35="IV",0.05*$K35,$K35)))))) -> 0 | AD35: =AC35+AA35 -> 0 | AE35: =IF(AND($E35<=1994,$M35="I"),1995+3,IF(AND($E35<=1994,$M35="II"),1995+7,IF(AND($E35<=1994,$M35="III"),1995+15,IF(AND($E35<=1994,$M35="IV"),1995+19,IF($M35="I",$E35+3,IF($M35="II",$E35+7,IF($M35="III",$E35+15,IF($M35="IV",$E35+19,1995)))))))) -> 1995 | AF35: =IF($E35>=2001,$F35,$F35-AD35) -> 0 | AG35: =IF($E35>=2002,0,IF($AE35-2001<=0,AF35,IF($M35="I",0.25*$K35,IF($M35="II",0.125*$K35,IF($M35="III",0.0625*$K35,IF($M35="IV",0.05*$K35,$K35)))))) -> 0 | AH35: =AG35+AD35 -> 0 | AI35: =IF($E35>=2002,$F35,$F35-AH35) -> 0 | AJ35: =IF($E35>=2003,0,IF($AE35-2002<=0,AI35,IF($M35="I",0.25*$K35,IF($M35="II",0.125*$K35,IF($M35="III",0.0625*$K35,IF($M35="IV",0.05*$K35,$K35)))))) -> 0 | AK35: =AJ35+AH35 -> 0 | BH35: =IF($E35>=2003,$F35,$F35-AK35) -> 0 | BI35: =IF($E35>=2004,0,IF($AE35-2003<=0,BH35,IF($M35="I",0.25*$K35,IF($M35="II",0.125*$K35,IF($M35="III",0.0625*$K35,IF($M35="IV",0.05*$K35,$K35)))))) -> 0 | BJ35: =BI35+AK35 -> 0 | BK35: =IF($E35>=2004,$F35,$F35-BJ35) -> 0 | BL35: =IF($E35>=2005,0,IF($AE35-2004<=0,BK35,IF($M35="I",0.25*$K35,IF($M35="II",0.125*$K35,IF($M35="III",0.0625*$K35,IF($M35="IV",0.05*$K35,$K35)))))) -> 0 | BM35: =BJ35+BL35 -> 0 | BN35: =IF($E35>=2005,$F35,$F35-BM35) -> 0 | BO35: =IF($E35>=2006,0,IF($AE35-2005<=0,BN35,IF($M35="I",0.25*$K35,IF($M35="II",0.125*$K35,IF($M35="III",0.0625*$K35,IF($M35="IV",0.05*$K35,$K35)))))) -> 0 | BP35: =BM35+BO35 -> 0 | BQ35: =IF($E35>=2006,$F35,$F35-BP35) -> 0 | BR35: =IF($E35>=2007,0,IF($AE35-2006<=0,BQ35,IF($M35="I",0.25*$K35,IF($M35="II",0.125*$K35,IF($M35="III",0.0625*$K35,IF($M35="IV",0.05*$K35,$K35)))))) -> 0 | BS35: =BP35+BR35 -> 0 | BT35: =IF($E35>=2007,$F35,$F35-BS35) -> 0 | BU35: =IF($E35>=2008,0,IF($AE35-2007<=0,BT35,IF($M35="I",0.25*$K35,IF($M35="II",0.125*$K35,IF($M35="III",0.0625*$K35,IF($M35="IV",0.05*$K35,$K35)))))) -> 0 | BV35: =BS35+BU35 -> 0 | BW35: =IF($E35>=2008,$F35,$F35-BV35) -> 0 | BX35: =IF($E35>=2009,0,IF($AE35-2008<=0,BW35,IF($M35="I",0.25*$K35,IF($M35="II",0.125*$K35,IF($M35="III",0.0625*$K35,IF($M35="IV",0.05*$K35,$K35)))))) -> 0 | BY35: =BV35+BX35 -> 0 | BZ35: =IF($E35>=2009,$F35,$F35-BY35) -> 0 | CA35: =IF($E35>=2010,0,IF($AE35-2009<=0,BZ35,IF($M35="I",0.25*$K35,IF($M35="II",0.125*$K35,IF($M35="III",0.0625*$K35,IF($M35="IV",0.05*$K35,$K35)))))) -> 0 | CB35: =BY35+CA35 -> 0 | CC35: =IF($E35>=2010,$F35,$F35-CB35) -> 0 | CD35: =IF($E35>=2011,0,IF($AE35-2010<=0,CC35,IF($M35="I",0.25*$K35,IF($M35="II",0.125*$K35,IF($M35="III",0.0625*$K35,IF($M35="IV",0.05*$K35,$K35)))))) -> 0 | CE35: =CB35+CD35 -> 0 | CF35: =IF($E35>=2011,$F35,$F35-CE35) -> 0 | CG35: =IF($E35>=2012,0,IF($AE35-2011<=0,CF35,IF($M35="I",0.25*$K35,IF($M35="II",0.125*$K35,IF($M35="III",0.0625*$K35,IF($M35="IV",0.05*$K35,$K35)))))) -> 0 | CH35: =CE35+CG35 -> 0 | CI35: =IF($E35>=2012,$F35,$F35-CH35) -> 0 | CK35: GL | CL35: =IF($E35>=2012,0,IF($AE35-2011<=0,CI35,IF($M35="I",0.25*$K35,IF($M35="II",0.125*$K35,IF($M35="III",0.0625*$K35,IF($M35="IV",0.05*$K35,$K35)))))) -> 0 | CM35: =CH35+CL35 -> 0 | CN35: =IF($E35>=2013,$F35,$F35-CM35) -> 0 | CO35: =IF($E35>=2014,0,IF($AE35-2013<=0,CN35,IF($M35="I",0.25*$K35,IF($M35="II",0.125*$K35,IF($M35="III",0.0625*$K35,IF($M35="IV",0.05*$K35,$K35)))))) -> 0 | CP35: =CM35+CO35 -> 0 | CQ35: =IF($E35>=2014,$F35,$F35-CP35) -> 0 | CR35: =IF($E35>=2015,0,IF($AE35-2014<=0,CQ35,IF($M35="I",0.25*$K35,IF($M35="II",0.125*$K35,IF($M35="III",0.0625*$K35,IF($M35="IV",0.05*$K35,$K35)))))) -> 0 | CS35: =CP35+CR35 -> 0 | CT35: =IF($E35>=2015,$F35,$F35-CS35) -> 0 | CU35: =IF($E35>=2016,0,IF($AE35-2015<=0,CT35,IF($M35="I",0.25*$K35,IF($M35="II",0.125*$K35,IF($M35="III",0.0625*$K35,IF($M35="IV",0.05*$K35,$K35)))))) -> 0 | CV35: =CS35+CU35 -> 0 | CW35: =IF($E35>=2016,$F35,$F35-CV35) -> 0 | CX35: =IF($E35>=2017,0,IF($AE35-2016<=0,CW35,IF($M35="I",0.25*$K35,IF($M35="II",0.125*$K35,IF($M35="III",0.0625*$K35,IF($M35="IV",0.05*$K35,$K35)))))) -> 0 | CY35: =CV35+CX35 -> 0 | CZ35: =IF($E35>=2016,$F35,$F35-CY35) -> 0 | DA35: =IF($E35>=2018,0,IF($AE35-2017<=0,CZ35,IF($M35="I",0.25*$K35,IF($M35="II",0.125*$K35,IF($M35="III",0.0625*$K35,IF($M35="IV",0.05*$K35,$K35)))))) -> 0 | DB35: =CY35+DA35 -> 0 | DC35: =IF($E35>=2016,$F35,$F35-DB35) -> 0 | DD35: =IF($E35>=2019,0,IF($AE35-2018<=0,DC35,IF($M35="I",0.25*$K35,IF($M35="II",0.125*$K35,IF($M35="III",0.0625*$K35,IF($M35="IV",0.05*$K35,$K35)))))) -> 0 | DE35: =DB35+DD35 -> 0 | DF35: =IF($E35>=2019,$F35,$F35-DE35) -> 0 | DG35: =IF($E35>=2020,0,IF($AE35-2019<=0,DF35,IF($M35="I",0.25*$K35,IF($M35="II",0.125*$K35,IF($M35="III",0.0625*$K35,IF($M35="IV",0.05*$K35,$K35)))))) -> 0 | DH35: =DE35+DG35 -> 0 | DI35: =IF($E35>=2020,$F35,$F35-DH35) -> 0 | DJ35: =IF($E35>=2020,0,IF($AE35-2019<=0,DI35,IF($M35="I",0.25*$K35,IF($M35="II",0.125*$K35,IF($M35="III",0.0625*$K35,IF($M35="IV",0.05*$K35,$K35)))))) -> 0 | DK35: =DH35+DJ35 -> 0 | DL35: =IF($E35>=2021,$F35,$F35-DK35) -> 0 | DM35: =IF($E35>=2022,0,IF($AE35-2021<=0,DL35,IF($M35=1,0.05*$F35*BG35/12,0.1*$F35*BG35/12))) -> 0 | DN35: =DK35+DM35 -> 0 | DO35: =IF($E35>=2022,$F35,$F35-DN35) -> 0
B36: Kelompok I | DF36: =IF($E36>=2019,$F36,$F36-DE36) -> 0 | DH36: =DE36+DG36 -> 0 | DI36: =IF($E36>=2020,$F36,$F36-DH36) -> 0 | DK36: =DH36+DJ36 -> 0 | DL36: =IF($E36>=2021,$F36,$F36-DK36) -> 0 | DN36: =DK36+DM36 -> 0 | DO36: =IF($E36>=2021,$F36,$F36-DN36) -> 0
A37: 1 | B37: Komputer 4 UNIT | C37: I | D37: Mei | E37: 2017 | F37: =2200000+9000000 -> 11200000 | G37: =IF(C37="I",4,IF(C37="II",8,16)) -> 4 | H37: =IF(E37<=1995,1994+1-E37,0) -> 0 | I37: =IF(H37=0,G37,G37-H37) -> 4 | J37: =F37-K37 -> 0 | K37: =IF(E37>=1995,F37,F37*(1-L37)^H37) -> 11200000 | L37: =IF(C37="I",0.5,IF(C37="II",0.25,0.1)) -> 0.5 | M37: =IF(E37>=1995,C37,IF(AND(I37>1,I37<6),"I",IF(AND(I37>=6,I37<12),"II",IF(I37>=12,"III","-")))) -> I | N37: =IF($E37>=1996,0,IF($AE37=N$25,K37,IF($M37="I",0.25*$K37,IF($M37="II",0.125*$K37,IF($M37="III",0.0625*$K37,IF($M37="IV",0.05*$K37,$K37)))))) -> 0 | O37: =N37+J37 -> 0 | P37: =IF($E37>=1996,$F37,$F37-O37) -> 11200000 | Q37: =IF($E37>=1997,0,IF($AE37-1996<=0,P37,IF($M37="I",0.25*$K37,IF($M37="II",0.125*$K37,IF($M37="III",0.0625*$K37,IF($M37="IV",0.05*$K37,$K37)))))) -> 0 | R37: =Q37+O37 -> 0 | S37: =IF($E37>=1997,$F37,$F37-R37) -> 11200000 | T37: =IF($E37>=1998,0,IF($AE37-1997<=0,S37,IF($M37="I",0.25*$K37,IF($M37="II",0.125*$K37,IF($M37="III",0.0625*$K37,IF($M37="IV",0.05*$K37,$K37)))))) -> 0 | U37: =T37+R37 -> 0 | V37: =IF($E37>=1998,$F37,$F37-U37) -> 11200000 | W37: =IF($E37>=1999,0,IF($AE37-1998<=0,V37,IF($M37="I",0.25*$K37,IF($M37="II",0.125*$K37,IF($M37="III",0.0625*$K37,IF($M37="IV",0.05*$K37,$K37)))))) -> 0 | X37: =W37+U37 -> 0 | Y37: =IF($E37>=1999,$F37,$F37-X37) -> 11200000 | Z37: =IF($E37>=2000,0,IF($AE37-1999<=0,Y37,IF($M37="I",0.25*$K37,IF($M37="II",0.125*$K37,IF($M37="III",0.0625*$K37,IF($M37="IV",0.05*$K37,$K37)))))) -> 0 | AA37: =Z37+X37 -> 0 | AB37: =IF($E37>=2000,$F37,$F37-AA37) -> 11200000 | AC37: =IF($E37>=2001,0,IF($AE37-2000<=0,AB37,IF($M37="I",0.25*$K37,IF($M37="II",0.125*$K37,IF($M37="III",0.0625*$K37,IF($M37="IV",0.05*$K37,$K37)))))) -> 0 | AD37: =AC37+AA37 -> 0 | AE37: =IF(AND($E37<=1994,$M37="I"),1995+3,IF(AND($E37<=1994,$M37="II"),1995+7,IF(AND($E37<=1994,$M37="III"),1995+15,IF(AND($E37<=1994,$M37="IV"),1995+19,IF($M37="I",$E37+3,IF($M37="II",$E37+7,IF($M37="III",$E37+15,IF($M37="IV",$E37+19,1995)))))))) -> 2020 | AF37: =IF($E37>=2001,$F37,$F37-AD37) -> 11200000 | AG37: =IF($E37>=2002,0,IF($AE37-2001<=0,AF37,IF($M37="I",0.25*$K37*AM37/12,IF($M37="II",0.125*$K37*AM37/12,IF($M37="III",0.0625*$K37*AM37/12,IF($M37="IV",0.05*$K37*AM37/12,$K37)))))) -> 0 | AH37: =AG37+AD37 -> 0 | AI37: =IF($E37>=2002,$F37,$F37-AH37) -> 11200000 | AJ37: =IF($E37>=2003,0,IF($AE37-2002<=0,AI37,IF($M37="I",0.25*$K37*AN37/12,IF($M37="II",0.125*$K37*AN37/12,IF($M37="III",0.0625*$K37*AN37/12,IF($M37="IV",0.05*$K37*AN37/12,$K37)))))) -> 0 | AK37: =AJ37+AH37 -> 0 | AL37: =VLOOKUP(D37,$C$11:$D$22,2,0) -> 5 | AM37: =IF(E37>=2001,13-AL37,12) -> 8 | AN37: =IF(E37>=2002,13-AL37,12) -> 8 | AO37: =IF(E37>=2003,13-AL37,12) -> 8 | AP37: =IF(E37>=2004,13-AL37,12) -> 8 | AQ37: =IF(E37>=2005,13-AL37,12) -> 8 | AR37: =IF(E37>=2006,13-AL37,12) -> 8 | AS37: =IF(E37>=2007,13-AL37,12) -> 8 | AT37: =IF(E37>=2008,13-AL37,12) -> 8 | AU37: =IF(E37>=2009,13-AL37,12) -> 8 | AV37: =IF(E37>=2010,13-AL37,12) -> 8 | AW37: =IF(E37>=2011,13-AL37,12) -> 8 | AX37: =IF(E37>=2012,13-AL37,12) -> 8 | AY37: =IF(E37>=2013,13-AL37,12) -> 8 | AZ37: =IF(E37>=2014,13-AL37,12) -> 8 | BA37: =IF(E37>=2015,13-AL37,12) -> 8 | BB37: =IF(E37>=2016,13-AL37,12) -> 8 | BC37: =IF(E37>=2017,13-AL37,12) -> 8 | BD37: =IF(E37>=2018,13-AL37,12) -> 12 | BE37: =IF(E37>=2019,13-AL37,12) -> 12 | BF37: =IF(E37>=2020,13-AL37,12) -> 12 | BG37: =IF(E37>=2021,13-AL37,12) -> 12 | BH37: =IF($E37>=2003,$F37,$F37-AK37) -> 11200000 | BI37: =IF($E37>=2004,0,IF($AE37-2003<=0,BH37,IF($M37="I",0.25*$K37*AO37/12,IF($M37="II",0.125*$K37*AO37/12,IF($M37="III",0.0625*$K37*AO37/12,IF($M37="IV",0.05*$K37*AO37/12,$K37)))))) -> 0 | BJ37: =BI37+AK37 -> 0 | BK37: =IF($E37>=2004,$F37,$F37-BJ37) -> 11200000 | BL37: =IF($E37>=2005,0,IF($AE37-2004<=0,BK37,IF($M37="I",0.25*$K37*AP37/12,IF($M37="II",0.125*$K37*AP37/12,IF($M37="III",0.0625*$K37*AP37/12,IF($M37="IV",0.05*$K37*AP37/12,$K37)))))) -> 0 | BM37: =BJ37+BL37 -> 0 | BN37: =IF($E37>=2005,$F37,$F37-BM37) -> 11200000 | BO37: =IF($E37>=2006,0,IF($AE37-2005<=0,BN37,IF($M37="I",0.25*$K37*AQ37/12,IF($M37="II",0.125*$K37*AQ37/12,IF($M37="III",0.0625*$K37*AQ37/12,IF($M37="IV",0.05*$K37*AQ37/12,$K37)))))) -> 0 | BP37: =BM37+BO37 -> 0 | BQ37: =IF($E37>=2006,$F37,$F37-BP37) -> 11200000 | BR37: =IF($E37>=2007,0,IF($AE37-2006<=0,BQ37,IF($M37="I",0.25*$K37*AR37/12,IF($M37="II",0.125*$K37*AR37/12,IF($M37="III",0.0625*$K37*AR37/12,IF($M37="IV",0.05*$K37*AR37/12,$K37)))))) -> 0 | BS37: =BP37+BR37 -> 0 | BT37: =IF($E37>=2007,$F37,$F37-BS37) -> 11200000 | BU37: =IF($E37>=2008,0,IF($AE37-2007<=0,BT37,IF($M37="I",0.25*$K37*AS37/12,IF($M37="II",0.125*$K37*AS37/12,IF($M37="III",0.0625*$K37*AS37/12,IF($M37="IV",0.05*$K37*AS37/12,$K37)))))) -> 0 | BV37: =BS37+BU37 -> 0 | BW37: =IF($E37>=2008,$F37,$F37-BV37) -> 11200000 | BX37: =IF($E37>=2009,0,IF($AE37-2008<=0,BW37,IF($M37="I",0.25*$K37*AT37/12,IF($M37="II",0.125*$K37*AT37/12,IF($M37="III",0.0625*$K37*AT37/12,IF($M37="IV",0.05*$K37*AT37/12,$K37)))))) -> 0 | BY37: =BV37+BX37 -> 0 | BZ37: =IF($E37>=2009,$F37,$F37-BY37) -> 11200000 | CA37: =IF($E37>=2010,0,IF($AE37-2009<=0,BZ37,IF($M37="I",0.25*$K37*AU37/12,IF($M37="II",0.125*$K37*AU37/12,IF($M37="III",0.0625*$K37*AU37/12,IF($M37="IV",0.05*$K37*AU37/12,$K37)))))) -> 0 | CB37: =BY37+CA37 -> 0 | CC37: =IF($E37>=2010,$F37,$F37-CB37) -> 11200000 | CD37: =IF($E37>=2011,0,IF($AE37-2010<=0,CC37,IF($M37="I",0.25*$K37*AV37/12,IF($M37="II",0.125*$K37*AV37/12,IF($M37="III",0.0625*$K37*AV37/12,IF($M37="IV",0.05*$K37*AV37/12,$K37)))))) -> 0 | CE37: =CB37+CD37 -> 0 | CF37: =IF($E37>=2011,$F37,$F37-CE37) -> 11200000 | CG37: =IF($E37>=2012,0,IF($AE37-2011<=0,CF37,IF($M37="I",0.25*$K37*AW37/12,IF($M37="II",0.125*$K37*AW37/12,IF($M37="III",0.0625*$K37*AW37/12,IF($M37="IV",0.05*$K37*AW37/12,$K37)))))) -> 0 | CH37: =CE37+CG37 -> 0 | CI37: =IF($E37>=2012,$F37,$F37-CH37) -> 11200000 | CK37: GL | CL37: =IF($E37>=2013,0,IF($AE37-2012<=0,CI37,IF($M37="I",0.25*$K37*AX37/12,IF($M37="II",0.125*$K37*AX37/12,IF($M37="III",0.0625*$K37*AX37/12,IF($M37="IV",0.05*$K37*AX37/12,$K37)))))) -> 0 | CM37: =CH37+CL37 -> 0 | CN37: =IF($E37>=2013,$F37,$F37-CM37) -> 11200000 | CO37: =IF($E37>=2014,0,IF($AE37-2013<=0,CN37,IF($M37="I",0.25*$K37*AY37/12,IF($M37="II",0.125*$K37*AY37/12,IF($M37="III",0.0625*$K37*AY37/12,IF($M37="IV",0.05*$K37*AY37/12,$K37)))))) -> 0 | CP37: =CM37+CO37 -> 0 | CQ37: =IF($E37>=2014,$F37,$F37-CP37) -> 11200000 | CR37: =IF($E37>=2015,0,IF($AE37-2014<=0,CQ37,IF($M37="I",0.25*$K37*AZ37/12,IF($M37="II",0.125*$K37*AZ37/12,IF($M37="III",0.0625*$K37*AZ37/12,IF($M37="IV",0.05*$K37*AZ37/12,$K37)))))) -> 0 | CS37: =CP37+CR37 -> 0 | CT37: =IF($E37>=2015,$F37,$F37-CS37) -> 11200000 | CU37: =IF($E37>=2016,0,IF($AE37-2015<=0,CT37,IF($M37="I",0.25*$K37*BA37/12,IF($M37="II",0.125*$K37*BA37/12,IF($M37="III",0.0625*$K37*BA37/12,IF($M37="IV",0.05*$K37*BA37/12,$K37)))))) -> 0 | CV37: =CS37+CU37 -> 0 | CW37: =IF($E37>=2016,$F37,$F37-CV37) -> 11200000 | CX37: =IF($E37>=2017,0,IF($AE37-2016<=0,CW37,IF($M37="I",0.25*$K37*BB37/12,IF($M37="II",0.125*$K37*BB37/12,IF($M37="III",0.0625*$K37*BB37/12,IF($M37="IV",0.05*$K37*BB37/12,$K37)))))) -> 0 | CY37: =CV37+CX37 -> 0 | CZ37: =IF($E37>=2017,$F37,$F37-CY37) -> 11200000 | DA37: =IF($E37>=2018,0,IF($AE37-2017<=0,CZ37,IF($M37="I",0.25*$K37*BC37/12,IF($M37="II",0.125*$K37*BC37/12,IF($M37="III",0.0625*$K37*BC37/12,IF($M37="IV",0.05*$K37*BC37/12,$K37)))))) -> 1866666.7 | DB37: =CY37+DA37 -> 1866666.7 | DC37: =IF($E37>=2018,$F37,$F37-DB37) -> 9333333.3 | DD37: =IF($E37>=2019,0,IF($AE37-2018<=0,DC37,IF($M37="I",0.25*$K37*BD37/12,IF($M37="II",0.125*$K37*BD37/12,IF($M37="III",0.0625*$K37*BD37/12,IF($M37="IV",0.05*$K37*BD37/12,$K37)))))) -> 2800000 | DE37: =DB37+DD37 -> 4666666.7 | DF37: =IF($E37>=2019,$F37,$F37-DE37) -> 6533333.3 | DG37: =IF($E37>=2020,0,IF($AE37-2019<=0,DF37,IF($M37="I",0.25*$K37*BE37/12,IF($M37="II",0.125*$K37*BE37/12,IF($M37="III",0.0625*$K37*BE37/12,IF($M37="IV",0.05*$K37*BE37/12,$K37)))))) -> 2800000 | DH37: =DE37+DG37 -> 7466666.7 | DI37: =IF($E37>=2020,$F37,$F37-DH37) -> 3733333.3 | DJ37: =IF($E37>=2021,0,IF($AE37-2020<=0,DI37,IF($M37="I",0.25*$K37*BF37/12,IF($M37="II",0.125*$K37*BF37/12,IF($M37="III",0.0625*$K37*BF37/12,IF($M37="IV",0.05*$K37*BF37/12,$K37)))))) -> 3733333.3 | DK37: =DH37+DJ37 -> 11200000 | DL37: =IF($E37>=2021,$F37,$F37-DK37) -> 0 | DM37: =IF($E37>=2022,0,IF($AE37-2021<=0,DL37,IF($M37="I",0.25*$K37*BG37/12,IF($M37="II",0.125*$K37*BG37/12,IF($M37="III",0.0625*$K37*BG37/12,IF($M37="IV",0.05*$K37*BG37/12,$K37)))))) -> 0 | DN37: =DK37+DM37 -> 11200000 | DO37: =IF($E37>=2022,$F37,$F37-DN37) -> 0 | DQ37: =+DN37+DP37 -> 11200000 | DR37: =F37-DQ37 -> 0 | DS37: 0 | DT37: =+DQ37+DS37 -> 11200000 | DU37: =+F37-DT37 -> 0
A38: =A37+1 -> 2 | B38: PRINTER | C38: I | D38: Jun | E38: 2018 | F38: 1631818 | G38: =IF(C38="I",4,IF(C38="II",8,16)) -> 4 | H38: =IF(E38<=1995,1994+1-E38,0) -> 0 | I38: =IF(H38=0,G38,G38-H38) -> 4 | J38: =F38-K38 -> 0 | K38: =IF(E38>=1995,F38,F38*(1-L38)^H38) -> 1631818 | L38: =IF(C38="I",0.5,IF(C38="II",0.25,0.1)) -> 0.5 | M38: =IF(E38>=1995,C38,IF(AND(I38>1,I38<6),"I",IF(AND(I38>=6,I38<12),"II",IF(I38>=12,"III","-")))) -> I | N38: =IF($E38>=1996,0,IF($AE38=N$25,K38,IF($M38="I",0.25*$K38,IF($M38="II",0.125*$K38,IF($M38="III",0.0625*$K38,IF($M38="IV",0.05*$K38,$K38)))))) -> 0 | O38: =N38+J38 -> 0 | P38: =IF($E38>=1996,$F38,$F38-O38) -> 1631818 | Q38: =IF($E38>=1997,0,IF($AE38-1996<=0,P38,IF($M38="I",0.25*$K38,IF($M38="II",0.125*$K38,IF($M38="III",0.0625*$K38,IF($M38="IV",0.05*$K38,$K38)))))) -> 0 | R38: =Q38+O38 -> 0 | S38: =IF($E38>=1997,$F38,$F38-R38) -> 1631818 | T38: =IF($E38>=1998,0,IF($AE38-1997<=0,S38,IF($M38="I",0.25*$K38,IF($M38="II",0.125*$K38,IF($M38="III",0.0625*$K38,IF($M38="IV",0.05*$K38,$K38)))))) -> 0 | U38: =T38+R38 -> 0 | V38: =IF($E38>=1998,$F38,$F38-U38) -> 1631818 | W38: =IF($E38>=1999,0,IF($AE38-1998<=0,V38,IF($M38="I",0.25*$K38,IF($M38="II",0.125*$K38,IF($M38="III",0.0625*$K38,IF($M38="IV",0.05*$K38,$K38)))))) -> 0 | X38: =W38+U38 -> 0 | Y38: =IF($E38>=1999,$F38,$F38-X38) -> 1631818 | Z38: =IF($E38>=2000,0,IF($AE38-1999<=0,Y38,IF($M38="I",0.25*$K38,IF($M38="II",0.125*$K38,IF($M38="III",0.0625*$K38,IF($M38="IV",0.05*$K38,$K38)))))) -> 0 | AA38: =Z38+X38 -> 0 | AB38: =IF($E38>=2000,$F38,$F38-AA38) -> 1631818 | AC38: =IF($E38>=2001,0,IF($AE38-2000<=0,AB38,IF($M38="I",0.25*$K38,IF($M38="II",0.125*$K38,IF($M38="III",0.0625*$K38,IF($M38="IV",0.05*$K38,$K38)))))) -> 0 | AD38: =AC38+AA38 -> 0 | AE38: =IF(AND($E38<=1994,$M38="I"),1995+3,IF(AND($E38<=1994,$M38="II"),1995+7,IF(AND($E38<=1994,$M38="III"),1995+15,IF(AND($E38<=1994,$M38="IV"),1995+19,IF($M38="I",$E38+3,IF($M38="II",$E38+7,IF($M38="III",$E38+15,IF($M38="IV",$E38+19,1995)))))))) -> 2021 | AF38: =IF($E38>=2001,$F38,$F38-AD38) -> 1631818 | AG38: =IF($E38>=2002,0,IF($AE38-2001<=0,AF38,IF($M38="I",0.25*$K38*AM38/12,IF($M38="II",0.125*$K38*AM38/12,IF($M38="III",0.0625*$K38*AM38/12,IF($M38="IV",0.05*$K38*AM38/12,$K38)))))) -> 0 | AH38: =AG38+AD38 -> 0 | AI38: =IF($E38>=2002,$F38,$F38-AH38) -> 1631818 | AJ38: =IF($E38>=2003,0,IF($AE38-2002<=0,AI38,IF($M38="I",0.25*$K38*AN38/12,IF($M38="II",0.125*$K38*AN38/12,IF($M38="III",0.0625*$K38*AN38/12,IF($M38="IV",0.05*$K38*AN38/12,$K38)))))) -> 0 | AK38: =AJ38+AH38 -> 0 | AL38: =VLOOKUP(D38,$C$11:$D$22,2,0) -> 6 | AM38: =IF(E38>=2001,13-AL38,12) -> 7 | AN38: =IF(E38>=2002,13-AL38,12) -> 7 | AO38: =IF(E38>=2003,13-AL38,12) -> 7 | AP38: =IF(E38>=2004,13-AL38,12) -> 7 | AQ38: =IF(E38>=2005,13-AL38,12) -> 7 | AR38: =IF(E38>=2006,13-AL38,12) -> 7 | AS38: =IF(E38>=2007,13-AL38,12) -> 7 | AT38: =IF(E38>=2008,13-AL38,12) -> 7 | AU38: =IF(E38>=2009,13-AL38,12) -> 7 | AV38: =IF(E38>=2010,13-AL38,12) -> 7 | AW38: =IF(E38>=2011,13-AL38,12) -> 7 | AX38: =IF(E38>=2012,13-AL38,12) -> 7 | AY38: =IF(E38>=2013,13-AL38,12) -> 7 | AZ38: =IF(E38>=2014,13-AL38,12) -> 7 | BA38: =IF(E38>=2015,13-AL38,12) -> 7 | BB38: =IF(E38>=2016,13-AL38,12) -> 7 | BC38: =IF(E38>=2017,13-AL38,12) -> 7 | BD38: =IF(E38>=2018,13-AL38,12) -> 7 | BE38: =IF(E38>=2019,13-AL38,12) -> 12 | BF38: =IF(E38>=2020,13-AL38,12) -> 12 | BG38: =IF(E38>=2021,13-AL38,12) -> 12 | BH38: =IF($E38>=2003,$F38,$F38-AK38) -> 1631818 | BI38: =IF($E38>=2004,0,IF($AE38-2003<=0,BH38,IF($M38="I",0.25*$K38*AO38/12,IF($M38="II",0.125*$K38*AO38/12,IF($M38="III",0.0625*$K38*AO38/12,IF($M38="IV",0.05*$K38*AO38/12,$K38)))))) -> 0 | BJ38: =BI38+AK38 -> 0 | BK38: =IF($E38>=2004,$F38,$F38-BJ38) -> 1631818 | BL38: =IF($E38>=2005,0,IF($AE38-2004<=0,BK38,IF($M38="I",0.25*$K38*AP38/12,IF($M38="II",0.125*$K38*AP38/12,IF($M38="III",0.0625*$K38*AP38/12,IF($M38="IV",0.05*$K38*AP38/12,$K38)))))) -> 0 | BM38: =BJ38+BL38 -> 0 | BN38: =IF($E38>=2005,$F38,$F38-BM38) -> 1631818 | BO38: =IF($E38>=2006,0,IF($AE38-2005<=0,BN38,IF($M38="I",0.25*$K38*AQ38/12,IF($M38="II",0.125*$K38*AQ38/12,IF($M38="III",0.0625*$K38*AQ38/12,IF($M38="IV",0.05*$K38*AQ38/12,$K38)))))) -> 0 | BP38: =BM38+BO38 -> 0 | BQ38: =IF($E38>=2006,$F38,$F38-BP38) -> 1631818 | BR38: =IF($E38>=2007,0,IF($AE38-2006<=0,BQ38,IF($M38="I",0.25*$K38*AR38/12,IF($M38="II",0.125*$K38*AR38/12,IF($M38="III",0.0625*$K38*AR38/12,IF($M38="IV",0.05*$K38*AR38/12,$K38)))))) -> 0 | BS38: =BP38+BR38 -> 0 | BT38: =IF($E38>=2007,$F38,$F38-BS38) -> 1631818 | BU38: =IF($E38>=2008,0,IF($AE38-2007<=0,BT38,IF($M38="I",0.25*$K38*AS38/12,IF($M38="II",0.125*$K38*AS38/12,IF($M38="III",0.0625*$K38*AS38/12,IF($M38="IV",0.05*$K38*AS38/12,$K38)))))) -> 0 | BV38: =BS38+BU38 -> 0 | BW38: =IF($E38>=2008,$F38,$F38-BV38) -> 1631818 | BX38: =IF($E38>=2009,0,IF($AE38-2008<=0,BW38,IF($M38="I",0.25*$K38*AT38/12,IF($M38="II",0.125*$K38*AT38/12,IF($M38="III",0.0625*$K38*AT38/12,IF($M38="IV",0.05*$K38*AT38/12,$K38)))))) -> 0 | BY38: =BV38+BX38 -> 0 | BZ38: =IF($E38>=2009,$F38,$F38-BY38) -> 1631818 | CA38: =IF($E38>=2010,0,IF($AE38-2009<=0,BZ38,IF($M38="I",0.25*$K38*AU38/12,IF($M38="II",0.125*$K38*AU38/12,IF($M38="III",0.0625*$K38*AU38/12,IF($M38="IV",0.05*$K38*AU38/12,$K38)))))) -> 0 | CB38: =BY38+CA38 -> 0 | CC38: =IF($E38>=2010,$F38,$F38-CB38) -> 1631818 | CD38: =IF($E38>=2011,0,IF($AE38-2010<=0,CC38,IF($M38="I",0.25*$K38*AV38/12,IF($M38="II",0.125*$K38*AV38/12,IF($M38="III",0.0625*$K38*AV38/12,IF($M38="IV",0.05*$K38*AV38/12,$K38)))))) -> 0 | CE38: =CB38+CD38 -> 0 | CF38: =IF($E38>=2011,$F38,$F38-CE38) -> 1631818 | CG38: =IF($E38>=2012,0,IF($AE38-2011<=0,CF38,IF($M38="I",0.25*$K38*AW38/12,IF($M38="II",0.125*$K38*AW38/12,IF($M38="III",0.0625*$K38*AW38/12,IF($M38="IV",0.05*$K38*AW38/12,$K38)))))) -> 0 | CH38: =CE38+CG38 -> 0 | CI38: =IF($E38>=2012,$F38,$F38-CH38) -> 1631818 | CK38: GL | CL38: =IF($E38>=2013,0,IF($AE38-2012<=0,CI38,IF($M38="I",0.25*$K38*AX38/12,IF($M38="II",0.125*$K38*AX38/12,IF($M38="III",0.0625*$K38*AX38/12,IF($M38="IV",0.05*$K38*AX38/12,$K38)))))) -> 0 | CM38: =CH38+CL38 -> 0 | CN38: =IF($E38>=2013,$F38,$F38-CM38) -> 1631818 | CO38: =IF($E38>=2014,0,IF($AE38-2013<=0,CN38,IF($M38="I",0.25*$K38*AY38/12,IF($M38="II",0.125*$K38*AY38/12,IF($M38="III",0.0625*$K38*AY38/12,IF($M38="IV",0.05*$K38*AY38/12,$K38)))))) -> 0 | CP38: =CM38+CO38 -> 0 | CQ38: =IF($E38>=2014,$F38,$F38-CP38) -> 1631818 | CR38: =IF($E38>=2015,0,IF($AE38-2014<=0,CQ38,IF($M38="I",0.25*$K38*AZ38/12,IF($M38="II",0.125*$K38*AZ38/12,IF($M38="III",0.0625*$K38*AZ38/12,IF($M38="IV",0.05*$K38*AZ38/12,$K38)))))) -> 0 | CS38: =CP38+CR38 -> 0 | CT38: =IF($E38>=2015,$F38,$F38-CS38) -> 1631818 | CU38: =IF($E38>=2016,0,IF($AE38-2015<=0,CT38,IF($M38="I",0.25*$K38*BA38/12,IF($M38="II",0.125*$K38*BA38/12,IF($M38="III",0.0625*$K38*BA38/12,IF($M38="IV",0.05*$K38*BA38/12,$K38)))))) -> 0 | CV38: =CS38+CU38 -> 0 | CW38: =IF($E38>=2016,$F38,$F38-CV38) -> 1631818 | CX38: =IF($E38>=2017,0,IF($AE38-2016<=0,CW38,IF($M38="I",0.25*$K38*BB38/12,IF($M38="II",0.125*$K38*BB38/12,IF($M38="III",0.0625*$K38*BB38/12,IF($M38="IV",0.05*$K38*BB38/12,$K38)))))) -> 0 | CY38: =CV38+CX38 -> 0 | CZ38: =IF($E38>=2017,$F38,$F38-CY38) -> 1631818 | DA38: =IF($E38>=2018,0,IF($AE38-2017<=0,CZ38,IF($M38="I",0.25*$K38*BC38/12,IF($M38="II",0.125*$K38*BC38/12,IF($M38="III",0.0625*$K38*BC38/12,IF($M38="IV",0.05*$K38*BC38/12,$K38)))))) -> 0 | DB38: =CY38+DA38 -> 0 | DC38: =IF($E38>=2018,$F38,$F38-DB38) -> 1631818 | DD38: =IF($E38>=2019,0,IF($AE38-2018<=0,DC38,IF($M38="I",0.25*$K38*BD38/12,IF($M38="II",0.125*$K38*BD38/12,IF($M38="III",0.0625*$K38*BD38/12,IF($M38="IV",0.05*$K38*BD38/12,$K38)))))) -> 237973.46 | DE38: =DB38+DD38 -> 237973.46 | DF38: =IF($E38>=2019,$F38,$F38-DE38) -> 1393844.5 | DG38: =IF($E38>=2020,0,IF($AE38-2019<=0,DF38,IF($M38="I",0.25*$K38*BE38/12,IF($M38="II",0.125*$K38*BE38/12,IF($M38="III",0.0625*$K38*BE38/12,IF($M38="IV",0.05*$K38*BE38/12,$K38)))))) -> 407954.5 | DH38: =DE38+DG38 -> 645927.96 | DI38: =IF($E38>=2020,$F38,$F38-DH38) -> 985890.04 | DJ38: =IF($E38>=2021,0,IF($AE38-2020<=0,DI38,IF($M38="I",0.25*$K38*BF38/12,IF($M38="II",0.125*$K38*BF38/12,IF($M38="III",0.0625*$K38*BF38/12,IF($M38="IV",0.05*$K38*BF38/12,$K38)))))) -> 407954.5 | DK38: =DH38+DJ38 -> 1053882.5 | DL38: =IF($E38>=2021,$F38,$F38-DK38) -> 577935.54 | DM38: 407954.5 | DN38: =DK38+DM38 -> 1461837 | DO38: =IF($E38>=2022,$F38,$F38-DN38) -> 169981.04 | DP38: =F38*5/48 -> 169981.04 | DQ38: =+DN38+DP38 -> 1631818 | DR38: =F38-DQ38 -> 0 | DS38: 0 | DT38: =+DQ38+DS38 -> 1631818 | DU38: =+F38-DT38 -> 0 | DX38: =F38/4 -> 407954.5
